Workbook

Sheet Encounter Sheet
B2: GM Encounter Sheet | H2: Round # | L2: Scene Notes
H3: 1
B5: Active Combatant List | L5: Light Screen x2
B6: Enemy 1 | C6: Combatant Name | D6: Combatant Category | E6: Current HP | F6: Link to full Character Sheet
C7: Mismagius | D7: Boss (Alpha) | E7: 19
C8: Current Buffs & Notes | F8: # of HP Bars Remaining | G8: TRUE | H8: FALSE | I8: FALSE | J8: FALSE
C9: Current Debuffs | D9: Dazed | F9: Turns left this Round | G9: FALSE | H9: FALSE | I9: FALSE
B11: Enemy 2 | C11: Combatant Name | D11: Combatant Category | E11: Current HP | F11: Link to full Character Sheet
C12: Golett 1 | E12: 1
C13: Current Buffs & Notes | F13: # of HP Bars Remaining | G13: TRUE | H13: FALSE | I13: FALSE | J13: FALSE
C14: Current Debuffs | F14: Turns left this Round | G14: FALSE | H14: FALSE | I14: FALSE
B16: Enemy 3 | C16: Combatant Name | D16: Combatant Category | E16: Current HP | F16: Link to full Character Sheet
C17: Gollet 2 | E17: 1
C18: Current Buffs & Notes | D18: Offensive | F18: # of HP Bars Remaining | G18: TRUE | H18: FALSE | I18: FALSE | J18: FALSE | L18: Mini Damage Calculator
C19: Current Debuffs | F19: Turns left this Round | G19: FALSE | H19: FALSE | I19: FALSE
B21: Enemy 4 | C21: Combatant Name | D21: Combatant Category | E21: Current HP | F21: Link to full Character Sheet | L21: Starting HP | M21: Damage Dealt | N21: Resolving HP
C22: Gollet 3 | E22: 1 | N22: =IFERROR(IF(L26="HP Loss",MINUS(L22,M22),MINUS(L22,MULTIPLY(L26,MINUS(M22,SUM(M26,N26))))),"--") -> 0
C23: Current Buffs & Notes | F23: # of HP Bars Remaining | G23: TRUE | H23: FALSE | I23: FALSE | J23: FALSE
C24: Current Debuffs | D24: Dazed | F24: Turns left this Round | G24: TRUE | H24: FALSE | I24: FALSE | L24: Attack's Effectiveness | M24: Relevant Defense Stat | N24: Damage Reduction
B26: Enemy 5 | C26: Combatant Name | D26: Combatant Category | E26: Current HP | F26: Link to full Character Sheet | L26: 1
C27: Shuppet 1 | E27: 3
C28: Current Buffs & Notes | F28: # of HP Bars Remaining | G28: TRUE | H28: FALSE | I28: FALSE | J28: FALSE | L28: Type Effectivness Calculator
C29: Current Debuffs | F29: Turns left this Round | G29: FALSE | H29: FALSE | I29: FALSE
B31: Enemy 6 | C31: Combatant Name | D31: Combatant Category | E31: Current HP | F31: Link to full Character Sheet | L31: Attack Type | M31: Defender Type 1 | N31: Defender Type 2
C32: Shuppet 2 | E32: 1
C33: Current Buffs & Notes | F33: # of HP Bars Remaining | G33: FALSE | H33: FALSE | I33: FALSE | J33: FALSE | L33: =IFERROR( IFS( IF( NOT(ISBLANK(N32)), MULTIPLY( HLOOKUP(L32,Calculations!$F$1:$X$20,MATCH(M32,Calculations!$F$1:$F$20),FALSE), HLOOKUP(L32,Calculations!$F$1:$X$20,MATCH(N32,Calculations!$F$1:$F$20),FALSE)), HLOOKUP(L32,Calculations!$F$1:$X$20,MATCH(M32,Calculations!$F$1:$F$20),FALSE))=0.25, "Double Resist! [.25x]", IF( NOT(ISBLANK(N32)), MULTIPLY( HLOOKUP(L32,Calculations!$F$1:$X$20,MATCH(M32,Calculations!$F$1:$F$20),FALSE), HLOOKUP(L32,Calculations!$F$1:$X$20,MATCH(N32,Calculations!$F$1:$F$20),FALSE)), HLOOKUP(L32,Calculations!$F$1:$X$20,MATCH(M32,Calculations!$F$1:$F$20),FALSE))=0.5, "Resist! [.5x]", IF( NOT(ISBLANK(N32)), MULTIPLY( HLOOKUP(L32,Calculations!$F$1:$X$20,MATCH(M32,Calculations!$F$1:$F$20),FALSE), HLOOKUP(L32,Calculations!$F$1:$X$20,MATCH(N32,Calculations!$F$1:$F$20),FALSE)), HLOOKUP(L32,Calculations!$F$1:$X$20,MATCH(M32,Calculations!$F$1:$F$20),FALSE))=1, "Neutral Damage [1x]", IF( NOT(ISBLANK(N32)), MULTIPLY( HLOOKUP(L32,Calculations!$F$1:$X$20,MATCH(M32,Calculations!$F$1:$F$20),FALSE), HLOOKUP(L32,Calculations!$F$1:$X$20,MATCH(N32,Calculations!$F$1:$F$20),FALSE)), HLOOKUP(L32,Calculations!$F$1:$X$20,MATCH(M32,Calculations!$F$1:$F$20),FALSE))=2, "Super Effective! [1.5x]", IF( NOT(ISBLANK(N32)), MULTIPLY( HLOOKUP(L32,Calculations!$F$1:$X$20,MATCH(M32,Calculations!$F$1:$F$20),FALSE), HLOOKUP(L32,Calculations!$F$1:$X$20,MATCH(N32,Calculations!$F$1:$F$20),FALSE)), HLOOKUP(L32,Calculations!$F$1:$X$20,MATCH(M32,Calculations!$F$1:$F$20),FALSE))=4, "Double Effectiveness! [2x]", IF( NOT(ISBLANK(N32)), MULTIPLY( HLOOKUP(L32,Calculations!$F$1:$X$20,MATCH(M32,Calculations!$F$1:$F$20),FALSE), HLOOKUP(L32,Calculations!$F$1:$X$20,MATCH(N32,Calculations!$F$1:$F$20),FALSE)), HLOOKUP(L32,Calculations!$F$1:$X$20,MATCH(M32,Calculations!$F$1:$F$20),FALSE))=0, "Immune! [0x]"), "Slot some types to get some info!") -> Slot some types to get some info!
C34: Current Debuffs | F34: Turns left this Round | G34: FALSE | H34: FALSE | I34: FALSE
B36: Enemy 7 | C36: Combatant Name | D36: Combatant Category | E36: Current HP | F36: Link to full Character Sheet
C37: Shuppet 3 | E37: 3
C38: Current Buffs & Notes | D38: Drowsy | F38: # of HP Bars Remaining | G38: FALSE | H38: FALSE | I38: FALSE | J38: FALSE
C39: Current Debuffs | F39: Turns left this Round | G39: FALSE | H39: FALSE | I39: FALSE
B41: Enemy 8 | C41: Combatant Name | D41: Combatant Category | E41: Current HP | F41: Link to full Character Sheet
C42: Portal 1/2/3 | E42: 100
C43: Current Buffs & Notes | F43: # of HP Bars Remaining | G43: TRUE | H43: FALSE | I43: FALSE | J43: FALSE
C44: Current Debuffs | F44: Turns left this Round | G44: TRUE | H44: FALSE | I44: FALSE
B46: Enemy 9 | C46: Combatant Name | D46: Combatant Category | E46: Current HP | F46: Link to full Character Sheet
C48: Current Buffs & Notes | F48: # of HP Bars Remaining | G48: TRUE | H48: FALSE | I48: FALSE | J48: FALSE
C49: Current Debuffs | F49: Turns left this Round | G49: TRUE | H49: FALSE | I49: FALSE
B51: Enemy 10 | C51: Combatant Name | D51: Combatant Category | E51: Current HP | F51: Link to full Character Sheet
C53: Current Buffs & Notes | F53: # of HP Bars Remaining | G53: TRUE | H53: FALSE | I53: FALSE | J53: FALSE
C54: Current Debuffs | F54: Turns left this Round | G54: TRUE | H54: FALSE | I54: FALSE

Sheet  Encounter Balance Calculator
A1: Encounter Balance
A3: Allies | D3: Enemies
A4: Trainer points | B4: Trainer lvl | C4: Advantages | D4: Trainer points | E4: Pkmn points | F4: Advantages
A5: 3 | B5: 1
A6: Pkmn points | B6: Pkmn max lvl | C6: Disavantages | D6: Trainer lvl | E6: Pkmn lvl | F6: Disavantages
A7: 3 | B7: 5
A8: Balance: | B8: =IFS( F9-C9<=-4, "Very Easy", F9-C9<=-1, "Easy", F9-C9<=1, "Balanced", F9-C9<=4, "Hard", F9-C9>=5, "Very Hard" ) -> Very Easy | C8: Ally Total | D8: Trainer value | E8: Pkmn Value | F8: Enemy Total
C9: =A5+A7+C5-C7 -> 6 | D9: =IFS(D7<=B5-4, 0.5, D7>=B5+4, 2, TRUE, 1) -> 1 | E9: =IFS(E7<=B7/2, 0.5, E7>=B7*2, 3, TRUE, 1) -> 0.5 | F9: =D5+E5+F5-F7 -> 0

Sheet References
B2: Combatant Category Reference
B3: Name | C3: Combatant Rules
C4: =IFERROR(VLOOKUP($B$4,'Combatant Category Data'!A$2:B8,2,FALSE),"--") -> --
B5: Boss Perks | C5: =IF(B4="","--",IF(OR(B4="Boss (Alpha)",B4="Boss (Guardian)"),'Combatant Category Data'!C3,"N/A")) -> --
B7: Boss Perk Reference
B8: Name | C8: Boss Perk Rules
C9: =IFERROR(VLOOKUP($B$9,'Combatant Category Data'!A$2:$B54,2,FALSE),"--") -> --
B11: Surge Token Reference
B12: Name | C12: Surge Token Rules
C13: =IFERROR(VLOOKUP($B$13,'Combatant Category Data'!A$2:$B54,2,FALSE),"--") -> --
B15: Stance Reference
B16: Name | C16: Stance Effect | G16: Break Condition
C17: =IFERROR(VLOOKUP($B$17,'Combatant Category Data'!A$2:$B54,2,FALSE),"--") -> -- | G17: =IFERROR(VLOOKUP($B$17,'Combatant Category Data'!A$2:$C54,3,FALSE),"--") -> --
B19: Lair Action Reference
B20: Name | C20: Lair Action Rules | G20: Example
C21: =IFERROR(VLOOKUP($B$21,'Combatant Category Data'!A$2:$B54,2,FALSE),"--") -> -- | G21: =IFERROR(VLOOKUP($B$21,'Combatant Category Data'!A$2:$C54,3,FALSE),"--") -> --
B23: Attack Reference
B24: Name | C24: Type | D24: Category | E24: Frequency | F24: Range | G24: AC | DB | H24: Effect
C25: =IFERROR(VLOOKUP(B25,'Attack Data'!$A$2:$J54,2,FALSE),"--") -> -- | D25: =IFERROR(VLOOKUP(B25,'Attack Data'!$A$2:$J54,3,FALSE),"--") -> -- | E25: =IFERROR(VLOOKUP(B25,'Attack Data'!$A$2:$J54,4,FALSE),"--") -> -- | F25: =IFERROR(VLOOKUP(B25,'Attack Data'!$A$2:$J54,5,FALSE),"--") -> -- | G25: =IFERROR(CONCATENATE(VLOOKUP(B25,'Attack Data'!$A$2:$J54,6,FALSE)," | ",VLOOKUP(B25,'Attack Data'!$A$2:$J54,7,FALSE)),"--") -> -- | H25: =IFERROR(CONCATENATE(VLOOKUP(B25,'Attack Data'!$A$2:$J54,8,FALSE),CHAR(10),CHAR(10),"Rank 2 Effect:",CHAR(10),VLOOKUP(B25,'Attack Data'!$A$2:$J54,9,FALSE)),"--") -> --
B27: Role Reference
B28: Name | C28: Rank 1 Effect | G28: Rank 2 Effect
C29: =IFERROR(VLOOKUP($B$29,'Role Data'!$A$2:$C54,2,FALSE),"--") -> -- | G29: =IFERROR(VLOOKUP($B$29,'Role Data'!$A$2:$C54,3,FALSE),"--") -> --
B31: Status & Condition Reference
B32: Name | C32: Effects
B33: Suppressed | C33: =IFERROR(VLOOKUP($B$33,'Misc Data'!$C$2:$D54,2,FALSE),"--") -> » Whenever a Suppressed Combatant uses an EOT Attack, after Damage Calculations, they become Vulnerable until the end of the next Round. » Whenever a Suppressed Combatant uses a Scene or Daily Attack or Ability, after its resolution, they become Vulnerable and Weakened until the end of the next Round. » Combatants with a Boss Template are automatically cured of the Suppressed Affliction when they end their last Turn in a Round.
B35: Capability Reference
B36: Name | C36: Effects
C37: =IFERROR(VLOOKUP($B$37,'Misc Data'!$A$2:$B54,2,FALSE),"--") -> --
B39: Maneuver Reference
B40: Name | C40: Range | D40: Action | E40: Target | F40: AC | G40: Effect
C41: =IFERROR(VLOOKUP($B$41,'OrderTechnique Data'!$K$2:$P54,2,FALSE),"--") -> -- | D41: =IFERROR(VLOOKUP($B$41,'OrderTechnique Data'!$K$2:$P54,3,FALSE),"--") -> -- | E41: =IFERROR(VLOOKUP($B$41,'OrderTechnique Data'!$K$2:$P54,4,FALSE),"--") -> -- | F41: =IFERROR(VLOOKUP($B$41,'OrderTechnique Data'!$K$2:$P54,5,FALSE),"--") -> -- | G41: =IFERROR(VLOOKUP($B$41,'OrderTechnique Data'!$K$2:$P54,6,FALSE),"--") -> --
B43: Keyword Reference
B44: Name | C44: Effects
C45: =IFERROR(VLOOKUP($B$45,'Misc Data'!$E$2:$F54,2,FALSE),"--") -> --
B47: Terrain Type & Environment Reference
B48: Name | C48: Effects
C49: =IFERROR(VLOOKUP($B$49,'Misc Data'!$G$2:$H54,2,FALSE),"--") -> --
B51: Item Reference
B52: Name | C52: Effects
C53: =IFERROR(VLOOKUP($B$53,'Item Data'!$M$2:$N54,2,FALSE),"--") -> --

Sheet Combatant Category Data
B1: Rules | C1: Perks
A3: Boss (Alpha) | B3: 1. Alpha Pokemon are always 5 Levels higher than your Player’s Maximum Pokemon Level. If their Maximum level is 40 or higher, this is instead 10 Levels. If these Pokemon are captured, they are reverted to the Player’s Maximum Pokemon Level. 2. Alpha Pokemon will have multiple Health Bars. If there are 1-2 Players in the Party, they have 2. If there are 3+ Players, they have 3. Whenever they would faint, they instead revert to their Maximum Hit Point value with the damage not carrying over, then they lose one of their Health Bars. This is considered a “Bar Break”. 3. Alpha Pokemon may have multiple Turns, equal to the number of Players in the opposing Party. 4. Alpha Pokemon have 8 Attack Slots by default instead of 6. 5. Effects that reference, Start of Turn, Per Turn, or End of Turn, only occur once per Round on their first applicable turn where they could occur, regardless of the number of turns they have. Additionally, Save Checks can only occur on the Boss’s last Turn in a Round unless provoked by an outside source such as the Help Maneuver. 6. Boss Pokemon also may perform Boss Perks, listed below, once at the start of a Scene and twice each time a Bar Break would occur and they don’t faint as a result. | C3: 1. Choose two different Combat Values below to gain +1 (Modifier or CS) in or reset to their Default Value: Any Stat except HP, Accuracy, Critical Hit Range, Effect Range, Save Checks. 2. The Boss is cured (or removes) of two of the following options: A Status Affliction, A Coat, A Condition other than Fainted. 3. The Boss gains a Surge Token or two if there are 3+ Players in the opposing Party. 4. The Boss may enter a Stance. This can only occur once per Scene. 5. The Boss may use a Lair Action. 6. The Boss may transform into a different form that you have prepared. Cannot be used at the start of Combat.
A4: Boss (Guardian) | B4: 1. Guardian Pokemon are instead always +10 Levels higher than your Player’s Maximum Pokemon Level. If they are Tier 3, this is instead 20 Levels. 2. Guardian Pokemon will have multiple Health Bars. If there are 1-2 Players in the Party, they have 2. If there are 3+ Players, they have 3. Whenever they would faint, they instead revert to their Maximum Hit Point value with the damage not carrying over, then they lose one of their Health Bars. This is considered a “Bar Break”. 3. Guardian Pokemon may have multiple Turns, equal to the number of Players in the opposing Party. 4. Guardian Pokemon instead have 10 Attack Slots and may choose any Attack from their Tutor Lists to gain, ignoring Pokemon Advancement. 5. Effects that reference, Start of Turn, Per Turn, or End of Turn, only occur once per Round on their first applicable turn where they could occur, regardless of the number of turns they have. Additionally, Save Checks can only occur on the Boss’s last Turn in a Round unless provoked by an outside source such as the Help Maneuver. 6. Boss Pokemon also may perform Boss Perks, listed below, once at the start of a Scene and twice each time a Bar Break would occur and they don’t faint as a result. At the end of each Round, the Guardian may use a Boss Perk. We recommend this be used mostly for Lair Actions. 7. At Level 30 Advancement, Guardians gain both an Ability and the 2nd Rank of their Role, instead of choosing between the two. | C4: 1. Choose two different Combat Values below to gain +1 (Modifier or CS) in or reset to their Default Value: Any Stat except HP, Accuracy, Critical Hit Range, Effect Range, Save Checks. 2. The Boss is cured (or removes) of two of the following options: A Status Affliction, A Coat, A Condition other than Fainted. 3. The Boss gains a Surge Token or two if there are 3+ Players in the opposing Party. 4. The Boss may enter a Stance. This can only occur once per Scene. 5. The Boss may use a Lair Action. 6. The Boss may transform into a different form that you have prepared. Cannot be used at the start of Combat.
A5: Boss (Swarm) | B5: 1. Instead of Statting multiple Pokemon, a Swarm Pokemon has one Character Sheet representing the entire Swarm. 2. The Swarm will have a number of Turns equal to the number of Players in the Opposing Party +1. 3. Whenever the Swarm Pokemon hits 0 HP, they instead permanently lose a Turn, then reset to 100% Hit Points. When they have no Turns remaining, the Swarm faints. 4. Swarm Pokemon do not have Battle Attack Lists, and instead may use any Attack they can learn. 5. Swarm Pokemon do not have Pokemon Roles, instead, each time they would gain an Ability from Pokemon Progression, they instead gain two. 6. There will be a number of tokens to represent on the Swarm equal to the number of Turns they currently have. These are all treated as different combatants. If multiple tokens would be targeted by the same Attack, it doesn't deal damage or apply the effect twice, but instead is treated as one step more effective. | C5: --
A6: Minion (Offensive) | B6: 1. Minions start with 3 Hit Points. Minions cannot lose hit points outside of listed methods here. They cannot restore Hit Points and cannot gain Temporary Hit Points. When Minions lose a Tick of Hit Points, they lose -1 Hit Point. Whenever they’re hit with a Damaging Attack, they lose -1 Hit Point but they lose an additional Hit Point per condition they meet: the Attack was Super Effective, 1-Target, or a Critical Hit. 2. Minions can use any Attack from their Level-Up or Tutor List, provided their level is high enough. If you stat a Minion before an Encounter, you may choose to instead have Minions only have a maximum of 3 Attacks. 3. The Level of all Minions are 5 less than the Maximum Pokemon Level of the Party. 4. Minions cannot perform Save Checks to cure the effects of Afflictions. 5. The Minion can use Damaging Attacks with the At-Will or EOT Frequency. Their Offensive Stat for Damage Calculations is equal to their Level. 6. The Minion can use Tactic Maneuvers. Swift Action Maneuvers are instead Standard Actions. | C6: --
A7: Minion (Defensive) | B7: 1. Minions start with 3 Hit Points. Minions cannot lose hit points outside of listed methods here. They cannot restore Hit Points and cannot gain Temporary Hit Points. When Minions lose a Tick of Hit Points, they lose -1 Hit Point. Whenever they’re hit with a Damaging Attack, they lose -1 Hit Point but they lose an additional Hit Point per condition they meet: the Attack was Super Effective, 1-Target, or a Critical Hit. 2. Minions can use any Attack from their Level-Up or Tutor List, provided their level is high enough. If you stat a Minion before an Encounter, you may choose to instead have Minions only have a maximum of 3 Attacks. 3. The Level of all Minions are 5 less than the Maximum Pokemon Level of the Party. 4. Minions cannot perform Save Checks to cure the effects of Afflictions. 5. The Minion can use Status Attacks with the At-Will Frequency without the Shield Keyword. 6. The Minions can use the Defend, Provoke and Intercept Maneuver. | C7: --
A8: Minion (Supportive) | B8: 1. Minions start with 3 Hit Points. Minions cannot lose hit points outside of listed methods here. They cannot restore Hit Points and cannot gain Temporary Hit Points. When Minions lose a Tick of Hit Points, they lose -1 Hit Point. Whenever they’re hit with a Damaging Attack, they lose -1 Hit Point but they lose an additional Hit Point per condition they meet: the Attack was Super Effective, 1-Target, or a Critical Hit. 2. Minions can use any Attack from their Level-Up or Tutor List, provided their level is high enough. If you stat a Minion before an Encounter, you may choose to instead have Minions only have a maximum of 3 Attacks. 3. The Level of all Minions are 5 less than the Maximum Pokemon Level of the Party. 4. Minions cannot perform Save Checks to cure the effects of Afflictions. 5. The Minion can use Status Attacks without the Shield Keyword or Scene x1 Frequency. 6. The Minion can use the Help Maneuver and Manipulate Maneuvers. | C8: --
A9: Pokemon | B9: -- | C9: --
A10: Trainer | B10: -- | C10: --
A11: NPC | B11: -- | C11: --
A13: Surge Token | B13: In order to even the scales of an Encounter, you could grant your Boss Surge Tokens either as a Boss Perk when they lose HP Bars or through special occasions such as an Environmental Conduit granting Surge Tokens while they’re active. Bosses can expend a Surge Token to perform any of the following as a Free Action either on their Turn, at the end of any Turn, or when it would be triggered (Such as using it for an Intercept Maneuver)
A14: Stance | B14: Sometimes Bosses enter a certain Stance that empowers them in a specific way, but also has the chance to leave them vulnerable if a weakness is exploited, leaving it as a high risk for higher output option. Each Stance has an Effect and a Break Condition. During their current Health Bar, they will have the Effect of the Stance applied to them. When they lose an HP Bar, they automatically lose their Stance’s Effects, however if the Break Condition occurs, they lose their Stance’s Effects and they become Vulnerable until the end of the next Round.
A15: Lair Action | B15: Lair Actions can be done easily by Guardians but sometimes by regular bosses in order to show that the environment is alive and often dangerous. Whenever you wish to perform a Lair Action, choose something from the Lair Action references below to enable on the Scene. These are just examples however and you can create your own effects if desired based on the environment your Players are in and what they’re facing.
A17: Damaging Attack | B17: Expend a Surge Token to perform a Damaging Attack. This Attack is resisted by an additional damage step, but this can be ignored if the Attack only has one Target or if another Surger Token is expended
A18: Status Attack | B18: Expend a Surge Token to perform a Status Attack. This Attack cannot have a range of “Self or Shield”. The Frequency of an Attack used this way is not expended.
A19: Maneuver | B19: Expend a Surge Token to perform a Maneuver. This Maneuver cannot be an Attack of Opportunity, Riposte or Respite. If they use the Help Maneuver, it ignores its restrictions.
A20: Resist Attack | B20: Expend a Surge Token to resist an Attack by an additional damage step. However, the boss's next Swift Action is expended.
A21: Save Check | B21: Expend a Surge Token to perfrom a Save Check. However, the boss's next Swift Action is Expended.
A23: Frenzied | B23: The Boss immediately becomes Enraged and cannot be cured of it while affected by this Stance. The user’s Damaging Attacks all gain the Smite Keyword and their Critical Hit Range is increased by +2. | C23: The Stance is broken when the Boss misses two Attacks or causes one of their enemies to faint.
A24: Shielded | B24: The Boss gains 5 Ticks of Temporary Hit Points and then becomes one step more resistant to all Physical or Special Category Attacks, depending on which of their Defense Stats are higher (choose on tie). | C24: The Stance is broken when the Boss loses all Temporary Hit Points gained this way or has their higher Defense Stat lowered to a negative CS Value
A25: Unyielding | B25: When the Boss enters an Unyielding Stance, they choose a Player to become their Rival (All their Pokemon are also treated as Rivals). Whenever the Boss Attacks a Rival, they have a +3 to Accuracy, ignore Damage Reduction and can’t have their Attacks resisted by the Rival by any means. | C25: The Stance is broken if a Rival of the Boss inflicts a Critical Hit against the Boss or avoids two Attacks.
A26: Charging | B26: While in this Stance, as a Swift Action, they gain +1 Charge Token. Whenever they’re hit by a Critical Hit or gain an Affliction, they lose a Charge Token. At the end of the Round, if they have at least one Charge Token, they expend all Charge Tokens and may use a Damaging Attack as a Free Action. For each Charge Token expended, they gain a benefit listed below: » The Attack gains +3 DB » The Attack gains the Smite Keyword or Sureshot if it already has Smite. » The Attack increases its Area of Effect by +1 | C26: The Stance automatically breaks after the resolution of the Attack used with the expended Charge Tokens or the end of the Round if they’re unable to use the Attack. The Stance is also considered to be broken if they lose their HP Bar before they would resolve this Attack.
A27: Desperate | B27: When the Boss enters the Desperate Stance, a Minion enters the Field for each opposing Player. Whenever the Boss would start their Turn, instead, two Minions may act or they may add another Minion to the Encounter. | C27: The Stance breaks when a number of Minions equal to double the number of Players in the opposing Party faint. After this Stance breaks, all Minions flee the Encounter.
A28: Regenerative | B28: The user has a +3 bonus to Save Checks and at the end of their Turns (Ignoring the end of Turn rule), they restore two Ticks of Hit Points or gain a Tick of Temporary Hit Points. | C28: The Stance breaks when the Boss is hit by a Critical Hit, recovers at least 8 Ticks of Hit Points, or recovers from at least 2 Status Afflictions while in the Stance.
A30: Area Retaliation | B30: Choose one Attack on the Boss’s Battle Attack List or an Attack that would make sense to come from the environment. Then choose either three 3x3 Zones or a 5x5 Zone, or whatever other Zone would make sense for the trigger (These Zones are visible to all Combatants). At the end of the next Round or upon a Trigger being fulfilled, the chosen Attack is used as a Free Action, Targeting all Combatants or Enemies of the Boss within the chosen Zones. If it was chosen from the Boss’s list of Attacks, it ignores Frequency and uses their Offensive Stat. Otherwise it follows the Environmental Damage rules under “Other Damage Types”. | C30: A wild jungle causes vines to whiplash in five “Line 4” Ranges, each using the Power Whip Attack. A loud Exploud causes Stalactites to fall from the ceiling in three 3x3 Zones with the Rock Slide Attack.
A31: Attack Blowback | B31: A delayed change in the environment has occurred based on something that happened during this Round. Resolving the effects of this blowback should use a Standard action or Swift Action if resourceful. | C31: A machine overloads from a missed thunderbolt causing anyone who ends their turn adjacent to it to become Paralyzed, trees catching on fire from a flamethrower leading to an area of effect of Fire Hazards or a draco meteor landing on a grassland causing a cloud of pollen to haze the field, leading to a -2 to Accuracy for a Round.
A32: Battlefield Alteration | B32: The Battlefield has been altered somehow. One Effect enters the field or alters the terrain that either affects all Combatants, harms the Player’s Party or benefits the Boss’s Party. This usually is either Terrain being changed, Blessings entering the field or the Weather changing. | C32: The Weather changes to Thunderstorm. A Nidoking’s rampage leads to a lot of earthen blocking terrain being created on the field on a labyrinth pattern. Psionic aura created by an Alakazam lead to a protective aura on its allies, leading to 2 Activations of the Reflect Attack.
A33: Environmental Conduit | B33: Something appears on the Battlefield that likely has a connection with the Boss and causes a passive effect while it remains undestroyed. This “Conduit” is treated as Blocking Terrain and has HP equal to 20 times the Party’s Trainer Level. Alternatively, three “Conduits” can appear but they only have HP equal to 5 Times their Trainer Level. When it is destroyed, the effects that derived from it cease. | C33: Three paintings in a Haunted House start to look alive and at the end of each turn unless destroyed, they roll a Luck Check and on a 5 or under, they Curse someone within 3m of them. A massive generator starts to stir, creating a psychic aura that makes all Psychic Attacks have the Sureshot Keyword unless destroyed and increases in power each round. The Boss creates a crystal that gives it Immunity to Dark Type Damage while active.
A34: Fleeting Catastrophe | B34: Something has occurred on the battlefield that doesn’t have any immediate impact but if not dealt with somehow, it will cause something to occur at the end of the next round or a timer of your discretion. The result from this Catastrophe not being resolved could be another Lair Action but with more drastic impact. Resolving this Catastrophe should use a Standard action or Swift Action if resourceful. | C34: A generator starts to fizz and spark looking like it’ll explode. If the Party doesn’t destroy it before it explodes or stops the explosion, it’ll cause a Burst 2 Electric Special Attack with Massive Damage. Alternatively they could use it to their advantage and slide an enemy into its range! A Forest Fire is beginning and will double in Fire Hazards every round its not extinguished.
A35: Reactive Battlefield | B35: Something has occurred in the scene that requires a quick reaction from a Combatant in order to stave off its negative effects. Designate a Combatant or a maximum of a 3x3 Zone to be affected by this Lair Action. They then must perform a Luck Roll with a Modifier of their Skill Rank in a Skill allowed by the GM and a DC of 12. If they fail this Luck Roll, they’re affected by the negative effect, usually gaining a Status Affliction or Conditions or temporary penalty. The Modifier can be doubled before rolling as a Swift Action, Priority (Advanced). If it makes sense to, the Combatant can add an appropriate Skill Rank as a modifier to this Luck Roll. | C35: A cloud of dark smoke looms towards a Player that Suppresses them on a failed roll, they can use Occult Edu as their Skill Modifier or Intuition to determine the weird nature of the smoke. The earth shifts under a 2x2 zone from an Earthquake and on a failed roll they are Tripped, they can use Acrobatics as their Skill Modifier to represent their nimbleness.
A36: Reinforcements | B36: A Path has opened on the battlefield in which Pokemon that are allied to the Boss can enter the field. A Minion (Or two if there are 3+ Players in the Party) enters the Field when this Lair Action is used and at the end of every subsequent Round this isn’t resolved. Resolving this Lair Action should use a Standard action or Swift Action if resourceful. | C36: A rift in space is opened and a Solrock comes out. The player’s Metagross attacks the portal with a Psychic and it fizzles out. Goomy start to wander out of a swamp lake. The player’s Pangoro stands nearby the lake and uses a Swift Action to intimidate and stave off any other goomy from joining the encounter.

Sheet Item Data
A1: Valuables | B1: Valuables Effect | C1: Consumables | D1: Consumables Effect | E1: Equipment | F1: Equipment Effect | G1: Weapon List | I1: Armor List | K1: Pokemon List | M1: All Items | N1: All Effects
A2: =IFERROR(__xludf.DUMMYFUNCTION("IMPORTRANGE('Homebrew Sheet'!$A$6,""'Items'!$A$2:$F$101"")"),"") | G2: =IFERROR(__xludf.DUMMYFUNCTION("QUERY($E$2:F1001,""select Col1,Col2 where Col2 contains 'Weapon]' or Col2 contains 'Any]'"",-1)"),"Braced Shield") -> Braced Shield | H2: =IFERROR(__xludf.DUMMYFUNCTION("""COMPUTED_VALUE"""),"While Equipped, whenever the user uses a Defend Maneuver, the Target has Damage Reduction equal to your Tier Value for the duration of the Maneuver. If the Target is no longer Adjacent to you, they do not benefit from this Effect [Medium] [Equipment - Wea"&"pon]") -> While Equipped, whenever the user uses a Defend Maneuver, the Target has Damage Reduction equal to your Tier Value for the duration of the Maneuver. If the Target is no longer Adjacent to you, they do not benefit from this Effect [Medium] [Equipment - Weapon] | I2: =IFERROR(__xludf.DUMMYFUNCTION("QUERY($E$2:F1001,""select Col1,Col2 where Col2 contains 'Armor]' or Col2 contains 'Any]'"",-1)"),"Arcane Armor ") -> Arcane Armor | J2: =IFERROR(__xludf.DUMMYFUNCTION("""COMPUTED_VALUE"""),"While Equipped, the user has +10 Damage Reduction and their Special Defense CS their Default CS Value set to +1. While Equipped, the user has their Default Movement Value lowered by -2. You must be Trainer Level 10+ to equip this. [Large] [Equipment - Ar"&"mor]") -> While Equipped, the user has +10 Damage Reduction and their Special Defense CS their Default CS Value set to +1. While Equipped, the user has their Default Movement Value lowered by -2. You must be Trainer Level 10+ to equip this. [Large] [Equipment - Armor] | K2: =IFERROR(__xludf.DUMMYFUNCTION("QUERY($E$2:F1001,""select Col1,Col2 where Col2 contains '[Pokemon]'"")"),"Air Balloon") -> Air Balloon | L2: =IFERROR(__xludf.DUMMYFUNCTION("""COMPUTED_VALUE"""),"This Item may only be equipped by Small Pokemon. While this Item is equipped, the User is immune to Attacks with the Groundsource Keyword and gains the Flier Capability. [Large] [Pokemon]") -> This Item may only be equipped by Small Pokemon. While this Item is equipped, the User is immune to Attacks with the Groundsource Keyword and gains the Flier Capability. [Large] [Pokemon] | M2: =IFERROR(__xludf.DUMMYFUNCTION("UNIQUE(QUERY({QUERY({$A$2:$B1001;$C$2:$D1001;$E$2:$F1001},""select Col1,Col2 where Col1 is not null"")},""select * order by Col1""))"),"(X) Shard") -> (X) Shard | N2: =IFERROR(__xludf.DUMMYFUNCTION("""COMPUTED_VALUE"""),"A Shard can be expended as a Free Action in the user's Inventory upon hitting a Damaging Attack that corresponds to an associated Type to increase its Damage Base by +3. The user may only expend one Shard per Attack. A Shard can come in any of the followi"&"ng colors and has the associated Types. Red (Fire, Fairy, Psychic), Orange (Normal, Fighting, Dragon), Yellow (Electric, Rock, Steel), Green (Bug, Grass, Ground), Blue (Flying, Ice, Water), Violet (Dark, Ghost, Poison). [Small] [Consumable] [Pokemon]") -> A Shard can be expended as a Free Action in the user's Inventory upon hitting a Damaging Attack that corresponds to an associated Type to increase its Damage Base by +3. The user may only expend one Shard per Attack. A Shard can come in any of the following colors and has the associated Types. Red (Fire, Fairy, Psychic), Orange (Normal, Fighting, Dragon), Yellow (Electric, Rock, Steel), Green (Bug, Grass, Ground), Blue (Flying, Ice, Water), Violet (Dark, Ghost, Poison). [Small] [Consumable] [Pokemon]
G3: =IFERROR(__xludf.DUMMYFUNCTION("""COMPUTED_VALUE"""),"Fine Weapon") -> Fine Weapon | H3: =IFERROR(__xludf.DUMMYFUNCTION("""COMPUTED_VALUE"""),"To determine the Effects of this Weapon while Equipped, refer to the ""Creating Weapon Item's Section in the Core Book. [Medium or Large] [Equipment - Weapon]") -> To determine the Effects of this Weapon while Equipped, refer to the "Creating Weapon Item's Section in the Core Book. [Medium or Large] [Equipment - Weapon] | I3: =IFERROR(__xludf.DUMMYFUNCTION("""COMPUTED_VALUE"""),"Assault Vest") -> Assault Vest | J3: =IFERROR(__xludf.DUMMYFUNCTION("""COMPUTED_VALUE"""),"While this Item is Equipped, the user gains a TIck of Temporary Hit Points whenever they're hit by a Physical Atack after Damage Calculations [Equipment - Armor] [[Large] [Pokemon]") -> While this Item is Equipped, the user gains a TIck of Temporary Hit Points whenever they're hit by a Physical Atack after Damage Calculations [Equipment - Armor] [[Large] [Pokemon] | K3: =IFERROR(__xludf.DUMMYFUNCTION("""COMPUTED_VALUE"""),"Analytic Lens") -> Analytic Lens | L3: =IFERROR(__xludf.DUMMYFUNCTION("""COMPUTED_VALUE"""),"While this Item is Equipped, the user has +1 to Effect Ranges. [Equipment] [Medium] [Pokemon]") -> While this Item is Equipped, the user has +1 to Effect Ranges. [Equipment] [Medium] [Pokemon] | M3: =IFERROR(__xludf.DUMMYFUNCTION("""COMPUTED_VALUE"""),"Ability Capsule") -> Ability Capsule | N3: =IFERROR(__xludf.DUMMYFUNCTION("""COMPUTED_VALUE"""),"When this Item is created, the GM will choose any Ability. When this Item is expended, choose a Pokemon you own. The Target may choose that Ability whenever they would be able to learn one, instead of one from their natural Ability List. [Small] [Consumab"&"le]") -> When this Item is created, the GM will choose any Ability. When this Item is expended, choose a Pokemon you own. The Target may choose that Ability whenever they would be able to learn one, instead of one from their natural Ability List. [Small] [Consumable]
G4: =IFERROR(__xludf.DUMMYFUNCTION("""COMPUTED_VALUE"""),"Heavy Shield") -> Heavy Shield | H4: =IFERROR(__xludf.DUMMYFUNCTION("""COMPUTED_VALUE"""),"While Equipped, whenever the user uses a Defend Maneuver, the Target has Damage Reduction equal to your Tier Value for the duration of the Maneuver. If the Target is no longer Adjacent to you, they do not benefit from this Effect. Additionally, while Equi"&"pped, you may use a Swift Action to gain Damage Reduction equal to your Tier Value for a Full Round. You must be Trainer Level 5+ to equip this. [Large] [Equipment - Weapon]") -> While Equipped, whenever the user uses a Defend Maneuver, the Target has Damage Reduction equal to your Tier Value for the duration of the Maneuver. If the Target is no longer Adjacent to you, they do not benefit from this Effect. Additionally, while Equipped, you may use a Swift Action to gain Damage Reduction equal to your Tier Value for a Full Round. You must be Trainer Level 5+ to equip this. [Large] [Equipment - Weapon] | I4: =IFERROR(__xludf.DUMMYFUNCTION("""COMPUTED_VALUE"""),"Covert Cloak") -> Covert Cloak | J4: =IFERROR(__xludf.DUMMYFUNCTION("""COMPUTED_VALUE"""),"While Equipped, Attacks against the user have a -2 Penalty to Effect Ranges. [Medium] [Equipment - Armor] [Pokemon]") -> While Equipped, Attacks against the user have a -2 Penalty to Effect Ranges. [Medium] [Equipment - Armor] [Pokemon] | K4: =IFERROR(__xludf.DUMMYFUNCTION("""COMPUTED_VALUE"""),"Assault Vest") -> Assault Vest | L4: =IFERROR(__xludf.DUMMYFUNCTION("""COMPUTED_VALUE"""),"While this Item is Equipped, the user gains a TIck of Temporary Hit Points whenever they're hit by a Physical Atack after Damage Calculations [Equipment - Armor] [[Large] [Pokemon]") -> While this Item is Equipped, the user gains a TIck of Temporary Hit Points whenever they're hit by a Physical Atack after Damage Calculations [Equipment - Armor] [[Large] [Pokemon] | M4: =IFERROR(__xludf.DUMMYFUNCTION("""COMPUTED_VALUE"""),"Air Balloon") -> Air Balloon | N4: =IFERROR(__xludf.DUMMYFUNCTION("""COMPUTED_VALUE"""),"This Item may only be equipped by Small Pokemon. While this Item is equipped, the User is immune to Attacks with the Groundsource Keyword and gains the Flier Capability. [Large] [Pokemon]") -> This Item may only be equipped by Small Pokemon. While this Item is equipped, the User is immune to Attacks with the Groundsource Keyword and gains the Flier Capability. [Large] [Pokemon]
G5: =IFERROR(__xludf.DUMMYFUNCTION("""COMPUTED_VALUE"""),"Legendary Weapon") -> Legendary Weapon | H5: =IFERROR(__xludf.DUMMYFUNCTION("""COMPUTED_VALUE"""),"To determine the Effects of this Weapon while Equipped, refer to the ""Creating Weapon Item's Section in the Core Book. [Medium or Large] [Equipment - Weapon]") -> To determine the Effects of this Weapon while Equipped, refer to the "Creating Weapon Item's Section in the Core Book. [Medium or Large] [Equipment - Weapon] | I5: =IFERROR(__xludf.DUMMYFUNCTION("""COMPUTED_VALUE"""),"Crude Armor") -> Crude Armor | J5: =IFERROR(__xludf.DUMMYFUNCTION("""COMPUTED_VALUE"""),"While Equipped, the user has +5 Damage Reduction. [Medium] [Equipment - Armor]") -> While Equipped, the user has +5 Damage Reduction. [Medium] [Equipment - Armor] | K5: =IFERROR(__xludf.DUMMYFUNCTION("""COMPUTED_VALUE"""),"Berserk Belt") -> Berserk Belt | L5: =IFERROR(__xludf.DUMMYFUNCTION("""COMPUTED_VALUE"""),"While this Item is Equipped, whenever the user causes an Enemy to faint via a Damaging Attack, they gain +1 CS to Attack or Special Attack. [Equipment] [Medium] [Pokemon]") -> While this Item is Equipped, whenever the user causes an Enemy to faint via a Damaging Attack, they gain +1 CS to Attack or Special Attack. [Equipment] [Medium] [Pokemon] | M5: =IFERROR(__xludf.DUMMYFUNCTION("""COMPUTED_VALUE"""),"Alarm Rune [Occult]") -> Alarm Rune [Occult] | N5: =IFERROR(__xludf.DUMMYFUNCTION("""COMPUTED_VALUE"""),"Cost: 4 Counters Effect: This Rune may be inscribed onto the surface of any object and be given an appropriate trigger condition, such as the inscribed book or door being opened. If the Trigger occurs, the rune lights up and you telepathically hear an ala"&"rm in your head to alert you. If you are further than a Mile from your Alarm Rune, it cannot be triggered. You can only have one Alarm Rune inscribed at a time.This can only be used by a Rune Master [Small] [Consumable] Advanced: The Rune can be triggered"&" and alert you regardless of your distance from it. You can have up to 3 Alarm Runes inscribed at a time.") -> Cost: 4 Counters Effect: This Rune may be inscribed onto the surface of any object and be given an appropriate trigger condition, such as the inscribed book or door being opened. If the Trigger occurs, the rune lights up and you telepathically hear an alarm in your head to alert you. If you are further than a Mile from your Alarm Rune, it cannot be triggered. You can only have one Alarm Rune inscribed at a time.This can only be used by a Rune Master [Small] [Consumable] Advanced: The Rune can be triggered and alert you regardless of your distance from it. You can have up to 3 Alarm Runes inscribed at a time.
G6: =IFERROR(__xludf.DUMMYFUNCTION("""COMPUTED_VALUE"""),"Ranger Styler") -> Ranger Styler | H6: =IFERROR(__xludf.DUMMYFUNCTION("""COMPUTED_VALUE"""),"Outside of Combat, whenever a Pokemon would be in a state where they could be Captured by a Pokeball, you may use this Item to cause them to become a Companion (See Mechanics). While Equipped, as a Standard Action you may Target an Enemy within 5m and per"&"form a Command or Charm Check opposed by their Focus. If they fail, choose one of the following Effects to apply: [Medium] [Equipment - Weapon] » Guard Break - The next Attack that Targets them ignores Evasion. » Pacify - During their next Turn, the Targe"&"t’s Damaging Attacks are resisted by an additional step. » Restrain - Until the end of their next Turn, the Target either becomes Trapped by an Ally or Yourself or has their Movement Value halved. The Ally must be within 3m of the Target to be Trapped. ") -> Outside of Combat, whenever a Pokemon would be in a state where they could be Captured by a Pokeball, you may use this Item to cause them to become a Companion (See Mechanics). While Equipped, as a Standard Action you may Target an Enemy within 5m and perform a Command or Charm Check opposed by their Focus. If they fail, choose one of the following Effects to apply: [Medium] [Equipment - Weapon] » Guard Break - The next Attack that Targets them ignores Evasion. » Pacify - During their next Turn, the Target’s Damaging Attacks are resisted by an additional step. » Restrain - Until the end of their next Turn, the Target either becomes Trapped by an Ally or Yourself or has their Movement Value halved. The Ally must be within 3m of the Target to be Trapped. | I6: =IFERROR(__xludf.DUMMYFUNCTION("""COMPUTED_VALUE"""),"Heavy Armor") -> Heavy Armor | J6: =IFERROR(__xludf.DUMMYFUNCTION("""COMPUTED_VALUE"""),"While Equipped, the user has +10 Damage Reduction and their Defense CS their Default CS Value set to +1. While Equipped, the user has their Default Movement Value lowered by -2. You must be Trainer Level 10+ to equip this. [Large] [Equipment - Armor]") -> While Equipped, the user has +10 Damage Reduction and their Defense CS their Default CS Value set to +1. While Equipped, the user has their Default Movement Value lowered by -2. You must be Trainer Level 10+ to equip this. [Large] [Equipment - Armor] | K6: =IFERROR(__xludf.DUMMYFUNCTION("""COMPUTED_VALUE"""),"Blessed Relic") -> Blessed Relic | L6: =IFERROR(__xludf.DUMMYFUNCTION("""COMPUTED_VALUE"""),"While this Item is Equipped, the user has +2 to Save Checks. [Equipment] [Medium] [Pokemon]") -> While this Item is Equipped, the user has +2 to Save Checks. [Equipment] [Medium] [Pokemon] | M6: =IFERROR(__xludf.DUMMYFUNCTION("""COMPUTED_VALUE"""),"Analytic Lens") -> Analytic Lens | N6: =IFERROR(__xludf.DUMMYFUNCTION("""COMPUTED_VALUE"""),"While this Item is Equipped, the user has +1 to Effect Ranges. [Equipment] [Medium] [Pokemon]") -> While this Item is Equipped, the user has +1 to Effect Ranges. [Equipment] [Medium] [Pokemon]
G7: =IFERROR(__xludf.DUMMYFUNCTION("""COMPUTED_VALUE"""),"Simple Weapon") -> Simple Weapon | H7: =IFERROR(__xludf.DUMMYFUNCTION("""COMPUTED_VALUE"""),"To determine the Effects of this Weapon while Equipped, refer to the ""Creating Weapon Item's Section in the Core Book. [Medium or Large] [Equipment - Weapon]") -> To determine the Effects of this Weapon while Equipped, refer to the "Creating Weapon Item's Section in the Core Book. [Medium or Large] [Equipment - Weapon] | I7: =IFERROR(__xludf.DUMMYFUNCTION("""COMPUTED_VALUE"""),"High Quality Heavy Armor") -> High Quality Heavy Armor | J7: =IFERROR(__xludf.DUMMYFUNCTION("""COMPUTED_VALUE"""),"While Equipped, the user has +20 Damage Reduction. You must be Trainer Level 15+ to equip this. [Large] [Equipment - Armor]") -> While Equipped, the user has +20 Damage Reduction. You must be Trainer Level 15+ to equip this. [Large] [Equipment - Armor] | K7: =IFERROR(__xludf.DUMMYFUNCTION("""COMPUTED_VALUE"""),"Cargo Bag") -> Cargo Bag | L7: =IFERROR(__xludf.DUMMYFUNCTION("""COMPUTED_VALUE"""),"While Equipped, the user has 4 Inventory Slots (Pokemon cannot use these Items). An adjacent Trainer may equip or use Items in these Slots as if they were in their own Inventory. Only Pokemon may equip this Item. Large Items cannot be put in these Slots i"&"f the user’s size is Small. [Large] [Pokemon] [Inventory 2]") -> While Equipped, the user has 4 Inventory Slots (Pokemon cannot use these Items). An adjacent Trainer may equip or use Items in these Slots as if they were in their own Inventory. Only Pokemon may equip this Item. Large Items cannot be put in these Slots if the user’s size is Small. [Large] [Pokemon] [Inventory 2] | M7: =IFERROR(__xludf.DUMMYFUNCTION("""COMPUTED_VALUE"""),"Arcane Armor ") -> Arcane Armor | N7: =IFERROR(__xludf.DUMMYFUNCTION("""COMPUTED_VALUE"""),"While Equipped, the user has +10 Damage Reduction and their Special Defense CS their Default CS Value set to +1. While Equipped, the user has their Default Movement Value lowered by -2. You must be Trainer Level 10+ to equip this. [Large] [Equipment - Ar"&"mor]") -> While Equipped, the user has +10 Damage Reduction and their Special Defense CS their Default CS Value set to +1. While Equipped, the user has their Default Movement Value lowered by -2. You must be Trainer Level 10+ to equip this. [Large] [Equipment - Armor]
G8: =IFERROR(__xludf.DUMMYFUNCTION("""COMPUTED_VALUE"""),"Training Weapon") -> Training Weapon | H8: =IFERROR(__xludf.DUMMYFUNCTION("""COMPUTED_VALUE"""),"To determine the Effects of this Weapon while Equipped, refer to the ""Creating Weapon Item's Section in the Core Book. [Medium or Large] [Equipment - Weapon]") -> To determine the Effects of this Weapon while Equipped, refer to the "Creating Weapon Item's Section in the Core Book. [Medium or Large] [Equipment - Weapon] | I8: =IFERROR(__xludf.DUMMYFUNCTION("""COMPUTED_VALUE"""),"High Quality Light Armor") -> High Quality Light Armor | J8: =IFERROR(__xludf.DUMMYFUNCTION("""COMPUTED_VALUE"""),"While Equipped, the user has +10 Damage Reduction. You must be Trainer Level 15+ to equip this. [Medium] [Equipment - Armor]") -> While Equipped, the user has +10 Damage Reduction. You must be Trainer Level 15+ to equip this. [Medium] [Equipment - Armor] | K8: =IFERROR(__xludf.DUMMYFUNCTION("""COMPUTED_VALUE"""),"Covert Cloak") -> Covert Cloak | L8: =IFERROR(__xludf.DUMMYFUNCTION("""COMPUTED_VALUE"""),"While Equipped, Attacks against the user have a -2 Penalty to Effect Ranges. [Medium] [Equipment - Armor] [Pokemon]") -> While Equipped, Attacks against the user have a -2 Penalty to Effect Ranges. [Medium] [Equipment - Armor] [Pokemon] | M8: =IFERROR(__xludf.DUMMYFUNCTION("""COMPUTED_VALUE"""),"Artificing Kit") -> Artificing Kit | N8: =IFERROR(__xludf.DUMMYFUNCTION("""COMPUTED_VALUE"""),"As a Downtime Action you may perform an Occult, Nature or Tech Edu Skill Check. If an area would be less likely to find shards, perform it with a Bane. if it would be more likely to find shards such as in a cave, perform it with a Boon. For each Success, "&"you find a Shard Item. Whenever you gain a shard this way, roll a d6 to determine the color. 1 is Red, 2 is Orange, 3 is Yellow, 4 is Green, 5 is Blue, 6 is Violet. [Medium] ") -> As a Downtime Action you may perform an Occult, Nature or Tech Edu Skill Check. If an area would be less likely to find shards, perform it with a Bane. if it would be more likely to find shards such as in a cave, perform it with a Boon. For each Success, you find a Shard Item. Whenever you gain a shard this way, roll a d6 to determine the color. 1 is Red, 2 is Orange, 3 is Yellow, 4 is Green, 5 is Blue, 6 is Violet. [Medium]
I9: =IFERROR(__xludf.DUMMYFUNCTION("""COMPUTED_VALUE"""),"Light Armor") -> Light Armor | J9: =IFERROR(__xludf.DUMMYFUNCTION("""COMPUTED_VALUE"""),"While Equipped, the user has +10 Damage Reduction. You must be Trainer Level 5+ to equip this. [Large] [Equipment - Armor]") -> While Equipped, the user has +10 Damage Reduction. You must be Trainer Level 5+ to equip this. [Large] [Equipment - Armor] | K9: =IFERROR(__xludf.DUMMYFUNCTION("""COMPUTED_VALUE"""),"Dodge Scarf") -> Dodge Scarf | L9: =IFERROR(__xludf.DUMMYFUNCTION("""COMPUTED_VALUE"""),"While this Item is Equipped, the user has a bonus to Evasion equal to their Tier Level. As a Reaction + Movement Action, they may treat this bonus as Uncapped until the start of their next Turn. [Equipment] [Large] [Pokemon]") -> While this Item is Equipped, the user has a bonus to Evasion equal to their Tier Level. As a Reaction + Movement Action, they may treat this bonus as Uncapped until the start of their next Turn. [Equipment] [Large] [Pokemon] | M9: =IFERROR(__xludf.DUMMYFUNCTION("""COMPUTED_VALUE"""),"Artisan Kit (X)") -> Artisan Kit (X) | N9: =IFERROR(__xludf.DUMMYFUNCTION("""COMPUTED_VALUE"""),"Whenever you Innovate or Research during a Downtime Phase and use an Exertion Modifier, if it’s for something that is related to (X), you reroll all dice that land on a 1. [Large]") -> Whenever you Innovate or Research during a Downtime Phase and use an Exertion Modifier, if it’s for something that is related to (X), you reroll all dice that land on a 1. [Large]
I10: =IFERROR(__xludf.DUMMYFUNCTION("""COMPUTED_VALUE"""),"Psionic Vest") -> Psionic Vest | J10: =IFERROR(__xludf.DUMMYFUNCTION("""COMPUTED_VALUE"""),"While this Item is Equipped, the user gains a TIck of Temporary Hit Points whenever they're hit by a Special Atack after Damage Calculations [Equipment - Armor] [[Large] [Pokemon]") -> While this Item is Equipped, the user gains a TIck of Temporary Hit Points whenever they're hit by a Special Atack after Damage Calculations [Equipment - Armor] [[Large] [Pokemon] | K10: =IFERROR(__xludf.DUMMYFUNCTION("""COMPUTED_VALUE"""),"Eject Module") -> Eject Module | L10: =IFERROR(__xludf.DUMMYFUNCTION("""COMPUTED_VALUE"""),"This Item may only be equipped by a Pokemon. While this Item is Equipped, whenever the User is hit with an Attack, after Damage Resolution they may choose to be recalled as a Reaction, Free Action. Their Trainer may then send out a new Pokemon as a Free A"&"ction in the same spot the holder was. This cannot be used if the User fainted as a result of the Triggering Attack. [Medium] [Equipment] [Pokemon]") -> This Item may only be equipped by a Pokemon. While this Item is Equipped, whenever the User is hit with an Attack, after Damage Resolution they may choose to be recalled as a Reaction, Free Action. Their Trainer may then send out a new Pokemon as a Free Action in the same spot the holder was. This cannot be used if the User fainted as a result of the Triggering Attack. [Medium] [Equipment] [Pokemon] | M10: =IFERROR(__xludf.DUMMYFUNCTION("""COMPUTED_VALUE"""),"Artisan Pack") -> Artisan Pack | N10: =IFERROR(__xludf.DUMMYFUNCTION("""COMPUTED_VALUE"""),"As an Extended Action, choose a [Small] Item. While Equipped, you treat that item as if it had the [Resource] Keyword within GM approval. If this Item is Impaired, you cannot access any Items within these Slots. [Medium] [Equipment]") -> As an Extended Action, choose a [Small] Item. While Equipped, you treat that item as if it had the [Resource] Keyword within GM approval. If this Item is Impaired, you cannot access any Items within these Slots. [Medium] [Equipment]
I11: =IFERROR(__xludf.DUMMYFUNCTION("""COMPUTED_VALUE"""),"Rocky Helmet") -> Rocky Helmet | J11: =IFERROR(__xludf.DUMMYFUNCTION("""COMPUTED_VALUE"""),"While this Item is Equipped, whenever the user is Targeted by a Melee Attack, the Attacker loses a Tick of Hit Points. [Equipment - Armor] [Large] [Pokemon]") -> While this Item is Equipped, whenever the user is Targeted by a Melee Attack, the Attacker loses a Tick of Hit Points. [Equipment - Armor] [Large] [Pokemon] | K11: =IFERROR(__xludf.DUMMYFUNCTION("""COMPUTED_VALUE"""),"Focus Sash") -> Focus Sash | L11: =IFERROR(__xludf.DUMMYFUNCTION("""COMPUTED_VALUE"""),"While this Item is Equipped, the user has the Endure Attack added to their Attack List without taking a Slot. If the Endure Attack is used, the User’s Positive Combat Stages are reset to their Default Value. [Large] [Equipment] [Pokemon]") -> While this Item is Equipped, the user has the Endure Attack added to their Attack List without taking a Slot. If the Endure Attack is used, the User’s Positive Combat Stages are reset to their Default Value. [Large] [Equipment] [Pokemon] | M11: =IFERROR(__xludf.DUMMYFUNCTION("""COMPUTED_VALUE"""),"Assault Vest") -> Assault Vest | N11: =IFERROR(__xludf.DUMMYFUNCTION("""COMPUTED_VALUE"""),"While this Item is Equipped, the user gains a TIck of Temporary Hit Points whenever they're hit by a Physical Atack after Damage Calculations [Equipment - Armor] [[Large] [Pokemon]") -> While this Item is Equipped, the user gains a TIck of Temporary Hit Points whenever they're hit by a Physical Atack after Damage Calculations [Equipment - Armor] [[Large] [Pokemon]
K12: =IFERROR(__xludf.DUMMYFUNCTION("""COMPUTED_VALUE"""),"Jewelry") -> Jewelry | L12: =IFERROR(__xludf.DUMMYFUNCTION("""COMPUTED_VALUE"""),"This Item does nothing without being given an effect by the GM. [Small] [Equipment] [Pokemon]") -> This Item does nothing without being given an effect by the GM. [Small] [Equipment] [Pokemon] | M12: =IFERROR(__xludf.DUMMYFUNCTION("""COMPUTED_VALUE"""),"Bardic Instrument") -> Bardic Instrument | N12: =IFERROR(__xludf.DUMMYFUNCTION("""COMPUTED_VALUE"""),"When this Item is created, choose two of the following Attacks to apply to it. While this Item is equipped, the user may use those Attacks. If this Item is Large, instead choose three. [Large or Medium] [Equipment] Options are: Heal Bell, Sing, Screech,So"&"nic Boom, Supersonic or Metal Sound") -> When this Item is created, choose two of the following Attacks to apply to it. While this Item is equipped, the user may use those Attacks. If this Item is Large, instead choose three. [Large or Medium] [Equipment] Options are: Heal Bell, Sing, Screech,Sonic Boom, Supersonic or Metal Sound
K13: =IFERROR(__xludf.DUMMYFUNCTION("""COMPUTED_VALUE"""),"Large Gadget") -> Large Gadget | L13: =IFERROR(__xludf.DUMMYFUNCTION("""COMPUTED_VALUE"""),"When this Item is created, the GM will determine what the effect of the Gadget is upon usage. While equipped, the user benefits from the effects of the Gadget. [Large] [Equipment] [Pokemon]") -> When this Item is created, the GM will determine what the effect of the Gadget is upon usage. While equipped, the user benefits from the effects of the Gadget. [Large] [Equipment] [Pokemon] | M13: =IFERROR(__xludf.DUMMYFUNCTION("""COMPUTED_VALUE"""),"Basic Healing Potion") -> Basic Healing Potion | N13: =IFERROR(__xludf.DUMMYFUNCTION("""COMPUTED_VALUE"""),"Choose one of the following Effects to apply to the Target. A Combatant cannot be Targeted by a ‘Healing Potion’ more than once per Scene. [Throwable] [Small] [Consumable] » They restore 3 Ticks of Hit Points or 50 HP, whichever is higher. » They are cu"&"red of 1 Status Affliction of your choice. » They are revived and set to 1 Tick of Hit Points or 20 Hit Points, whichever is higher.") -> Choose one of the following Effects to apply to the Target. A Combatant cannot be Targeted by a ‘Healing Potion’ more than once per Scene. [Throwable] [Small] [Consumable] » They restore 3 Ticks of Hit Points or 50 HP, whichever is higher. » They are cured of 1 Status Affliction of your choice. » They are revived and set to 1 Tick of Hit Points or 20 Hit Points, whichever is higher.
K14: =IFERROR(__xludf.DUMMYFUNCTION("""COMPUTED_VALUE"""),"Leftovers") -> Leftovers | L14: =IFERROR(__xludf.DUMMYFUNCTION("""COMPUTED_VALUE"""),"While this Item is Equipped, as a Swift+Movement Action, the user may gain a Tick of Temporary Hit Points or restore a Tick of Hit Points [Medium] [Equipment] [Pokemon]") -> While this Item is Equipped, as a Swift+Movement Action, the user may gain a Tick of Temporary Hit Points or restore a Tick of Hit Points [Medium] [Equipment] [Pokemon] | M14: =IFERROR(__xludf.DUMMYFUNCTION("""COMPUTED_VALUE"""),"Basic Healing Potion [Lethality]") -> Basic Healing Potion [Lethality] | N14: =IFERROR(__xludf.DUMMYFUNCTION("""COMPUTED_VALUE"""),"Choose one of the following Effects to apply to the Target. A Combatant cannot be Targeted by a ‘Healing Potion’ more than once per Scene. [Throwable] [Small] [Consumable] » They restore 3 Ticks of Hit Points or 50 HP, whichever is higher. » They are cure"&"d of 1 Status Affliction of your choice. » They are revived and set to 1 Tick of Hit Points or 20 Hit Points, whichever is higher. » They are cured of one Wound (Max 2 per Day - Extended Action only)") -> Choose one of the following Effects to apply to the Target. A Combatant cannot be Targeted by a ‘Healing Potion’ more than once per Scene. [Throwable] [Small] [Consumable] » They restore 3 Ticks of Hit Points or 50 HP, whichever is higher. » They are cured of 1 Status Affliction of your choice. » They are revived and set to 1 Tick of Hit Points or 20 Hit Points, whichever is higher. » They are cured of one Wound (Max 2 per Day - Extended Action only)
K15: =IFERROR(__xludf.DUMMYFUNCTION("""COMPUTED_VALUE"""),"Lucky Charm") -> Lucky Charm | L15: =IFERROR(__xludf.DUMMYFUNCTION("""COMPUTED_VALUE"""),"While this Item is Equipped, the user rerolls any Accuracy Roll that was a natural 1. [Equipment] [Medium] [Pokemon]") -> While this Item is Equipped, the user rerolls any Accuracy Roll that was a natural 1. [Equipment] [Medium] [Pokemon] | M15: =IFERROR(__xludf.DUMMYFUNCTION("""COMPUTED_VALUE"""),"Basic Malady Potion (Burned)") -> Basic Malady Potion (Burned) | N15: =IFERROR(__xludf.DUMMYFUNCTION("""COMPUTED_VALUE"""),"The Target hit by this Item becomes Burned. [Throwable] [Small] [Consumable]") -> The Target hit by this Item becomes Burned. [Throwable] [Small] [Consumable]
K16: =IFERROR(__xludf.DUMMYFUNCTION("""COMPUTED_VALUE"""),"Mega Stone") -> Mega Stone | L16: =IFERROR(__xludf.DUMMYFUNCTION("""COMPUTED_VALUE"""),"When this Item is created, choose a Pokemon and an Ability on their Dex List. While Equipped by a Pokemon, the user may shift into their Mega form as a Swift Action. When they do so, they gain +1 CS in a Stat of their choice, then gain the chosen Ability "&"until the end of the Scene. The user may not shift into their Mega Form during the Turn they used a Damaging Attack and they cannot use a Damaging Attatck for the rest of the Turn once they do shift into their Mega Form. [Medium] [Pokemon]") -> When this Item is created, choose a Pokemon and an Ability on their Dex List. While Equipped by a Pokemon, the user may shift into their Mega form as a Swift Action. When they do so, they gain +1 CS in a Stat of their choice, then gain the chosen Ability until the end of the Scene. The user may not shift into their Mega Form during the Turn they used a Damaging Attack and they cannot use a Damaging Attatck for the rest of the Turn once they do shift into their Mega Form. [Medium] [Pokemon] | M16: =IFERROR(__xludf.DUMMYFUNCTION("""COMPUTED_VALUE"""),"Basic Malady Potion (Enraged)") -> Basic Malady Potion (Enraged) | N16: =IFERROR(__xludf.DUMMYFUNCTION("""COMPUTED_VALUE"""),"The Target hit by this Item becomes Enraged. [Throwable] [Small] [Consumable]") -> The Target hit by this Item becomes Enraged. [Throwable] [Small] [Consumable]
K17: =IFERROR(__xludf.DUMMYFUNCTION("""COMPUTED_VALUE"""),"Pokemon Saddle") -> Pokemon Saddle | L17: =IFERROR(__xludf.DUMMYFUNCTION("""COMPUTED_VALUE"""),"While this Item is Equipped, the user gains the Mountable Capability. This Item may only be equipped by Pokemon that are Medium Size or Larger and with GM Approval and it may only be equipped by Pokemon. If this Item is Impaired, anyone currently Mounting"&" the user becomes unmounted and Tripped unless they pass a Standard CR (2) Acrobatics Check [Equipment] [Large] [Pokemon] ") -> While this Item is Equipped, the user gains the Mountable Capability. This Item may only be equipped by Pokemon that are Medium Size or Larger and with GM Approval and it may only be equipped by Pokemon. If this Item is Impaired, anyone currently Mounting the user becomes unmounted and Tripped unless they pass a Standard CR (2) Acrobatics Check [Equipment] [Large] [Pokemon] | M17: =IFERROR(__xludf.DUMMYFUNCTION("""COMPUTED_VALUE"""),"Basic Malady Potion (Entranced)") -> Basic Malady Potion (Entranced) | N17: =IFERROR(__xludf.DUMMYFUNCTION("""COMPUTED_VALUE"""),"The Target hit by this Item becomes Entranced. [Throwable] [Small] [Consumable]") -> The Target hit by this Item becomes Entranced. [Throwable] [Small] [Consumable]
K18: =IFERROR(__xludf.DUMMYFUNCTION("""COMPUTED_VALUE"""),"Precision Lens") -> Precision Lens | L18: =IFERROR(__xludf.DUMMYFUNCTION("""COMPUTED_VALUE"""),"While this Item is Equipped, the user has +2 to Accuracy. [Equipment] [Medium] [Pokemon]") -> While this Item is Equipped, the user has +2 to Accuracy. [Equipment] [Medium] [Pokemon] | M18: =IFERROR(__xludf.DUMMYFUNCTION("""COMPUTED_VALUE"""),"Basic Malady Potion (Poisoned)") -> Basic Malady Potion (Poisoned) | N18: =IFERROR(__xludf.DUMMYFUNCTION("""COMPUTED_VALUE"""),"The Target hit by this Item becomes Poisoned. [Throwable] [Small] [Consumable]") -> The Target hit by this Item becomes Poisoned. [Throwable] [Small] [Consumable]
K19: =IFERROR(__xludf.DUMMYFUNCTION("""COMPUTED_VALUE"""),"Psionic Vest") -> Psionic Vest | L19: =IFERROR(__xludf.DUMMYFUNCTION("""COMPUTED_VALUE"""),"While this Item is Equipped, the user gains a TIck of Temporary Hit Points whenever they're hit by a Special Atack after Damage Calculations [Equipment - Armor] [[Large] [Pokemon]") -> While this Item is Equipped, the user gains a TIck of Temporary Hit Points whenever they're hit by a Special Atack after Damage Calculations [Equipment - Armor] [[Large] [Pokemon] | M19: =IFERROR(__xludf.DUMMYFUNCTION("""COMPUTED_VALUE"""),"Basic Malady Potion (Suppressed)") -> Basic Malady Potion (Suppressed) | N19: =IFERROR(__xludf.DUMMYFUNCTION("""COMPUTED_VALUE"""),"The Target hit by this Item becomes Suppressed. [Throwable] [Small] [Consumable]") -> The Target hit by this Item becomes Suppressed. [Throwable] [Small] [Consumable]
K20: =IFERROR(__xludf.DUMMYFUNCTION("""COMPUTED_VALUE"""),"Quick Boots") -> Quick Boots | L20: =IFERROR(__xludf.DUMMYFUNCTION("""COMPUTED_VALUE"""),"While this Item is Equipped, the user has +2 to their Movement Value and may perform their Turn at the start of each Round, regardless of which Party goes first. If multiple Combatants would have this effect, perform a Luck Check plus your Speed to determ"&"ine who goes first that Round, while the rest cannot apply this Effect. [Equipment] [Medium] [Pokemon]") -> While this Item is Equipped, the user has +2 to their Movement Value and may perform their Turn at the start of each Round, regardless of which Party goes first. If multiple Combatants would have this effect, perform a Luck Check plus your Speed to determine who goes first that Round, while the rest cannot apply this Effect. [Equipment] [Medium] [Pokemon] | M20: =IFERROR(__xludf.DUMMYFUNCTION("""COMPUTED_VALUE"""),"Basic Malady Potion (Wounded)") -> Basic Malady Potion (Wounded) | N20: =IFERROR(__xludf.DUMMYFUNCTION("""COMPUTED_VALUE"""),"The Target hit by this Item becomes Wounded. [Throwable] [Small] [Consumable]") -> The Target hit by this Item becomes Wounded. [Throwable] [Small] [Consumable]
K21: =IFERROR(__xludf.DUMMYFUNCTION("""COMPUTED_VALUE"""),"Quick Claw") -> Quick Claw | L21: =IFERROR(__xludf.DUMMYFUNCTION("""COMPUTED_VALUE"""),"While this Item is Equipped, whenever the Dash Keyword is Activated by the user, Enemies that weren’t Targeted cannot use Reactions against the Triggering Attack. [Equipment] [Small] [Pokemon]") -> While this Item is Equipped, whenever the Dash Keyword is Activated by the user, Enemies that weren’t Targeted cannot use Reactions against the Triggering Attack. [Equipment] [Small] [Pokemon] | M21: =IFERROR(__xludf.DUMMYFUNCTION("""COMPUTED_VALUE"""),"Basic Malady Potion (X)") -> Basic Malady Potion (X) | N21: =IFERROR(__xludf.DUMMYFUNCTION("""COMPUTED_VALUE"""),"Basic Malady Potions come in different variations which are determined by the GM. The Target hit by this Item gains the corresponding Status Affliction. Basic Malady Potions can inflict the following Afflictions. Burned, Poisoned, Enraged, Entranced, Supp"&"ressed, Wounded. [Throwable] [Small] [Consumable]") -> Basic Malady Potions come in different variations which are determined by the GM. The Target hit by this Item gains the corresponding Status Affliction. Basic Malady Potions can inflict the following Afflictions. Burned, Poisoned, Enraged, Entranced, Suppressed, Wounded. [Throwable] [Small] [Consumable]
K22: =IFERROR(__xludf.DUMMYFUNCTION("""COMPUTED_VALUE"""),"Razor Claw") -> Razor Claw | L22: =IFERROR(__xludf.DUMMYFUNCTION("""COMPUTED_VALUE"""),"While this Item is Equipped, the User's Melee Attacks are treated as having the Pass Keyword. [Equipment] [Medium] [Pokemon]") -> While this Item is Equipped, the User's Melee Attacks are treated as having the Pass Keyword. [Equipment] [Medium] [Pokemon] | M22: =IFERROR(__xludf.DUMMYFUNCTION("""COMPUTED_VALUE"""),"Basic Pokefood") -> Basic Pokefood | N22: =IFERROR(__xludf.DUMMYFUNCTION("""COMPUTED_VALUE"""),"If expended with a Throw Maneuver, choose an unoccupied Space for the food to land. All Enemy Pokemon within 3m of it must pass a Focus Check with a Tough CR (3). If any fail, one of them will use their next Standard Action to move to that space and eat i"&"t. If it wouldn’t make sense to logically move there (Such as being on a hazard), or the Pokemon has been tricked before in this Scene, the CR is reduced at GM Discretion. [Throwable] [Small] [Consumable]") -> If expended with a Throw Maneuver, choose an unoccupied Space for the food to land. All Enemy Pokemon within 3m of it must pass a Focus Check with a Tough CR (3). If any fail, one of them will use their next Standard Action to move to that space and eat it. If it wouldn’t make sense to logically move there (Such as being on a hazard), or the Pokemon has been tricked before in this Scene, the CR is reduced at GM Discretion. [Throwable] [Small] [Consumable]
K23: =IFERROR(__xludf.DUMMYFUNCTION("""COMPUTED_VALUE"""),"Revenge Band") -> Revenge Band | L23: =IFERROR(__xludf.DUMMYFUNCTION("""COMPUTED_VALUE"""),"While this Item is Equipped, the user has +3 DB to Attacks that Target Enemies that Targeted them last Round. [Equipment] [Medium] [Pokemon]") -> While this Item is Equipped, the user has +3 DB to Attacks that Target Enemies that Targeted them last Round. [Equipment] [Medium] [Pokemon] | M23: =IFERROR(__xludf.DUMMYFUNCTION("""COMPUTED_VALUE"""),"Basic Strength Potion (Accuracy)") -> Basic Strength Potion (Accuracy) | N23: =IFERROR(__xludf.DUMMYFUNCTION("""COMPUTED_VALUE"""),"The Target gains a +2 Modifier to Accuracy for the rest of the Scene. [Throwable] [Small] [Consumable]") -> The Target gains a +2 Modifier to Accuracy for the rest of the Scene. [Throwable] [Small] [Consumable]
K24: =IFERROR(__xludf.DUMMYFUNCTION("""COMPUTED_VALUE"""),"Rocky Helmet") -> Rocky Helmet | L24: =IFERROR(__xludf.DUMMYFUNCTION("""COMPUTED_VALUE"""),"While this Item is Equipped, whenever the user is Targeted by a Melee Attack, the Attacker loses a Tick of Hit Points. [Equipment - Armor] [Large] [Pokemon]") -> While this Item is Equipped, whenever the user is Targeted by a Melee Attack, the Attacker loses a Tick of Hit Points. [Equipment - Armor] [Large] [Pokemon] | M24: =IFERROR(__xludf.DUMMYFUNCTION("""COMPUTED_VALUE"""),"Basic Strength Potion (Attack)") -> Basic Strength Potion (Attack) | N24: =IFERROR(__xludf.DUMMYFUNCTION("""COMPUTED_VALUE"""),"The Target gains +2 CS in Attack. [Throwable] [Small] [Consumable]") -> The Target gains +2 CS in Attack. [Throwable] [Small] [Consumable]
K25: =IFERROR(__xludf.DUMMYFUNCTION("""COMPUTED_VALUE"""),"Scope Lens") -> Scope Lens | L25: =IFERROR(__xludf.DUMMYFUNCTION("""COMPUTED_VALUE"""),"While this Item is Equipped, the user has +1 to Critical Hit Ranges. [Equipment] [Medium] [Pokemon]") -> While this Item is Equipped, the user has +1 to Critical Hit Ranges. [Equipment] [Medium] [Pokemon] | M25: =IFERROR(__xludf.DUMMYFUNCTION("""COMPUTED_VALUE"""),"Basic Strength Potion (Critical Hit)") -> Basic Strength Potion (Critical Hit) | N25: =IFERROR(__xludf.DUMMYFUNCTION("""COMPUTED_VALUE"""),"The Target gains a +2 Modifier to Critical Hit for the rest of the Scene. [Throwable] [Small] [Consumable]") -> The Target gains a +2 Modifier to Critical Hit for the rest of the Scene. [Throwable] [Small] [Consumable]
K26: =IFERROR(__xludf.DUMMYFUNCTION("""COMPUTED_VALUE"""),"Small Gadget") -> Small Gadget | L26: =IFERROR(__xludf.DUMMYFUNCTION("""COMPUTED_VALUE"""),"When this Item is created, the GM will determine what the effect of the Gadget is upon usage. If it grants a Capability, such as through the Tech Researcher Class, it lasts until the end of a Session or Scene, whichever is longer. [Consumable] [Medium] [P"&"okemon]") -> When this Item is created, the GM will determine what the effect of the Gadget is upon usage. If it grants a Capability, such as through the Tech Researcher Class, it lasts until the end of a Session or Scene, whichever is longer. [Consumable] [Medium] [Pokemon] | M26: =IFERROR(__xludf.DUMMYFUNCTION("""COMPUTED_VALUE"""),"Basic Strength Potion (Special Attack)") -> Basic Strength Potion (Special Attack) | N26: =IFERROR(__xludf.DUMMYFUNCTION("""COMPUTED_VALUE"""),"The Target gains +2 CS in Special Attack. [Throwable] [Small] [Consumable]") -> The Target gains +2 CS in Special Attack. [Throwable] [Small] [Consumable]
K27: =IFERROR(__xludf.DUMMYFUNCTION("""COMPUTED_VALUE"""),"Stat Booster (Attack)") -> Stat Booster (Attack) | L27: =IFERROR(__xludf.DUMMYFUNCTION("""COMPUTED_VALUE"""),"While this Item is Equipped, the user's Default Attack CS Value is set to +1 CS. [Equipment] [Large] [Pokemon]") -> While this Item is Equipped, the user's Default Attack CS Value is set to +1 CS. [Equipment] [Large] [Pokemon] | M27: =IFERROR(__xludf.DUMMYFUNCTION("""COMPUTED_VALUE"""),"Basic Strength Potion (X)") -> Basic Strength Potion (X) | N27: =IFERROR(__xludf.DUMMYFUNCTION("""COMPUTED_VALUE"""),"Basic Strength Potions come in different Variations which are determined by the GM. X May be Attack, Special Attack, Critical Hit or Accuracy. If X is Attack or Special Attack, the Target gains +2 CS in that Stat. If X is Critical Hit or Accuracy, they ga"&"in a +2 Modifier to that Combat Value for the rest of the Scene. [Throwable] [Small] [Consumable]") -> Basic Strength Potions come in different Variations which are determined by the GM. X May be Attack, Special Attack, Critical Hit or Accuracy. If X is Attack or Special Attack, the Target gains +2 CS in that Stat. If X is Critical Hit or Accuracy, they gain a +2 Modifier to that Combat Value for the rest of the Scene. [Throwable] [Small] [Consumable]
K28: =IFERROR(__xludf.DUMMYFUNCTION("""COMPUTED_VALUE"""),"Stat Booster (Defense)") -> Stat Booster (Defense) | L28: =IFERROR(__xludf.DUMMYFUNCTION("""COMPUTED_VALUE"""),"While this Item is Equipped, the user's Default Defense CS Value is set to +1 CS. [Equipment] [Large] [Pokemon]") -> While this Item is Equipped, the user's Default Defense CS Value is set to +1 CS. [Equipment] [Large] [Pokemon] | M28: =IFERROR(__xludf.DUMMYFUNCTION("""COMPUTED_VALUE"""),"Basic Vitality Potion (Defense)") -> Basic Vitality Potion (Defense) | N28: =IFERROR(__xludf.DUMMYFUNCTION("""COMPUTED_VALUE"""),"The Target gains +2 CS in Defense. [Throwable] [Small] [Consumable]") -> The Target gains +2 CS in Defense. [Throwable] [Small] [Consumable]
K29: =IFERROR(__xludf.DUMMYFUNCTION("""COMPUTED_VALUE"""),"Stat Booster (Special Attack)") -> Stat Booster (Special Attack) | L29: =IFERROR(__xludf.DUMMYFUNCTION("""COMPUTED_VALUE"""),"While this Item is Equipped, the user's Default Special Attack CS Value is set to +1 CS. [Equipment] [Large] [Pokemon]") -> While this Item is Equipped, the user's Default Special Attack CS Value is set to +1 CS. [Equipment] [Large] [Pokemon] | M29: =IFERROR(__xludf.DUMMYFUNCTION("""COMPUTED_VALUE"""),"Basic Vitality Potion (Evasion)") -> Basic Vitality Potion (Evasion) | N29: =IFERROR(__xludf.DUMMYFUNCTION("""COMPUTED_VALUE"""),"The Target gains a +3 Modifier to Evasion for the rest of the Scene. [Throwable] [Small] [Consumable]") -> The Target gains a +3 Modifier to Evasion for the rest of the Scene. [Throwable] [Small] [Consumable]
K30: =IFERROR(__xludf.DUMMYFUNCTION("""COMPUTED_VALUE"""),"Stat Booster (Special Defense)") -> Stat Booster (Special Defense) | L30: =IFERROR(__xludf.DUMMYFUNCTION("""COMPUTED_VALUE"""),"While this Item is Equipped, the user's Default Special Defense CS Value is set to +1 CS. [Equipment] [Large] [Pokemon]") -> While this Item is Equipped, the user's Default Special Defense CS Value is set to +1 CS. [Equipment] [Large] [Pokemon] | M30: =IFERROR(__xludf.DUMMYFUNCTION("""COMPUTED_VALUE"""),"Basic Vitality Potion (Save Checks)") -> Basic Vitality Potion (Save Checks) | N30: =IFERROR(__xludf.DUMMYFUNCTION("""COMPUTED_VALUE"""),"The Target gains a +2 Modifier to Save Checks for the rest of the Scene. [Throwable] [Small] [Consumable]") -> The Target gains a +2 Modifier to Save Checks for the rest of the Scene. [Throwable] [Small] [Consumable]
K31: =IFERROR(__xludf.DUMMYFUNCTION("""COMPUTED_VALUE"""),"Stat Booster (Speed)") -> Stat Booster (Speed) | L31: =IFERROR(__xludf.DUMMYFUNCTION("""COMPUTED_VALUE"""),"While this Item is Equipped, the user's Default Speed CS Value is set to +1 CS. [Equipment] [Large] [Pokemon]") -> While this Item is Equipped, the user's Default Speed CS Value is set to +1 CS. [Equipment] [Large] [Pokemon] | M31: =IFERROR(__xludf.DUMMYFUNCTION("""COMPUTED_VALUE"""),"Basic Vitality Potion (Special Defense)") -> Basic Vitality Potion (Special Defense) | N31: =IFERROR(__xludf.DUMMYFUNCTION("""COMPUTED_VALUE"""),"The Target gains +2 CS in Special Defense. [Throwable] [Small] [Consumable]") -> The Target gains +2 CS in Special Defense. [Throwable] [Small] [Consumable]
K32: =IFERROR(__xludf.DUMMYFUNCTION("""COMPUTED_VALUE"""),"Stat Booster (X)") -> Stat Booster (X) | L32: =IFERROR(__xludf.DUMMYFUNCTION("""COMPUTED_VALUE"""),"When this Item is created, choose a Stat other than HP to determine the value for X. While this Item is Equipped, the user's Default CS Value for the Stat of X is set to +1 CS. [Equipment] [Large] [Pokemon]") -> When this Item is created, choose a Stat other than HP to determine the value for X. While this Item is Equipped, the user's Default CS Value for the Stat of X is set to +1 CS. [Equipment] [Large] [Pokemon] | M32: =IFERROR(__xludf.DUMMYFUNCTION("""COMPUTED_VALUE"""),"Basic Vitality Potion (X)") -> Basic Vitality Potion (X) | N32: =IFERROR(__xludf.DUMMYFUNCTION("""COMPUTED_VALUE"""),"Basic Strength Potions come in different Variations which are determined by the GM. X May be Defense, Special Defense, Evasion or Save Checks. If X is Defense or Special Defense, the Target gains +2 CS in that Stat. If X is Evasion, they gain a +3 Bonus t"&"o Evasion for the rest of the Scene. If X is Save Checks, they gain a +2 Modifier to that Combat Value for the rest of the Scene. [Throwable] [Small] [Consumable]") -> Basic Strength Potions come in different Variations which are determined by the GM. X May be Defense, Special Defense, Evasion or Save Checks. If X is Defense or Special Defense, the Target gains +2 CS in that Stat. If X is Evasion, they gain a +3 Bonus to Evasion for the rest of the Scene. If X is Save Checks, they gain a +2 Modifier to that Combat Value for the rest of the Scene. [Throwable] [Small] [Consumable]
K33: =IFERROR(__xludf.DUMMYFUNCTION("""COMPUTED_VALUE"""),"Status Guard (Burned)") -> Status Guard (Burned) | L33: =IFERROR(__xludf.DUMMYFUNCTION("""COMPUTED_VALUE"""),"While this Item is Equipped, the user's is Immune to being Burned. If it were to be inflicted by a Boss, the user has to pass a TN 8 Save Check or else they become Afflicted by it. [Equipment] [Medium] [Pokemon]") -> While this Item is Equipped, the user's is Immune to being Burned. If it were to be inflicted by a Boss, the user has to pass a TN 8 Save Check or else they become Afflicted by it. [Equipment] [Medium] [Pokemon] | M33: =IFERROR(__xludf.DUMMYFUNCTION("""COMPUTED_VALUE"""),"Berserk Belt") -> Berserk Belt | N33: =IFERROR(__xludf.DUMMYFUNCTION("""COMPUTED_VALUE"""),"While this Item is Equipped, whenever the user causes an Enemy to faint via a Damaging Attack, they gain +1 CS to Attack or Special Attack. [Equipment] [Medium] [Pokemon]") -> While this Item is Equipped, whenever the user causes an Enemy to faint via a Damaging Attack, they gain +1 CS to Attack or Special Attack. [Equipment] [Medium] [Pokemon]
K34: =IFERROR(__xludf.DUMMYFUNCTION("""COMPUTED_VALUE"""),"Status Guard (Chilled)") -> Status Guard (Chilled) | L34: =IFERROR(__xludf.DUMMYFUNCTION("""COMPUTED_VALUE"""),"While this Item is Equipped, the user's is Immune to being Chilled. If it were to be inflicted by a Boss, the user has to pass a TN 8 Save Check or else they become Afflicted by it. [Equipment] [Medium] [Pokemon]") -> While this Item is Equipped, the user's is Immune to being Chilled. If it were to be inflicted by a Boss, the user has to pass a TN 8 Save Check or else they become Afflicted by it. [Equipment] [Medium] [Pokemon] | M34: =IFERROR(__xludf.DUMMYFUNCTION("""COMPUTED_VALUE"""),"Blessed Relic") -> Blessed Relic | N34: =IFERROR(__xludf.DUMMYFUNCTION("""COMPUTED_VALUE"""),"While this Item is Equipped, the user has +2 to Save Checks. [Equipment] [Medium] [Pokemon]") -> While this Item is Equipped, the user has +2 to Save Checks. [Equipment] [Medium] [Pokemon]
K35: =IFERROR(__xludf.DUMMYFUNCTION("""COMPUTED_VALUE"""),"Status Guard (Cursed)") -> Status Guard (Cursed) | L35: =IFERROR(__xludf.DUMMYFUNCTION("""COMPUTED_VALUE"""),"While this Item is Equipped, the user's is Immune to being Cursed. If it were to be inflicted by a Boss, the user has to pass a TN 8 Save Check or else they become Afflicted by it. [Equipment] [Medium] [Pokemon]") -> While this Item is Equipped, the user's is Immune to being Cursed. If it were to be inflicted by a Boss, the user has to pass a TN 8 Save Check or else they become Afflicted by it. [Equipment] [Medium] [Pokemon] | M35: =IFERROR(__xludf.DUMMYFUNCTION("""COMPUTED_VALUE"""),"Blue Shard") -> Blue Shard | N35: =IFERROR(__xludf.DUMMYFUNCTION("""COMPUTED_VALUE"""),"This Item can be expended as a Free Action in the user's Inventory upon hitting a Flying, Ice or Water Type Damaging Attack to increase its Damage Base by +3. The user may only expend one Shard Item per Attack. [Small] [Consumable] [Pokemon]") -> This Item can be expended as a Free Action in the user's Inventory upon hitting a Flying, Ice or Water Type Damaging Attack to increase its Damage Base by +3. The user may only expend one Shard Item per Attack. [Small] [Consumable] [Pokemon]
K36: =IFERROR(__xludf.DUMMYFUNCTION("""COMPUTED_VALUE"""),"Status Guard (Dazed)") -> Status Guard (Dazed) | L36: =IFERROR(__xludf.DUMMYFUNCTION("""COMPUTED_VALUE"""),"While this Item is Equipped, the user's is Immune to being Dazed. If it were to be inflicted by a Boss, the user has to pass a TN 8 Save Check or else they become Afflicted by it. [Equipment] [Medium] [Pokemon]") -> While this Item is Equipped, the user's is Immune to being Dazed. If it were to be inflicted by a Boss, the user has to pass a TN 8 Save Check or else they become Afflicted by it. [Equipment] [Medium] [Pokemon] | M36: =IFERROR(__xludf.DUMMYFUNCTION("""COMPUTED_VALUE"""),"Bolstering Rune [Occult]") -> Bolstering Rune [Occult] | N36: =IFERROR(__xludf.DUMMYFUNCTION("""COMPUTED_VALUE"""),"Cost: 1 Counter Effect: Target an Ally within 3m and pick an effect to apply. They are cured of a Status Affliction. They gain two Ticks of Temporary Hit Points. They have a Stat at or below Default CS Value increased by +2. They have a Coat removed from "&"them. This can only be used by a Rune Master [Small] [Consumable] Advanced: You may choose to either Target all Allies within a 3x3 Zone that can be created within 5m; or pick two Effects to apply to the Target.") -> Cost: 1 Counter Effect: Target an Ally within 3m and pick an effect to apply. They are cured of a Status Affliction. They gain two Ticks of Temporary Hit Points. They have a Stat at or below Default CS Value increased by +2. They have a Coat removed from them. This can only be used by a Rune Master [Small] [Consumable] Advanced: You may choose to either Target all Allies within a 3x3 Zone that can be created within 5m; or pick two Effects to apply to the Target.
K37: =IFERROR(__xludf.DUMMYFUNCTION("""COMPUTED_VALUE"""),"Status Guard (Disabled)") -> Status Guard (Disabled) | L37: =IFERROR(__xludf.DUMMYFUNCTION("""COMPUTED_VALUE"""),"While this Item is Equipped, the user's is Immune to being Disabled. If it were to be inflicted by a Boss, the user has to pass a TN 8 Save Check or else they become Afflicted by it. [Equipment] [Medium] [Pokemon]") -> While this Item is Equipped, the user's is Immune to being Disabled. If it were to be inflicted by a Boss, the user has to pass a TN 8 Save Check or else they become Afflicted by it. [Equipment] [Medium] [Pokemon] | M37: =IFERROR(__xludf.DUMMYFUNCTION("""COMPUTED_VALUE"""),"Book") -> Book | N37: =IFERROR(__xludf.DUMMYFUNCTION("""COMPUTED_VALUE"""),"When this Item is created, the GM will determine the effect of the book and its associated Skill that is used to read it. This Item may be studied as a Research Downtime Action with the Target Number determined by the GM. When the Downtime Project is fini"&"shed, the Player will learn the contents of the book, leading to either information gained or a permanent boost to your Character, such as gaining a Specialty as if they had the Skill Specialty Talent. [Small]") -> When this Item is created, the GM will determine the effect of the book and its associated Skill that is used to read it. This Item may be studied as a Research Downtime Action with the Target Number determined by the GM. When the Downtime Project is finished, the Player will learn the contents of the book, leading to either information gained or a permanent boost to your Character, such as gaining a Specialty as if they had the Skill Specialty Talent. [Small]
K38: =IFERROR(__xludf.DUMMYFUNCTION("""COMPUTED_VALUE"""),"Status Guard (Drowsy)") -> Status Guard (Drowsy) | L38: =IFERROR(__xludf.DUMMYFUNCTION("""COMPUTED_VALUE"""),"While this Item is Equipped, the user's is Immune to being Drowsy. If it were to be inflicted by a Boss, the user has to pass a TN 8 Save Check or else they become Afflicted by it. [Equipment] [Medium] [Pokemon]") -> While this Item is Equipped, the user's is Immune to being Drowsy. If it were to be inflicted by a Boss, the user has to pass a TN 8 Save Check or else they become Afflicted by it. [Equipment] [Medium] [Pokemon] | M38: =IFERROR(__xludf.DUMMYFUNCTION("""COMPUTED_VALUE"""),"Braced Shield") -> Braced Shield | N38: =IFERROR(__xludf.DUMMYFUNCTION("""COMPUTED_VALUE"""),"While Equipped, whenever the user uses a Defend Maneuver, the Target has Damage Reduction equal to your Tier Value for the duration of the Maneuver. If the Target is no longer Adjacent to you, they do not benefit from this Effect [Medium] [Equipment - Wea"&"pon]") -> While Equipped, whenever the user uses a Defend Maneuver, the Target has Damage Reduction equal to your Tier Value for the duration of the Maneuver. If the Target is no longer Adjacent to you, they do not benefit from this Effect [Medium] [Equipment - Weapon]
K39: =IFERROR(__xludf.DUMMYFUNCTION("""COMPUTED_VALUE"""),"Status Guard (Enraged)") -> Status Guard (Enraged) | L39: =IFERROR(__xludf.DUMMYFUNCTION("""COMPUTED_VALUE"""),"While this Item is Equipped, the user's is Immune to being Enraged. If it were to be inflicted by a Boss, the user has to pass a TN 8 Save Check or else they become Afflicted by it. [Equipment] [Medium] [Pokemon]") -> While this Item is Equipped, the user's is Immune to being Enraged. If it were to be inflicted by a Boss, the user has to pass a TN 8 Save Check or else they become Afflicted by it. [Equipment] [Medium] [Pokemon] | M39: =IFERROR(__xludf.DUMMYFUNCTION("""COMPUTED_VALUE"""),"Burst Heart [Occult]") -> Burst Heart [Occult] | N39: =IFERROR(__xludf.DUMMYFUNCTION("""COMPUTED_VALUE"""),"Effect: This is a crystalline object that can capture a Fainted or Willing Pokemon, putting them in a stasis similar to a Pokeball. The Pokemon inside cannot be released from this Item unless it is destroyed. The Pokemon inside gains the Telepath Capabili"&"ty but can only communicate with their holder, and vice versa. For each Burst Heart a Trainer has in their Inventory or Equipped, their Pokemon Party size is reduced by -1. The Pokemon contained in this Item has its own Stat Sheet that must be tracked and"&" they may Level Up as normal. The contained Pokemon may allow another creature to enter their Burst Heart and interact with them normally, such as Training them or teaching them Tutor Attacks. This Item cannot be Disarmed if the holder is in their associa"&"ted Burst Form. [Large] [Equipment]") -> Effect: This is a crystalline object that can capture a Fainted or Willing Pokemon, putting them in a stasis similar to a Pokeball. The Pokemon inside cannot be released from this Item unless it is destroyed. The Pokemon inside gains the Telepath Capability but can only communicate with their holder, and vice versa. For each Burst Heart a Trainer has in their Inventory or Equipped, their Pokemon Party size is reduced by -1. The Pokemon contained in this Item has its own Stat Sheet that must be tracked and they may Level Up as normal. The contained Pokemon may allow another creature to enter their Burst Heart and interact with them normally, such as Training them or teaching them Tutor Attacks. This Item cannot be Disarmed if the holder is in their associated Burst Form. [Large] [Equipment]
K40: =IFERROR(__xludf.DUMMYFUNCTION("""COMPUTED_VALUE"""),"Status Guard (Entranced)") -> Status Guard (Entranced) | L40: =IFERROR(__xludf.DUMMYFUNCTION("""COMPUTED_VALUE"""),"While this Item is Equipped, the user's is Immune to being Entranced. If it were to be inflicted by a Boss, the user has to pass a TN 8 Save Check or else they become Afflicted by it. [Equipment] [Medium] [Pokemon]") -> While this Item is Equipped, the user's is Immune to being Entranced. If it were to be inflicted by a Boss, the user has to pass a TN 8 Save Check or else they become Afflicted by it. [Equipment] [Medium] [Pokemon] | M40: =IFERROR(__xludf.DUMMYFUNCTION("""COMPUTED_VALUE"""),"Caravan [Lethality]") -> Caravan [Lethality] | N40: =IFERROR(__xludf.DUMMYFUNCTION("""COMPUTED_VALUE"""),"This Item may be taken on a Journey and doesn’t take up an Inventory Slot. This Item has 20 Inventory Slots that can be filled with Items. In order to take this on a Journey, a Pokemon or Trainer must be the Primary Provisioner, whereas the total Power of"&" all Provisioners is 12 or higher. ") -> This Item may be taken on a Journey and doesn’t take up an Inventory Slot. This Item has 20 Inventory Slots that can be filled with Items. In order to take this on a Journey, a Pokemon or Trainer must be the Primary Provisioner, whereas the total Power of all Provisioners is 12 or higher.
K41: =IFERROR(__xludf.DUMMYFUNCTION("""COMPUTED_VALUE"""),"Status Guard (Paralyzed)") -> Status Guard (Paralyzed) | L41: =IFERROR(__xludf.DUMMYFUNCTION("""COMPUTED_VALUE"""),"While this Item is Equipped, the user's is Immune to being Paralyzed. If it were to be inflicted by a Boss, the user has to pass a TN 8 Save Check or else they become Afflicted by it. [Equipment] [Medium] [Pokemon]") -> While this Item is Equipped, the user's is Immune to being Paralyzed. If it were to be inflicted by a Boss, the user has to pass a TN 8 Save Check or else they become Afflicted by it. [Equipment] [Medium] [Pokemon] | M41: =IFERROR(__xludf.DUMMYFUNCTION("""COMPUTED_VALUE"""),"Cargo Bag") -> Cargo Bag | N41: =IFERROR(__xludf.DUMMYFUNCTION("""COMPUTED_VALUE"""),"While Equipped, the user has 4 Inventory Slots (Pokemon cannot use these Items). An adjacent Trainer may equip or use Items in these Slots as if they were in their own Inventory. Only Pokemon may equip this Item. Large Items cannot be put in these Slots i"&"f the user’s size is Small. [Large] [Pokemon] [Inventory 2]") -> While Equipped, the user has 4 Inventory Slots (Pokemon cannot use these Items). An adjacent Trainer may equip or use Items in these Slots as if they were in their own Inventory. Only Pokemon may equip this Item. Large Items cannot be put in these Slots if the user’s size is Small. [Large] [Pokemon] [Inventory 2]
K42: =IFERROR(__xludf.DUMMYFUNCTION("""COMPUTED_VALUE"""),"Status Guard (Poisoned)") -> Status Guard (Poisoned) | L42: =IFERROR(__xludf.DUMMYFUNCTION("""COMPUTED_VALUE"""),"While this Item is Equipped, the user's is Immune to being Poisoned. If it were to be inflicted by a Boss, the user has to pass a TN 8 Save Check or else they become Afflicted by it. [Equipment] [Medium] [Pokemon]") -> While this Item is Equipped, the user's is Immune to being Poisoned. If it were to be inflicted by a Boss, the user has to pass a TN 8 Save Check or else they become Afflicted by it. [Equipment] [Medium] [Pokemon] | M42: =IFERROR(__xludf.DUMMYFUNCTION("""COMPUTED_VALUE"""),"Climbing Kit") -> Climbing Kit | N42: =IFERROR(__xludf.DUMMYFUNCTION("""COMPUTED_VALUE"""),"While this Item is in your Inventory, you do not need to make any Skill Checks in order to climb or scale vertical surfaces such as a slope. This may be equipped as if it were an [Equipment - Weapon] Item in order to ignore Movement Penalites from vertica"&"l surfaces that would be Slow Terrain. [Medium]") -> While this Item is in your Inventory, you do not need to make any Skill Checks in order to climb or scale vertical surfaces such as a slope. This may be equipped as if it were an [Equipment - Weapon] Item in order to ignore Movement Penalites from vertical surfaces that would be Slow Terrain. [Medium]
K43: =IFERROR(__xludf.DUMMYFUNCTION("""COMPUTED_VALUE"""),"Status Guard (Slowed)") -> Status Guard (Slowed) | L43: =IFERROR(__xludf.DUMMYFUNCTION("""COMPUTED_VALUE"""),"While this Item is Equipped, the user's is Immune to being Slowed. If it were to be inflicted by a Boss, the user has to pass a TN 8 Save Check or else they become Afflicted by it. [Equipment] [Medium] [Pokemon]") -> While this Item is Equipped, the user's is Immune to being Slowed. If it were to be inflicted by a Boss, the user has to pass a TN 8 Save Check or else they become Afflicted by it. [Equipment] [Medium] [Pokemon] | M43: =IFERROR(__xludf.DUMMYFUNCTION("""COMPUTED_VALUE"""),"Companion Ball") -> Companion Ball | N43: =IFERROR(__xludf.DUMMYFUNCTION("""COMPUTED_VALUE"""),"As an Extended Action, Target any Pokemon you own to become bound by the Companion Ball (Limit 1). While you have this Item in your Inventory, the Targeted Pokemon is considered to be in your Party, ignoring the Limit of 3 Pokemon in a Party. Pokemon boun"&"d by this Ball cannot be used in Combat in any way. You can only have one Companion Ball in your Inventory at a time. At your GM's Discretion, this Item could provide some small benefit based on the Pokemon inside. [Medium] ") -> As an Extended Action, Target any Pokemon you own to become bound by the Companion Ball (Limit 1). While you have this Item in your Inventory, the Targeted Pokemon is considered to be in your Party, ignoring the Limit of 3 Pokemon in a Party. Pokemon bound by this Ball cannot be used in Combat in any way. You can only have one Companion Ball in your Inventory at a time. At your GM's Discretion, this Item could provide some small benefit based on the Pokemon inside. [Medium]
K44: =IFERROR(__xludf.DUMMYFUNCTION("""COMPUTED_VALUE"""),"Status Guard (Suppressed)") -> Status Guard (Suppressed) | L44: =IFERROR(__xludf.DUMMYFUNCTION("""COMPUTED_VALUE"""),"While this Item is Equipped, the user's is Immune to being Suppressed. If it were to be inflicted by a Boss, the user has to pass a TN 8 Save Check or else they become Afflicted by it. [Equipment] [Medium] [Pokemon]") -> While this Item is Equipped, the user's is Immune to being Suppressed. If it were to be inflicted by a Boss, the user has to pass a TN 8 Save Check or else they become Afflicted by it. [Equipment] [Medium] [Pokemon] | M44: =IFERROR(__xludf.DUMMYFUNCTION("""COMPUTED_VALUE"""),"Covert Cloak") -> Covert Cloak | N44: =IFERROR(__xludf.DUMMYFUNCTION("""COMPUTED_VALUE"""),"While Equipped, Attacks against the user have a -2 Penalty to Effect Ranges. [Medium] [Equipment - Armor] [Pokemon]") -> While Equipped, Attacks against the user have a -2 Penalty to Effect Ranges. [Medium] [Equipment - Armor] [Pokemon]
K45: =IFERROR(__xludf.DUMMYFUNCTION("""COMPUTED_VALUE"""),"Status Guard (Wounded)") -> Status Guard (Wounded) | L45: =IFERROR(__xludf.DUMMYFUNCTION("""COMPUTED_VALUE"""),"While this Item is Equipped, the user's is Immune to being Wounded. If it were to be inflicted by a Boss, the user has to pass a TN 8 Save Check or else they become Afflicted by it. [Equipment] [Medium] [Pokemon]") -> While this Item is Equipped, the user's is Immune to being Wounded. If it were to be inflicted by a Boss, the user has to pass a TN 8 Save Check or else they become Afflicted by it. [Equipment] [Medium] [Pokemon] | M45: =IFERROR(__xludf.DUMMYFUNCTION("""COMPUTED_VALUE"""),"Crude Armor") -> Crude Armor | N45: =IFERROR(__xludf.DUMMYFUNCTION("""COMPUTED_VALUE"""),"While Equipped, the user has +5 Damage Reduction. [Medium] [Equipment - Armor]") -> While Equipped, the user has +5 Damage Reduction. [Medium] [Equipment - Armor]
K46: =IFERROR(__xludf.DUMMYFUNCTION("""COMPUTED_VALUE"""),"Status Guard (X)") -> Status Guard (X) | L46: =IFERROR(__xludf.DUMMYFUNCTION("""COMPUTED_VALUE"""),"When this Item is created, choose a Status Affliction to determine the value for X. While this Item is Equipped, the user's is Immune to the chosen Affliction. If it were to be inflicted by a Boss, the user has to pass a TN 8 Save Check or else they becom"&"e Afflicted by it. [Equipment] [Medium] [Pokemon]") -> When this Item is created, choose a Status Affliction to determine the value for X. While this Item is Equipped, the user's is Immune to the chosen Affliction. If it were to be inflicted by a Boss, the user has to pass a TN 8 Save Check or else they become Afflicted by it. [Equipment] [Medium] [Pokemon] | M46: =IFERROR(__xludf.DUMMYFUNCTION("""COMPUTED_VALUE"""),"Dampening Rune [Occult]") -> Dampening Rune [Occult] | N46: =IFERROR(__xludf.DUMMYFUNCTION("""COMPUTED_VALUE"""),"Cost: 1 Counters Effect: Target an Enemy within 3m and pick an effect to apply. An Enemy can only be affected by each Effect once per Scene. They have a Stat with Positive CS set to its Default Value. Their next Accuracy Roll or Save Check has a Penalty e"&"qual to double your Tier Level. They have a Coat removed from them. This can only be used by a Rune Master [Small] [Consumable] Advanced: You may choose to either Target all Enemies within a 3x3 Zone that can be created within 5m; or pick two Effects to a"&"pply to the Target.") -> Cost: 1 Counters Effect: Target an Enemy within 3m and pick an effect to apply. An Enemy can only be affected by each Effect once per Scene. They have a Stat with Positive CS set to its Default Value. Their next Accuracy Roll or Save Check has a Penalty equal to double your Tier Level. They have a Coat removed from them. This can only be used by a Rune Master [Small] [Consumable] Advanced: You may choose to either Target all Enemies within a 3x3 Zone that can be created within 5m; or pick two Effects to apply to the Target.
K47: =IFERROR(__xludf.DUMMYFUNCTION("""COMPUTED_VALUE"""),"Stylish Clothes") -> Stylish Clothes | L47: =IFERROR(__xludf.DUMMYFUNCTION("""COMPUTED_VALUE"""),"Upon purchasing or crafting, the GM will declare what Skill this Item affects. If the Item is [Small], you gain a +1d6 while performing a Skill Check associated with that Skill, but cannot exceed 6d6. If the Item is [Large], you may also choose a Specialt"&"y as if you took the Skill Specialty Talent. While equipped, you have a Boon in that Specialty. This cannot affect Skill Checks performed as a Downtime Action. [Small or Large] [Equipment] [Pokemon]") -> Upon purchasing or crafting, the GM will declare what Skill this Item affects. If the Item is [Small], you gain a +1d6 while performing a Skill Check associated with that Skill, but cannot exceed 6d6. If the Item is [Large], you may also choose a Specialty as if you took the Skill Specialty Talent. While equipped, you have a Boon in that Specialty. This cannot affect Skill Checks performed as a Downtime Action. [Small or Large] [Equipment] [Pokemon] | M47: =IFERROR(__xludf.DUMMYFUNCTION("""COMPUTED_VALUE"""),"Destruction Rune [Occult]") -> Destruction Rune [Occult] | N47: =IFERROR(__xludf.DUMMYFUNCTION("""COMPUTED_VALUE"""),"Cost: 1 or 3 Counters Effect: When used, the user may use the Hidden Power Attack. The user may expend 3 Shards of an associated Type to select what Type Hidden Power will be instead of rolling. If the Rune was created with 3 Counters, you may choose what"&" Type Hidden Power is. This can only be used by a Rune Master [Small] [Consumable] Advanced: You may choose to either pick the Type of Hidden Power without paying the cost; or change its range to one of the following: Burst 2. 6, Ranged Blast 2. Close Bla"&"st 3. Line 4") -> Cost: 1 or 3 Counters Effect: When used, the user may use the Hidden Power Attack. The user may expend 3 Shards of an associated Type to select what Type Hidden Power will be instead of rolling. If the Rune was created with 3 Counters, you may choose what Type Hidden Power is. This can only be used by a Rune Master [Small] [Consumable] Advanced: You may choose to either pick the Type of Hidden Power without paying the cost; or change its range to one of the following: Burst 2. 6, Ranged Blast 2. Close Blast 3. Line 4
K48: =IFERROR(__xludf.DUMMYFUNCTION("""COMPUTED_VALUE"""),"Terastral Crystal") -> Terastral Crystal | L48: =IFERROR(__xludf.DUMMYFUNCTION("""COMPUTED_VALUE"""),"When this Item is created, choose a Type. While Equipped by a Pokemon, once per Scene as a Swift Action they may remove their current Typings and they gain the chosen Type until the end of the Scene. Any Attack on their Attacks on their Battle List that m"&"atched their lost Type may be shifted to the Type they changed to if desired. For example, a Magnezone with a Fire Terrastral would lose the Electric/Steel Typing and turn into Fire Type, possibly changing Thunderbolt to Fire Type. [Medium] [Pokemon]") -> When this Item is created, choose a Type. While Equipped by a Pokemon, once per Scene as a Swift Action they may remove their current Typings and they gain the chosen Type until the end of the Scene. Any Attack on their Attacks on their Battle List that matched their lost Type may be shifted to the Type they changed to if desired. For example, a Magnezone with a Fire Terrastral would lose the Electric/Steel Typing and turn into Fire Type, possibly changing Thunderbolt to Fire Type. [Medium] [Pokemon] | M48: =IFERROR(__xludf.DUMMYFUNCTION("""COMPUTED_VALUE"""),"Disguise") -> Disguise | N48: =IFERROR(__xludf.DUMMYFUNCTION("""COMPUTED_VALUE"""),"If this Item is [Small], while Equipped, anyone who performs a Skill Check to discern your identity has a Bane on it. If this Item is [Large], while Equipped, you also roll an additional 1d6 to Skill Checks related to your False Identity. [Small or Large]"&" [Equipment]") -> If this Item is [Small], while Equipped, anyone who performs a Skill Check to discern your identity has a Bane on it. If this Item is [Large], while Equipped, you also roll an additional 1d6 to Skill Checks related to your False Identity. [Small or Large] [Equipment]
K49: =IFERROR(__xludf.DUMMYFUNCTION("""COMPUTED_VALUE"""),"Type Augmentor (Bug)") -> Type Augmentor (Bug) | L49: =IFERROR(__xludf.DUMMYFUNCTION("""COMPUTED_VALUE"""),"While this Item is Equipped, as a Swift Action, the user may change a Damaging Attack they know to become Bug Type for the rest of the Scene. [Equipment] [Large] [Pokemon]") -> While this Item is Equipped, as a Swift Action, the user may change a Damaging Attack they know to become Bug Type for the rest of the Scene. [Equipment] [Large] [Pokemon] | M49: =IFERROR(__xludf.DUMMYFUNCTION("""COMPUTED_VALUE"""),"Dodge Scarf") -> Dodge Scarf | N49: =IFERROR(__xludf.DUMMYFUNCTION("""COMPUTED_VALUE"""),"While this Item is Equipped, the user has a bonus to Evasion equal to their Tier Level. As a Reaction + Movement Action, they may treat this bonus as Uncapped until the start of their next Turn. [Equipment] [Large] [Pokemon]") -> While this Item is Equipped, the user has a bonus to Evasion equal to their Tier Level. As a Reaction + Movement Action, they may treat this bonus as Uncapped until the start of their next Turn. [Equipment] [Large] [Pokemon]
K50: =IFERROR(__xludf.DUMMYFUNCTION("""COMPUTED_VALUE"""),"Type Augmentor (Dark)") -> Type Augmentor (Dark) | L50: =IFERROR(__xludf.DUMMYFUNCTION("""COMPUTED_VALUE"""),"While this Item is Equipped, as a Swift Action, the user may change a Damaging Attack they know to become Dark Type for the rest of the Scene. [Equipment] [Large] [Pokemon]") -> While this Item is Equipped, as a Swift Action, the user may change a Damaging Attack they know to become Dark Type for the rest of the Scene. [Equipment] [Large] [Pokemon] | M50: =IFERROR(__xludf.DUMMYFUNCTION("""COMPUTED_VALUE"""),"Eject Module") -> Eject Module | N50: =IFERROR(__xludf.DUMMYFUNCTION("""COMPUTED_VALUE"""),"This Item may only be equipped by a Pokemon. While this Item is Equipped, whenever the User is hit with an Attack, after Damage Resolution they may choose to be recalled as a Reaction, Free Action. Their Trainer may then send out a new Pokemon as a Free A"&"ction in the same spot the holder was. This cannot be used if the User fainted as a result of the Triggering Attack. [Medium] [Equipment] [Pokemon]") -> This Item may only be equipped by a Pokemon. While this Item is Equipped, whenever the User is hit with an Attack, after Damage Resolution they may choose to be recalled as a Reaction, Free Action. Their Trainer may then send out a new Pokemon as a Free Action in the same spot the holder was. This cannot be used if the User fainted as a result of the Triggering Attack. [Medium] [Equipment] [Pokemon]
K51: =IFERROR(__xludf.DUMMYFUNCTION("""COMPUTED_VALUE"""),"Type Augmentor (Dragon)") -> Type Augmentor (Dragon) | L51: =IFERROR(__xludf.DUMMYFUNCTION("""COMPUTED_VALUE"""),"While this Item is Equipped, as a Swift Action, the user may change a Damaging Attack they know to become Dragon Type for the rest of the Scene. [Equipment] [Large] [Pokemon]") -> While this Item is Equipped, as a Swift Action, the user may change a Damaging Attack they know to become Dragon Type for the rest of the Scene. [Equipment] [Large] [Pokemon] | M51: =IFERROR(__xludf.DUMMYFUNCTION("""COMPUTED_VALUE"""),"Elemental Catalyst (Bug)") -> Elemental Catalyst (Bug) | N51: =IFERROR(__xludf.DUMMYFUNCTION("""COMPUTED_VALUE"""),"When this Item is expended, Target a Willing Pokemon. The Target becomes a Bug Type Shift of the listed Type and follows the rules under that section to guide how they're altered. They may either choose to add the listed Type (If they only have one Type),"&" or replace one of their existing types with the listed Type. [Medium] [Consumable] ") -> When this Item is expended, Target a Willing Pokemon. The Target becomes a Bug Type Shift of the listed Type and follows the rules under that section to guide how they're altered. They may either choose to add the listed Type (If they only have one Type), or replace one of their existing types with the listed Type. [Medium] [Consumable]
K52: =IFERROR(__xludf.DUMMYFUNCTION("""COMPUTED_VALUE"""),"Type Augmentor (Electric)") -> Type Augmentor (Electric) | L52: =IFERROR(__xludf.DUMMYFUNCTION("""COMPUTED_VALUE"""),"While this Item is Equipped, as a Swift Action, the user may change a Damaging Attack they know to become Electric Type for the rest of the Scene. [Equipment] [Large] [Pokemon]") -> While this Item is Equipped, as a Swift Action, the user may change a Damaging Attack they know to become Electric Type for the rest of the Scene. [Equipment] [Large] [Pokemon] | M52: =IFERROR(__xludf.DUMMYFUNCTION("""COMPUTED_VALUE"""),"Elemental Catalyst (Dark)") -> Elemental Catalyst (Dark) | N52: =IFERROR(__xludf.DUMMYFUNCTION("""COMPUTED_VALUE"""),"When this Item is expended, Target a Willing Pokemon. The Target becomes a Dark Type Shift of the listed Type and follows the rules under that section to guide how they're altered. They may either choose to add the listed Type (If they only have one Type)"&", or replace one of their existing types with the listed Type. [Medium] [Consumable] ") -> When this Item is expended, Target a Willing Pokemon. The Target becomes a Dark Type Shift of the listed Type and follows the rules under that section to guide how they're altered. They may either choose to add the listed Type (If they only have one Type), or replace one of their existing types with the listed Type. [Medium] [Consumable]
K53: =IFERROR(__xludf.DUMMYFUNCTION("""COMPUTED_VALUE"""),"Type Augmentor (Fairy)") -> Type Augmentor (Fairy) | L53: =IFERROR(__xludf.DUMMYFUNCTION("""COMPUTED_VALUE"""),"While this Item is Equipped, as a Swift Action, the user may change a Damaging Attack they know to become Fairy Type for the rest of the Scene. [Equipment] [Large] [Pokemon]") -> While this Item is Equipped, as a Swift Action, the user may change a Damaging Attack they know to become Fairy Type for the rest of the Scene. [Equipment] [Large] [Pokemon] | M53: =IFERROR(__xludf.DUMMYFUNCTION("""COMPUTED_VALUE"""),"Elemental Catalyst (Dragon)") -> Elemental Catalyst (Dragon) | N53: =IFERROR(__xludf.DUMMYFUNCTION("""COMPUTED_VALUE"""),"When this Item is expended, Target a Willing Pokemon. The Target becomes a Dragon Type Shift of the listed Type and follows the rules under that section to guide how they're altered. They may either choose to add the listed Type (If they only have one Typ"&"e), or replace one of their existing types with the listed Type. [Medium] [Consumable] ") -> When this Item is expended, Target a Willing Pokemon. The Target becomes a Dragon Type Shift of the listed Type and follows the rules under that section to guide how they're altered. They may either choose to add the listed Type (If they only have one Type), or replace one of their existing types with the listed Type. [Medium] [Consumable]
K54: =IFERROR(__xludf.DUMMYFUNCTION("""COMPUTED_VALUE"""),"Type Augmentor (Fighting)") -> Type Augmentor (Fighting) | L54: =IFERROR(__xludf.DUMMYFUNCTION("""COMPUTED_VALUE"""),"While this Item is Equipped, as a Swift Action, the user may change a Damaging Attack they know to become Fighting Type for the rest of the Scene. [Equipment] [Large] [Pokemon]") -> While this Item is Equipped, as a Swift Action, the user may change a Damaging Attack they know to become Fighting Type for the rest of the Scene. [Equipment] [Large] [Pokemon] | M54: =IFERROR(__xludf.DUMMYFUNCTION("""COMPUTED_VALUE"""),"Elemental Catalyst (Electric)") -> Elemental Catalyst (Electric) | N54: =IFERROR(__xludf.DUMMYFUNCTION("""COMPUTED_VALUE"""),"When this Item is expended, Target a Willing Pokemon. The Target becomes an Electric Type Shift of the listed Type and follows the rules under that section to guide how they're altered. They may either choose to add the listed Type (If they only have one "&"Type), or replace one of their existing types with the listed Type. [Medium] [Consumable] ") -> When this Item is expended, Target a Willing Pokemon. The Target becomes an Electric Type Shift of the listed Type and follows the rules under that section to guide how they're altered. They may either choose to add the listed Type (If they only have one Type), or replace one of their existing types with the listed Type. [Medium] [Consumable]
K55: =IFERROR(__xludf.DUMMYFUNCTION("""COMPUTED_VALUE"""),"Type Augmentor (Fire)") -> Type Augmentor (Fire) | L55: =IFERROR(__xludf.DUMMYFUNCTION("""COMPUTED_VALUE"""),"While this Item is Equipped, as a Swift Action, the user may change a Damaging Attack they know to become Fire Type for the rest of the Scene. [Equipment] [Large] [Pokemon]") -> While this Item is Equipped, as a Swift Action, the user may change a Damaging Attack they know to become Fire Type for the rest of the Scene. [Equipment] [Large] [Pokemon] | M55: =IFERROR(__xludf.DUMMYFUNCTION("""COMPUTED_VALUE"""),"Elemental Catalyst (Fairy)") -> Elemental Catalyst (Fairy) | N55: =IFERROR(__xludf.DUMMYFUNCTION("""COMPUTED_VALUE"""),"When this Item is expended, Target a Willing Pokemon. The Target becomes a Fairy Type Shift of the listed Type and follows the rules under that section to guide how they're altered. They may either choose to add the listed Type (If they only have one Type"&"), or replace one of their existing types with the listed Type. [Medium] [Consumable] ") -> When this Item is expended, Target a Willing Pokemon. The Target becomes a Fairy Type Shift of the listed Type and follows the rules under that section to guide how they're altered. They may either choose to add the listed Type (If they only have one Type), or replace one of their existing types with the listed Type. [Medium] [Consumable]
K56: =IFERROR(__xludf.DUMMYFUNCTION("""COMPUTED_VALUE"""),"Type Augmentor (Flying)") -> Type Augmentor (Flying) | L56: =IFERROR(__xludf.DUMMYFUNCTION("""COMPUTED_VALUE"""),"While this Item is Equipped, as a Swift Action, the user may change a Damaging Attack they know to become Flying Type for the rest of the Scene. [Equipment] [Large] [Pokemon]") -> While this Item is Equipped, as a Swift Action, the user may change a Damaging Attack they know to become Flying Type for the rest of the Scene. [Equipment] [Large] [Pokemon] | M56: =IFERROR(__xludf.DUMMYFUNCTION("""COMPUTED_VALUE"""),"Elemental Catalyst (Fighting)") -> Elemental Catalyst (Fighting) | N56: =IFERROR(__xludf.DUMMYFUNCTION("""COMPUTED_VALUE"""),"When this Item is expended, Target a Willing Pokemon. The Target becomes a Fighting Type Shift of the listed Type and follows the rules under that section to guide how they're altered. They may either choose to add the listed Type (If they only have one T"&"ype), or replace one of their existing types with the listed Type. [Medium] [Consumable] ") -> When this Item is expended, Target a Willing Pokemon. The Target becomes a Fighting Type Shift of the listed Type and follows the rules under that section to guide how they're altered. They may either choose to add the listed Type (If they only have one Type), or replace one of their existing types with the listed Type. [Medium] [Consumable]
K57: =IFERROR(__xludf.DUMMYFUNCTION("""COMPUTED_VALUE"""),"Type Augmentor (Ghost)") -> Type Augmentor (Ghost) | L57: =IFERROR(__xludf.DUMMYFUNCTION("""COMPUTED_VALUE"""),"While this Item is Equipped, as a Swift Action, the user may change a Damaging Attack they know to become Ghost Type for the rest of the Scene. [Equipment] [Large] [Pokemon]") -> While this Item is Equipped, as a Swift Action, the user may change a Damaging Attack they know to become Ghost Type for the rest of the Scene. [Equipment] [Large] [Pokemon] | M57: =IFERROR(__xludf.DUMMYFUNCTION("""COMPUTED_VALUE"""),"Elemental Catalyst (Fire)") -> Elemental Catalyst (Fire) | N57: =IFERROR(__xludf.DUMMYFUNCTION("""COMPUTED_VALUE"""),"When this Item is expended, Target a Willing Pokemon. The Target becomes a Fire Type Shift of the listed Type and follows the rules under that section to guide how they're altered. They may either choose to add the listed Type (If they only have one Type)"&", or replace one of their existing types with the listed Type. [Medium] [Consumable] ") -> When this Item is expended, Target a Willing Pokemon. The Target becomes a Fire Type Shift of the listed Type and follows the rules under that section to guide how they're altered. They may either choose to add the listed Type (If they only have one Type), or replace one of their existing types with the listed Type. [Medium] [Consumable]
K58: =IFERROR(__xludf.DUMMYFUNCTION("""COMPUTED_VALUE"""),"Type Augmentor (Grass)") -> Type Augmentor (Grass) | L58: =IFERROR(__xludf.DUMMYFUNCTION("""COMPUTED_VALUE"""),"While this Item is Equipped, as a Swift Action, the user may change a Damaging Attack they know to become Grass Type for the rest of the Scene. [Equipment] [Large] [Pokemon]") -> While this Item is Equipped, as a Swift Action, the user may change a Damaging Attack they know to become Grass Type for the rest of the Scene. [Equipment] [Large] [Pokemon] | M58: =IFERROR(__xludf.DUMMYFUNCTION("""COMPUTED_VALUE"""),"Elemental Catalyst (Flying)") -> Elemental Catalyst (Flying) | N58: =IFERROR(__xludf.DUMMYFUNCTION("""COMPUTED_VALUE"""),"When this Item is expended, Target a Willing Pokemon. The Target becomes a Flying Type Shift of the listed Type and follows the rules under that section to guide how they're altered. They may either choose to add the listed Type (If they only have one Typ"&"e), or replace one of their existing types with the listed Type. [Medium] [Consumable] ") -> When this Item is expended, Target a Willing Pokemon. The Target becomes a Flying Type Shift of the listed Type and follows the rules under that section to guide how they're altered. They may either choose to add the listed Type (If they only have one Type), or replace one of their existing types with the listed Type. [Medium] [Consumable]
K59: =IFERROR(__xludf.DUMMYFUNCTION("""COMPUTED_VALUE"""),"Type Augmentor (Ground)") -> Type Augmentor (Ground) | L59: =IFERROR(__xludf.DUMMYFUNCTION("""COMPUTED_VALUE"""),"While this Item is Equipped, as a Swift Action, the user may change a Damaging Attack they know to become Ground Type for the rest of the Scene. [Equipment] [Large] [Pokemon]") -> While this Item is Equipped, as a Swift Action, the user may change a Damaging Attack they know to become Ground Type for the rest of the Scene. [Equipment] [Large] [Pokemon] | M59: =IFERROR(__xludf.DUMMYFUNCTION("""COMPUTED_VALUE"""),"Elemental Catalyst (Ghost)") -> Elemental Catalyst (Ghost) | N59: =IFERROR(__xludf.DUMMYFUNCTION("""COMPUTED_VALUE"""),"When this Item is expended, Target a Willing Pokemon. The Target becomes a Ghost Type Shift of the listed Type and follows the rules under that section to guide how they're altered. They may either choose to add the listed Type (If they only have one Type"&"), or replace one of their existing types with the listed Type. [Medium] [Consumable] ") -> When this Item is expended, Target a Willing Pokemon. The Target becomes a Ghost Type Shift of the listed Type and follows the rules under that section to guide how they're altered. They may either choose to add the listed Type (If they only have one Type), or replace one of their existing types with the listed Type. [Medium] [Consumable]
K60: =IFERROR(__xludf.DUMMYFUNCTION("""COMPUTED_VALUE"""),"Type Augmentor (Ice)") -> Type Augmentor (Ice) | L60: =IFERROR(__xludf.DUMMYFUNCTION("""COMPUTED_VALUE"""),"While this Item is Equipped, as a Swift Action, the user may change a Damaging Attack they know to become Ice Type for the rest of the Scene. [Equipment] [Large] [Pokemon]") -> While this Item is Equipped, as a Swift Action, the user may change a Damaging Attack they know to become Ice Type for the rest of the Scene. [Equipment] [Large] [Pokemon] | M60: =IFERROR(__xludf.DUMMYFUNCTION("""COMPUTED_VALUE"""),"Elemental Catalyst (Grass)") -> Elemental Catalyst (Grass) | N60: =IFERROR(__xludf.DUMMYFUNCTION("""COMPUTED_VALUE"""),"When this Item is expended, Target a Willing Pokemon. The Target becomes a Grass Type Shift of the listed Type and follows the rules under that section to guide how they're altered. They may either choose to add the listed Type (If they only have one Type"&"), or replace one of their existing types with the listed Type. [Medium] [Consumable] ") -> When this Item is expended, Target a Willing Pokemon. The Target becomes a Grass Type Shift of the listed Type and follows the rules under that section to guide how they're altered. They may either choose to add the listed Type (If they only have one Type), or replace one of their existing types with the listed Type. [Medium] [Consumable]
K61: =IFERROR(__xludf.DUMMYFUNCTION("""COMPUTED_VALUE"""),"Type Augmentor (Normal)") -> Type Augmentor (Normal) | L61: =IFERROR(__xludf.DUMMYFUNCTION("""COMPUTED_VALUE"""),"While this Item is Equipped, as a Swift Action, the user may change a Damaging Attack they know to become Normal Type for the rest of the Scene. [Equipment] [Large] [Pokemon]") -> While this Item is Equipped, as a Swift Action, the user may change a Damaging Attack they know to become Normal Type for the rest of the Scene. [Equipment] [Large] [Pokemon] | M61: =IFERROR(__xludf.DUMMYFUNCTION("""COMPUTED_VALUE"""),"Elemental Catalyst (Ground)") -> Elemental Catalyst (Ground) | N61: =IFERROR(__xludf.DUMMYFUNCTION("""COMPUTED_VALUE"""),"When this Item is expended, Target a Willing Pokemon. The Target becomes a Ground Type Shift of the listed Type and follows the rules under that section to guide how they're altered. They may either choose to add the listed Type (If they only have one Typ"&"e), or replace one of their existing types with the listed Type. [Medium] [Consumable] ") -> When this Item is expended, Target a Willing Pokemon. The Target becomes a Ground Type Shift of the listed Type and follows the rules under that section to guide how they're altered. They may either choose to add the listed Type (If they only have one Type), or replace one of their existing types with the listed Type. [Medium] [Consumable]
K62: =IFERROR(__xludf.DUMMYFUNCTION("""COMPUTED_VALUE"""),"Type Augmentor (Poison)") -> Type Augmentor (Poison) | L62: =IFERROR(__xludf.DUMMYFUNCTION("""COMPUTED_VALUE"""),"While this Item is Equipped, as a Swift Action, the user may change a Damaging Attack they know to become Poison Type for the rest of the Scene. [Equipment] [Large] [Pokemon]") -> While this Item is Equipped, as a Swift Action, the user may change a Damaging Attack they know to become Poison Type for the rest of the Scene. [Equipment] [Large] [Pokemon] | M62: =IFERROR(__xludf.DUMMYFUNCTION("""COMPUTED_VALUE"""),"Elemental Catalyst (Ice)") -> Elemental Catalyst (Ice) | N62: =IFERROR(__xludf.DUMMYFUNCTION("""COMPUTED_VALUE"""),"When this Item is expended, Target a Willing Pokemon. The Target becomes an Ice Type Shift of the listed Type and follows the rules under that section to guide how they're altered. They may either choose to add the listed Type (If they only have one Type)"&", or replace one of their existing types with the listed Type. [Medium] [Consumable] ") -> When this Item is expended, Target a Willing Pokemon. The Target becomes an Ice Type Shift of the listed Type and follows the rules under that section to guide how they're altered. They may either choose to add the listed Type (If they only have one Type), or replace one of their existing types with the listed Type. [Medium] [Consumable]
K63: =IFERROR(__xludf.DUMMYFUNCTION("""COMPUTED_VALUE"""),"Type Augmentor (Psychic)") -> Type Augmentor (Psychic) | L63: =IFERROR(__xludf.DUMMYFUNCTION("""COMPUTED_VALUE"""),"While this Item is Equipped, as a Swift Action, the user may change a Damaging Attack they know to become Psychic Type for the rest of the Scene. [Equipment] [Large] [Pokemon]") -> While this Item is Equipped, as a Swift Action, the user may change a Damaging Attack they know to become Psychic Type for the rest of the Scene. [Equipment] [Large] [Pokemon] | M63: =IFERROR(__xludf.DUMMYFUNCTION("""COMPUTED_VALUE"""),"Elemental Catalyst (Normal)") -> Elemental Catalyst (Normal) | N63: =IFERROR(__xludf.DUMMYFUNCTION("""COMPUTED_VALUE"""),"When this Item is expended, Target a Willing Pokemon. The Target becomes a Normal Type Shift of the listed Type and follows the rules under that section to guide how they're altered. They may either choose to add the listed Type (If they only have one Typ"&"e), or replace one of their existing types with the listed Type. [Medium] [Consumable] ") -> When this Item is expended, Target a Willing Pokemon. The Target becomes a Normal Type Shift of the listed Type and follows the rules under that section to guide how they're altered. They may either choose to add the listed Type (If they only have one Type), or replace one of their existing types with the listed Type. [Medium] [Consumable]
K64: =IFERROR(__xludf.DUMMYFUNCTION("""COMPUTED_VALUE"""),"Type Augmentor (Rock)") -> Type Augmentor (Rock) | L64: =IFERROR(__xludf.DUMMYFUNCTION("""COMPUTED_VALUE"""),"While this Item is Equipped, as a Swift Action, the user may change a Damaging Attack they know to become Rock Type for the rest of the Scene. [Equipment] [Large] [Pokemon]") -> While this Item is Equipped, as a Swift Action, the user may change a Damaging Attack they know to become Rock Type for the rest of the Scene. [Equipment] [Large] [Pokemon] | M64: =IFERROR(__xludf.DUMMYFUNCTION("""COMPUTED_VALUE"""),"Elemental Catalyst (Poison)") -> Elemental Catalyst (Poison) | N64: =IFERROR(__xludf.DUMMYFUNCTION("""COMPUTED_VALUE"""),"When this Item is expended, Target a Willing Pokemon. The Target becomes a Poison Type Shift of the listed Type and follows the rules under that section to guide how they're altered. They may either choose to add the listed Type (If they only have one Typ"&"e), or replace one of their existing types with the listed Type. [Medium] [Consumable] ") -> When this Item is expended, Target a Willing Pokemon. The Target becomes a Poison Type Shift of the listed Type and follows the rules under that section to guide how they're altered. They may either choose to add the listed Type (If they only have one Type), or replace one of their existing types with the listed Type. [Medium] [Consumable]
K65: =IFERROR(__xludf.DUMMYFUNCTION("""COMPUTED_VALUE"""),"Type Augmentor (Steel)") -> Type Augmentor (Steel) | L65: =IFERROR(__xludf.DUMMYFUNCTION("""COMPUTED_VALUE"""),"While this Item is Equipped, as a Swift Action, the user may change a Damaging Attack they know to become Steel Type for the rest of the Scene. [Equipment] [Large] [Pokemon]") -> While this Item is Equipped, as a Swift Action, the user may change a Damaging Attack they know to become Steel Type for the rest of the Scene. [Equipment] [Large] [Pokemon] | M65: =IFERROR(__xludf.DUMMYFUNCTION("""COMPUTED_VALUE"""),"Elemental Catalyst (Psychic)") -> Elemental Catalyst (Psychic) | N65: =IFERROR(__xludf.DUMMYFUNCTION("""COMPUTED_VALUE"""),"When this Item is expended, Target a Willing Pokemon. The Target becomes a Psychic Type Shift of the listed Type and follows the rules under that section to guide how they're altered. They may either choose to add the listed Type (If they only have one Ty"&"pe), or replace one of their existing types with the listed Type. [Medium] [Consumable] ") -> When this Item is expended, Target a Willing Pokemon. The Target becomes a Psychic Type Shift of the listed Type and follows the rules under that section to guide how they're altered. They may either choose to add the listed Type (If they only have one Type), or replace one of their existing types with the listed Type. [Medium] [Consumable]
K66: =IFERROR(__xludf.DUMMYFUNCTION("""COMPUTED_VALUE"""),"Type Augmentor (Water)") -> Type Augmentor (Water) | L66: =IFERROR(__xludf.DUMMYFUNCTION("""COMPUTED_VALUE"""),"While this Item is Equipped, as a Swift Action, the user may change a Damaging Attack they know to become Water Type for the rest of the Scene. [Equipment] [Large] [Pokemon]") -> While this Item is Equipped, as a Swift Action, the user may change a Damaging Attack they know to become Water Type for the rest of the Scene. [Equipment] [Large] [Pokemon] | M66: =IFERROR(__xludf.DUMMYFUNCTION("""COMPUTED_VALUE"""),"Elemental Catalyst (Rock)") -> Elemental Catalyst (Rock) | N66: =IFERROR(__xludf.DUMMYFUNCTION("""COMPUTED_VALUE"""),"When this Item is expended, Target a Willing Pokemon. The Target becomes a Rock Type Shift of the listed Type and follows the rules under that section to guide how they're altered. They may either choose to add the listed Type (If they only have one Type)"&", or replace one of their existing types with the listed Type. [Medium] [Consumable] ") -> When this Item is expended, Target a Willing Pokemon. The Target becomes a Rock Type Shift of the listed Type and follows the rules under that section to guide how they're altered. They may either choose to add the listed Type (If they only have one Type), or replace one of their existing types with the listed Type. [Medium] [Consumable]
K67: =IFERROR(__xludf.DUMMYFUNCTION("""COMPUTED_VALUE"""),"Type Augmentor (X)") -> Type Augmentor (X) | L67: =IFERROR(__xludf.DUMMYFUNCTION("""COMPUTED_VALUE"""),"When this Item is created, choose a Type to determine the value for X. While this Item is Equipped, as a Swift Action, the user may change a Damaging Attack they know to become the Type of this Item for the rest of the Scene. [Equipment] [Large] [Pokemon]") -> When this Item is created, choose a Type to determine the value for X. While this Item is Equipped, as a Swift Action, the user may change a Damaging Attack they know to become the Type of this Item for the rest of the Scene. [Equipment] [Large] [Pokemon] | M67: =IFERROR(__xludf.DUMMYFUNCTION("""COMPUTED_VALUE"""),"Elemental Catalyst (Steel)") -> Elemental Catalyst (Steel) | N67: =IFERROR(__xludf.DUMMYFUNCTION("""COMPUTED_VALUE"""),"When this Item is expended, Target a Willing Pokemon. The Target becomes a Steel Type Shift of the listed Type and follows the rules under that section to guide how they're altered. They may either choose to add the listed Type (If they only have one Type"&"), or replace one of their existing types with the listed Type. [Medium] [Consumable] ") -> When this Item is expended, Target a Willing Pokemon. The Target becomes a Steel Type Shift of the listed Type and follows the rules under that section to guide how they're altered. They may either choose to add the listed Type (If they only have one Type), or replace one of their existing types with the listed Type. [Medium] [Consumable]
K68: =IFERROR(__xludf.DUMMYFUNCTION("""COMPUTED_VALUE"""),"Type Booster (Bug)") -> Type Booster (Bug) | L68: =IFERROR(__xludf.DUMMYFUNCTION("""COMPUTED_VALUE"""),"While this Item is Equipped, the user's Damaging Bug Type Damaging Attacks gain the Smite Keyword. [Equipment] [Large] [Pokemon]") -> While this Item is Equipped, the user's Damaging Bug Type Damaging Attacks gain the Smite Keyword. [Equipment] [Large] [Pokemon] | M68: =IFERROR(__xludf.DUMMYFUNCTION("""COMPUTED_VALUE"""),"Elemental Catalyst (Water)") -> Elemental Catalyst (Water) | N68: =IFERROR(__xludf.DUMMYFUNCTION("""COMPUTED_VALUE"""),"When this Item is expended, Target a Willing Pokemon. The Target becomes a Water Type Shift of the listed Type and follows the rules under that section to guide how they're altered. They may either choose to add the listed Type (If they only have one Type"&"), or replace one of their existing types with the listed Type. [Medium] [Consumable] ") -> When this Item is expended, Target a Willing Pokemon. The Target becomes a Water Type Shift of the listed Type and follows the rules under that section to guide how they're altered. They may either choose to add the listed Type (If they only have one Type), or replace one of their existing types with the listed Type. [Medium] [Consumable]
K69: =IFERROR(__xludf.DUMMYFUNCTION("""COMPUTED_VALUE"""),"Type Booster (Dark)") -> Type Booster (Dark) | L69: =IFERROR(__xludf.DUMMYFUNCTION("""COMPUTED_VALUE"""),"While this Item is Equipped, the user's Damaging Dark Type Damaging Attacks gain the Smite Keyword. [Equipment] [Large] [Pokemon]") -> While this Item is Equipped, the user's Damaging Dark Type Damaging Attacks gain the Smite Keyword. [Equipment] [Large] [Pokemon] | M69: =IFERROR(__xludf.DUMMYFUNCTION("""COMPUTED_VALUE"""),"Elemental Catalyst (X)") -> Elemental Catalyst (X) | N69: =IFERROR(__xludf.DUMMYFUNCTION("""COMPUTED_VALUE"""),"When this Item is created, (X) is replaced with a Type of the GM’s choosing. When this Item is expended, Target a Willing Pokemon. The Target becomes a Type Shift of the listed Type and follows the rules under that section to guide how they're altered. Th"&"ey may either choose to add the listed Type (If they only have one Type), or replace one of their existing types with the listed Type. [Medium] [Consumable] ") -> When this Item is created, (X) is replaced with a Type of the GM’s choosing. When this Item is expended, Target a Willing Pokemon. The Target becomes a Type Shift of the listed Type and follows the rules under that section to guide how they're altered. They may either choose to add the listed Type (If they only have one Type), or replace one of their existing types with the listed Type. [Medium] [Consumable]
K70: =IFERROR(__xludf.DUMMYFUNCTION("""COMPUTED_VALUE"""),"Type Booster (Dragon)") -> Type Booster (Dragon) | L70: =IFERROR(__xludf.DUMMYFUNCTION("""COMPUTED_VALUE"""),"While this Item is Equipped, the user's Damaging Dragon Type Damaging Attacks gain the Smite Keyword. [Equipment] [Large] [Pokemon]") -> While this Item is Equipped, the user's Damaging Dragon Type Damaging Attacks gain the Smite Keyword. [Equipment] [Large] [Pokemon] | M70: =IFERROR(__xludf.DUMMYFUNCTION("""COMPUTED_VALUE"""),"Elemental Enchantment") -> Elemental Enchantment | N70: =IFERROR(__xludf.DUMMYFUNCTION("""COMPUTED_VALUE"""),"When this Item is created, choose a Type. This Item may be expended to Target an [Equipment] Item and grant it an Attack that matches the listed Type. An Item can only benefit from up to two Attack this way. While an Item with an Elemental Enchantment is "&"equipped, the holder may use the chosen Attack as if it were on their Attack List. If it is Damaging, it can also be used as if it were a Weapon Attack. Depending on the Rarity of this Item, you can only grant Attacks from a specific Tier. If it is Common"&", you can only choose a Tier 1 Attack. If it is Rare, you can choose Tier 1 or 2. If it's very Rare, you can choose any Tier. The GM must approve the chosen Attack, if it isn't already chosen. [Consumable]") -> When this Item is created, choose a Type. This Item may be expended to Target an [Equipment] Item and grant it an Attack that matches the listed Type. An Item can only benefit from up to two Attack this way. While an Item with an Elemental Enchantment is equipped, the holder may use the chosen Attack as if it were on their Attack List. If it is Damaging, it can also be used as if it were a Weapon Attack. Depending on the Rarity of this Item, you can only grant Attacks from a specific Tier. If it is Common, you can only choose a Tier 1 Attack. If it is Rare, you can choose Tier 1 or 2. If it's very Rare, you can choose any Tier. The GM must approve the chosen Attack, if it isn't already chosen. [Consumable]
K71: =IFERROR(__xludf.DUMMYFUNCTION("""COMPUTED_VALUE"""),"Type Booster (Electric)") -> Type Booster (Electric) | L71: =IFERROR(__xludf.DUMMYFUNCTION("""COMPUTED_VALUE"""),"While this Item is Equipped, the user's Damaging Electric Type Damaging Attacks gain the Smite Keyword. [Equipment] [Large] [Pokemon]") -> While this Item is Equipped, the user's Damaging Electric Type Damaging Attacks gain the Smite Keyword. [Equipment] [Large] [Pokemon] | M71: =IFERROR(__xludf.DUMMYFUNCTION("""COMPUTED_VALUE"""),"Elemental Essence") -> Elemental Essence | N71: =IFERROR(__xludf.DUMMYFUNCTION("""COMPUTED_VALUE"""),"When this Item is created, choose a Type. When this Item is expended, the Trainer who expended it gains the Elemental Afffinity Talent for the chosen Type. (This Talent does not take a slot) [Small] [Consumable]") -> When this Item is created, choose a Type. When this Item is expended, the Trainer who expended it gains the Elemental Afffinity Talent for the chosen Type. (This Talent does not take a slot) [Small] [Consumable]
K72: =IFERROR(__xludf.DUMMYFUNCTION("""COMPUTED_VALUE"""),"Type Booster (Fairy)") -> Type Booster (Fairy) | L72: =IFERROR(__xludf.DUMMYFUNCTION("""COMPUTED_VALUE"""),"While this Item is Equipped, the user's Damaging Fairy Type Damaging Attacks gain the Smite Keyword. [Equipment] [Large] [Pokemon]") -> While this Item is Equipped, the user's Damaging Fairy Type Damaging Attacks gain the Smite Keyword. [Equipment] [Large] [Pokemon] | M72: =IFERROR(__xludf.DUMMYFUNCTION("""COMPUTED_VALUE"""),"Energy Booster [Lethality]") -> Energy Booster [Lethality] | N72: =IFERROR(__xludf.DUMMYFUNCTION("""COMPUTED_VALUE"""),"The user gains the Hypersomnia Capability at the next Morning Time Phase, which lasts until the end of the next day, but only needs 4 Hours of Sleep to avoid gaining Fatigue for the current day. [Small] [Consumable] ") -> The user gains the Hypersomnia Capability at the next Morning Time Phase, which lasts until the end of the next day, but only needs 4 Hours of Sleep to avoid gaining Fatigue for the current day. [Small] [Consumable]
K73: =IFERROR(__xludf.DUMMYFUNCTION("""COMPUTED_VALUE"""),"Type Booster (Fighting)") -> Type Booster (Fighting) | L73: =IFERROR(__xludf.DUMMYFUNCTION("""COMPUTED_VALUE"""),"While this Item is Equipped, the user's Damaging Fighting Type Damaging Attacks gain the Smite Keyword. [Equipment] [Large] [Pokemon]") -> While this Item is Equipped, the user's Damaging Fighting Type Damaging Attacks gain the Smite Keyword. [Equipment] [Large] [Pokemon] | M73: =IFERROR(__xludf.DUMMYFUNCTION("""COMPUTED_VALUE"""),"Evolution Stone") -> Evolution Stone | N73: =IFERROR(__xludf.DUMMYFUNCTION("""COMPUTED_VALUE"""),"This Item can be expended by Targeting a Pokemon who isn't fully evolved, but is within 10 Levels of reaching one of its evolutions. The Targeted Pokemon evolves, learns a Tier 1 Tutor Attack, then this Item is expended. [Medium] [Consumable]") -> This Item can be expended by Targeting a Pokemon who isn't fully evolved, but is within 10 Levels of reaching one of its evolutions. The Targeted Pokemon evolves, learns a Tier 1 Tutor Attack, then this Item is expended. [Medium] [Consumable]
K74: =IFERROR(__xludf.DUMMYFUNCTION("""COMPUTED_VALUE"""),"Type Booster (Fire)") -> Type Booster (Fire) | L74: =IFERROR(__xludf.DUMMYFUNCTION("""COMPUTED_VALUE"""),"While this Item is Equipped, the user's Damaging Fire Type Damaging Attacks gain the Smite Keyword. [Equipment] [Large] [Pokemon]") -> While this Item is Equipped, the user's Damaging Fire Type Damaging Attacks gain the Smite Keyword. [Equipment] [Large] [Pokemon] | M74: =IFERROR(__xludf.DUMMYFUNCTION("""COMPUTED_VALUE"""),"Fine Weapon") -> Fine Weapon | N74: =IFERROR(__xludf.DUMMYFUNCTION("""COMPUTED_VALUE"""),"To determine the Effects of this Weapon while Equipped, refer to the ""Creating Weapon Item's Section in the Core Book. [Medium or Large] [Equipment - Weapon]") -> To determine the Effects of this Weapon while Equipped, refer to the "Creating Weapon Item's Section in the Core Book. [Medium or Large] [Equipment - Weapon]
K75: =IFERROR(__xludf.DUMMYFUNCTION("""COMPUTED_VALUE"""),"Type Booster (Flying)") -> Type Booster (Flying) | L75: =IFERROR(__xludf.DUMMYFUNCTION("""COMPUTED_VALUE"""),"While this Item is Equipped, the user's Damaging Flying Type Damaging Attacks gain the Smite Keyword. [Equipment] [Large] [Pokemon]") -> While this Item is Equipped, the user's Damaging Flying Type Damaging Attacks gain the Smite Keyword. [Equipment] [Large] [Pokemon] | M75: =IFERROR(__xludf.DUMMYFUNCTION("""COMPUTED_VALUE"""),"First Aid Kit") -> First Aid Kit | N75: =IFERROR(__xludf.DUMMYFUNCTION("""COMPUTED_VALUE"""),"The user is considered to have standard medical supplies that can stabilize injuries out in the field. As an Extended Action with around 5 Minutes of time, anyone with at least Adept Medicine Edu can cure any Physical Status Affliction. While this is in y"&"our Inventory, at the end of a Scene where Combat Occurred, the user and all Allies restore 3 Ticks of Hit Point. Multiple instances of the First Aid Kit or Mender Capability increase the Ticks restored by +1, instead of each seperately restoring 3. [Medi"&"um] ") -> The user is considered to have standard medical supplies that can stabilize injuries out in the field. As an Extended Action with around 5 Minutes of time, anyone with at least Adept Medicine Edu can cure any Physical Status Affliction. While this is in your Inventory, at the end of a Scene where Combat Occurred, the user and all Allies restore 3 Ticks of Hit Point. Multiple instances of the First Aid Kit or Mender Capability increase the Ticks restored by +1, instead of each seperately restoring 3. [Medium]
K76: =IFERROR(__xludf.DUMMYFUNCTION("""COMPUTED_VALUE"""),"Type Booster (Ghost)") -> Type Booster (Ghost) | L76: =IFERROR(__xludf.DUMMYFUNCTION("""COMPUTED_VALUE"""),"While this Item is Equipped, the user's Damaging Ghost Type Damaging Attacks gain the Smite Keyword. [Equipment] [Large] [Pokemon]") -> While this Item is Equipped, the user's Damaging Ghost Type Damaging Attacks gain the Smite Keyword. [Equipment] [Large] [Pokemon] | M76: =IFERROR(__xludf.DUMMYFUNCTION("""COMPUTED_VALUE"""),"First Aid Kit [Lethality]") -> First Aid Kit [Lethality] | N76: =IFERROR(__xludf.DUMMYFUNCTION("""COMPUTED_VALUE"""),"While this Item is in your Inventory, you can use the Downtime (Nursing) Action on another creature. As an Extended Action with around 5 Minutes of time, if you have at least Adept Medicine Edu, you can cure any Physical Affliction. At the end of a Scene "&"where Combat Occured, the user and all Allies restore 2 Ticks of Hit points or 5 if there is also a Mender present. [Medium]") -> While this Item is in your Inventory, you can use the Downtime (Nursing) Action on another creature. As an Extended Action with around 5 Minutes of time, if you have at least Adept Medicine Edu, you can cure any Physical Affliction. At the end of a Scene where Combat Occured, the user and all Allies restore 2 Ticks of Hit points or 5 if there is also a Mender present. [Medium]
K77: =IFERROR(__xludf.DUMMYFUNCTION("""COMPUTED_VALUE"""),"Type Booster (Grass)") -> Type Booster (Grass) | L77: =IFERROR(__xludf.DUMMYFUNCTION("""COMPUTED_VALUE"""),"While this Item is Equipped, the user's Damaging Grass Type Damaging Attacks gain the Smite Keyword. [Equipment] [Large] [Pokemon]") -> While this Item is Equipped, the user's Damaging Grass Type Damaging Attacks gain the Smite Keyword. [Equipment] [Large] [Pokemon] | M77: =IFERROR(__xludf.DUMMYFUNCTION("""COMPUTED_VALUE"""),"Focus Sash") -> Focus Sash | N77: =IFERROR(__xludf.DUMMYFUNCTION("""COMPUTED_VALUE"""),"While this Item is Equipped, the user has the Endure Attack added to their Attack List without taking a Slot. If the Endure Attack is used, the User’s Positive Combat Stages are reset to their Default Value. [Large] [Equipment] [Pokemon]") -> While this Item is Equipped, the user has the Endure Attack added to their Attack List without taking a Slot. If the Endure Attack is used, the User’s Positive Combat Stages are reset to their Default Value. [Large] [Equipment] [Pokemon]
K78: =IFERROR(__xludf.DUMMYFUNCTION("""COMPUTED_VALUE"""),"Type Booster (Ground)") -> Type Booster (Ground) | L78: =IFERROR(__xludf.DUMMYFUNCTION("""COMPUTED_VALUE"""),"While this Item is Equipped, the user's Damaging Ground Type Damaging Attacks gain the Smite Keyword. [Equipment] [Large] [Pokemon]") -> While this Item is Equipped, the user's Damaging Ground Type Damaging Attacks gain the Smite Keyword. [Equipment] [Large] [Pokemon] | M78: =IFERROR(__xludf.DUMMYFUNCTION("""COMPUTED_VALUE"""),"Fortifying Tools [Lethality]") -> Fortifying Tools [Lethality] | N78: =IFERROR(__xludf.DUMMYFUNCTION("""COMPUTED_VALUE"""),"This Item may be expended at a Campsite to increase the quality to exceedingly suitable. [Medium] ") -> This Item may be expended at a Campsite to increase the quality to exceedingly suitable. [Medium]
K79: =IFERROR(__xludf.DUMMYFUNCTION("""COMPUTED_VALUE"""),"Type Booster (Ice)") -> Type Booster (Ice) | L79: =IFERROR(__xludf.DUMMYFUNCTION("""COMPUTED_VALUE"""),"While this Item is Equipped, the user's Damaging Ice Type Damaging Attacks gain the Smite Keyword. [Equipment] [Large] [Pokemon]") -> While this Item is Equipped, the user's Damaging Ice Type Damaging Attacks gain the Smite Keyword. [Equipment] [Large] [Pokemon] | M79: =IFERROR(__xludf.DUMMYFUNCTION("""COMPUTED_VALUE"""),"Fossil") -> Fossil | N79: =IFERROR(__xludf.DUMMYFUNCTION("""COMPUTED_VALUE"""),"When this Item is created, choose a Pokemon Species. A person that has knowledge in the field of Paleontology may study this Item as an Research Downtime Action with a Downtime Subject of Poke Edu and a Target Number of 100. Once this project is completed"&", the Fossil may be restored to its former state, provided they have equipment to do so. The chosen Pokemon is hatched at Level 1 and if they aren't Rock Type already, may alter into a Rock Type Shift. [Medium] ") -> When this Item is created, choose a Pokemon Species. A person that has knowledge in the field of Paleontology may study this Item as an Research Downtime Action with a Downtime Subject of Poke Edu and a Target Number of 100. Once this project is completed, the Fossil may be restored to its former state, provided they have equipment to do so. The chosen Pokemon is hatched at Level 1 and if they aren't Rock Type already, may alter into a Rock Type Shift. [Medium]
K80: =IFERROR(__xludf.DUMMYFUNCTION("""COMPUTED_VALUE"""),"Type Booster (Normal)") -> Type Booster (Normal) | L80: =IFERROR(__xludf.DUMMYFUNCTION("""COMPUTED_VALUE"""),"While this Item is Equipped, the user's Damaging Normal Type Damaging Attacks gain the Smite Keyword. [Equipment] [Large] [Pokemon]") -> While this Item is Equipped, the user's Damaging Normal Type Damaging Attacks gain the Smite Keyword. [Equipment] [Large] [Pokemon] | M80: =IFERROR(__xludf.DUMMYFUNCTION("""COMPUTED_VALUE"""),"Gemstone") -> Gemstone | N80: =IFERROR(__xludf.DUMMYFUNCTION("""COMPUTED_VALUE"""),"This Item has no effect unless otherwise given one. Depending on its Rarity it will be given a cost it could sell for. Common Gemstones sell for $1,000. Rare Gemstones sell for $3,000. Very Rare Gemstones sell for $5,000. [Small]") -> This Item has no effect unless otherwise given one. Depending on its Rarity it will be given a cost it could sell for. Common Gemstones sell for $1,000. Rare Gemstones sell for $3,000. Very Rare Gemstones sell for $5,000. [Small]
K81: =IFERROR(__xludf.DUMMYFUNCTION("""COMPUTED_VALUE"""),"Type Booster (Poison)") -> Type Booster (Poison) | L81: =IFERROR(__xludf.DUMMYFUNCTION("""COMPUTED_VALUE"""),"While this Item is Equipped, the user's Damaging Poison Type Damaging Attacks gain the Smite Keyword. [Equipment] [Large] [Pokemon]") -> While this Item is Equipped, the user's Damaging Poison Type Damaging Attacks gain the Smite Keyword. [Equipment] [Large] [Pokemon] | M81: =IFERROR(__xludf.DUMMYFUNCTION("""COMPUTED_VALUE"""),"Greater Healing Potion") -> Greater Healing Potion | N81: =IFERROR(__xludf.DUMMYFUNCTION("""COMPUTED_VALUE"""),"Choose one of the following Effects to apply to the Target. A Combatant cannot be Targeted by a Healing Potion more than once per Scene. [Throwable] [Small] [Consumable] » They restore 5 Ticks of Hit Points or 100 HP, whichever is higher. » They are cur"&"ed of 2 Status Afflictions. » They are revived and set to 3 Ticks of Hit Points or 50 Hit Points, whichever is higher.") -> Choose one of the following Effects to apply to the Target. A Combatant cannot be Targeted by a Healing Potion more than once per Scene. [Throwable] [Small] [Consumable] » They restore 5 Ticks of Hit Points or 100 HP, whichever is higher. » They are cured of 2 Status Afflictions. » They are revived and set to 3 Ticks of Hit Points or 50 Hit Points, whichever is higher.
K82: =IFERROR(__xludf.DUMMYFUNCTION("""COMPUTED_VALUE"""),"Type Booster (Psychic)") -> Type Booster (Psychic) | L82: =IFERROR(__xludf.DUMMYFUNCTION("""COMPUTED_VALUE"""),"While this Item is Equipped, the user's Damaging Psychic Type Damaging Attacks gain the Smite Keyword. [Equipment] [Large] [Pokemon]") -> While this Item is Equipped, the user's Damaging Psychic Type Damaging Attacks gain the Smite Keyword. [Equipment] [Large] [Pokemon] | M82: =IFERROR(__xludf.DUMMYFUNCTION("""COMPUTED_VALUE"""),"Greater Healing Potion [Lethality]") -> Greater Healing Potion [Lethality] | N82: =IFERROR(__xludf.DUMMYFUNCTION("""COMPUTED_VALUE"""),"Choose one of the following Effects to apply to the Target. A Combatant cannot be Targeted by a ‘Healing Potion’ more than once per Scene. [Throwable] [Small] [Consumable] » They restore 5 Ticks of Hit Points or 100 HP, whichever is higher. » They are cur"&"ed of 2 Status Afflictions. » They are revived and set to 3 Ticks of Hit Points or 50 Hit Points, whichever is higher. » They are cured of two Wounds (Max 2 per Day - Extended Action only)") -> Choose one of the following Effects to apply to the Target. A Combatant cannot be Targeted by a ‘Healing Potion’ more than once per Scene. [Throwable] [Small] [Consumable] » They restore 5 Ticks of Hit Points or 100 HP, whichever is higher. » They are cured of 2 Status Afflictions. » They are revived and set to 3 Ticks of Hit Points or 50 Hit Points, whichever is higher. » They are cured of two Wounds (Max 2 per Day - Extended Action only)
K83: =IFERROR(__xludf.DUMMYFUNCTION("""COMPUTED_VALUE"""),"Type Booster (Rock)") -> Type Booster (Rock) | L83: =IFERROR(__xludf.DUMMYFUNCTION("""COMPUTED_VALUE"""),"While this Item is Equipped, the user's Damaging Rock Type Damaging Attacks gain the Smite Keyword. [Equipment] [Large] [Pokemon]") -> While this Item is Equipped, the user's Damaging Rock Type Damaging Attacks gain the Smite Keyword. [Equipment] [Large] [Pokemon] | M83: =IFERROR(__xludf.DUMMYFUNCTION("""COMPUTED_VALUE"""),"Greater Malady Potion (Chilled)") -> Greater Malady Potion (Chilled) | N83: =IFERROR(__xludf.DUMMYFUNCTION("""COMPUTED_VALUE"""),"The Target hit by this Item becomes Chilled. [Throwable] [Small] [Consumable]") -> The Target hit by this Item becomes Chilled. [Throwable] [Small] [Consumable]
K84: =IFERROR(__xludf.DUMMYFUNCTION("""COMPUTED_VALUE"""),"Type Booster (Steel)") -> Type Booster (Steel) | L84: =IFERROR(__xludf.DUMMYFUNCTION("""COMPUTED_VALUE"""),"While this Item is Equipped, the user's Damaging Steel Type Damaging Attacks gain the Smite Keyword. [Equipment] [Large] [Pokemon]") -> While this Item is Equipped, the user's Damaging Steel Type Damaging Attacks gain the Smite Keyword. [Equipment] [Large] [Pokemon] | M84: =IFERROR(__xludf.DUMMYFUNCTION("""COMPUTED_VALUE"""),"Greater Malady Potion (Cursed)") -> Greater Malady Potion (Cursed) | N84: =IFERROR(__xludf.DUMMYFUNCTION("""COMPUTED_VALUE"""),"The Target hit by this Item becomes Cursed. [Throwable] [Small] [Consumable]") -> The Target hit by this Item becomes Cursed. [Throwable] [Small] [Consumable]
K85: =IFERROR(__xludf.DUMMYFUNCTION("""COMPUTED_VALUE"""),"Type Booster (Water)") -> Type Booster (Water) | L85: =IFERROR(__xludf.DUMMYFUNCTION("""COMPUTED_VALUE"""),"While this Item is Equipped, the user's Damaging Water Type Damaging Attacks gain the Smite Keyword. [Equipment] [Large] [Pokemon]") -> While this Item is Equipped, the user's Damaging Water Type Damaging Attacks gain the Smite Keyword. [Equipment] [Large] [Pokemon] | M85: =IFERROR(__xludf.DUMMYFUNCTION("""COMPUTED_VALUE"""),"Greater Malady Potion (Dazed)") -> Greater Malady Potion (Dazed) | N85: =IFERROR(__xludf.DUMMYFUNCTION("""COMPUTED_VALUE"""),"The Target hit by this Item becomes Dazed. [Throwable] [Small] [Consumable]") -> The Target hit by this Item becomes Dazed. [Throwable] [Small] [Consumable]
K86: =IFERROR(__xludf.DUMMYFUNCTION("""COMPUTED_VALUE"""),"Type Booster (X)") -> Type Booster (X) | L86: =IFERROR(__xludf.DUMMYFUNCTION("""COMPUTED_VALUE"""),"When this Item is created, choose a Type to determine the value for X. While this Item is Equipped, the user's Damaging Attacks of that Type gain the Smite Keyword. [Equipment] [Large] [Pokemon]") -> When this Item is created, choose a Type to determine the value for X. While this Item is Equipped, the user's Damaging Attacks of that Type gain the Smite Keyword. [Equipment] [Large] [Pokemon] | M86: =IFERROR(__xludf.DUMMYFUNCTION("""COMPUTED_VALUE"""),"Greater Malady Potion (Paralyzed)") -> Greater Malady Potion (Paralyzed) | N86: =IFERROR(__xludf.DUMMYFUNCTION("""COMPUTED_VALUE"""),"The Target hit by this Item becomes Paralyzed. [Throwable] [Small] [Consumable]") -> The Target hit by this Item becomes Paralyzed. [Throwable] [Small] [Consumable]
K87: =IFERROR(__xludf.DUMMYFUNCTION("""COMPUTED_VALUE"""),"Type Brace (Bug)") -> Type Brace (Bug) | L87: =IFERROR(__xludf.DUMMYFUNCTION("""COMPUTED_VALUE"""),"While this Item is Equipped, the user resists Bug Type Damaging Attacks by an additional Damage Step. [Equipment] [Large] [Pokemon]") -> While this Item is Equipped, the user resists Bug Type Damaging Attacks by an additional Damage Step. [Equipment] [Large] [Pokemon] | M87: =IFERROR(__xludf.DUMMYFUNCTION("""COMPUTED_VALUE"""),"Greater Malady Potion (X)") -> Greater Malady Potion (X) | N87: =IFERROR(__xludf.DUMMYFUNCTION("""COMPUTED_VALUE"""),"Greater Malady Potions come in different variations which are determined by the GM. The Target hit by this Item gains the corresponding Status Affliction. Greater Malady Potions can inflict the following Afflictions. Chilled, Paralyzed, Cursed, Dazed. [Th"&"rowable] [Small] [Consumable]") -> Greater Malady Potions come in different variations which are determined by the GM. The Target hit by this Item gains the corresponding Status Affliction. Greater Malady Potions can inflict the following Afflictions. Chilled, Paralyzed, Cursed, Dazed. [Throwable] [Small] [Consumable]
K88: =IFERROR(__xludf.DUMMYFUNCTION("""COMPUTED_VALUE"""),"Type Brace (Dark)") -> Type Brace (Dark) | L88: =IFERROR(__xludf.DUMMYFUNCTION("""COMPUTED_VALUE"""),"While this Item is Equipped, the user resists Dark Type Damaging Attacks by an additional Damage Step. [Equipment] [Large] [Pokemon]") -> While this Item is Equipped, the user resists Dark Type Damaging Attacks by an additional Damage Step. [Equipment] [Large] [Pokemon] | M88: =IFERROR(__xludf.DUMMYFUNCTION("""COMPUTED_VALUE"""),"Greater Poultice") -> Greater Poultice | N88: =IFERROR(__xludf.DUMMYFUNCTION("""COMPUTED_VALUE"""),"Choose one of the following Effects to apply to an Adjacent Target. [Small] [Consumable] » They restore 4 Ticks of Hit Points or 100 HP, whichever is higher. » They are cured of 2 Status Afflictions. ") -> Choose one of the following Effects to apply to an Adjacent Target. [Small] [Consumable] » They restore 4 Ticks of Hit Points or 100 HP, whichever is higher. » They are cured of 2 Status Afflictions.
K89: =IFERROR(__xludf.DUMMYFUNCTION("""COMPUTED_VALUE"""),"Type Brace (Dragon)") -> Type Brace (Dragon) | L89: =IFERROR(__xludf.DUMMYFUNCTION("""COMPUTED_VALUE"""),"While this Item is Equipped, the user resists Dragon Type Damaging Attacks by an additional Damage Step. [Equipment] [Large] [Pokemon]") -> While this Item is Equipped, the user resists Dragon Type Damaging Attacks by an additional Damage Step. [Equipment] [Large] [Pokemon] | M89: =IFERROR(__xludf.DUMMYFUNCTION("""COMPUTED_VALUE"""),"Greater Strength Potion (Accuracy)") -> Greater Strength Potion (Accuracy) | N89: =IFERROR(__xludf.DUMMYFUNCTION("""COMPUTED_VALUE"""),"The Target gains a +3 Modifier to Accuracy for the rest of the Scene. [Throwable] [Small] [Consumable]") -> The Target gains a +3 Modifier to Accuracy for the rest of the Scene. [Throwable] [Small] [Consumable]
K90: =IFERROR(__xludf.DUMMYFUNCTION("""COMPUTED_VALUE"""),"Type Brace (Electric)") -> Type Brace (Electric) | L90: =IFERROR(__xludf.DUMMYFUNCTION("""COMPUTED_VALUE"""),"While this Item is Equipped, the user resists Electric Type Damaging Attacks by an additional Damage Step. [Equipment] [Large] [Pokemon]") -> While this Item is Equipped, the user resists Electric Type Damaging Attacks by an additional Damage Step. [Equipment] [Large] [Pokemon] | M90: =IFERROR(__xludf.DUMMYFUNCTION("""COMPUTED_VALUE"""),"Greater Strength Potion (Attack)") -> Greater Strength Potion (Attack) | N90: =IFERROR(__xludf.DUMMYFUNCTION("""COMPUTED_VALUE"""),"The Target gains +3 CS in Attack. [Throwable] [Small] [Consumable]") -> The Target gains +3 CS in Attack. [Throwable] [Small] [Consumable]
K91: =IFERROR(__xludf.DUMMYFUNCTION("""COMPUTED_VALUE"""),"Type Brace (Fairy)") -> Type Brace (Fairy) | L91: =IFERROR(__xludf.DUMMYFUNCTION("""COMPUTED_VALUE"""),"While this Item is Equipped, the user resists Fairy Type Damaging Attacks by an additional Damage Step. [Equipment] [Large] [Pokemon]") -> While this Item is Equipped, the user resists Fairy Type Damaging Attacks by an additional Damage Step. [Equipment] [Large] [Pokemon] | M91: =IFERROR(__xludf.DUMMYFUNCTION("""COMPUTED_VALUE"""),"Greater Strength Potion (Critical Hit)") -> Greater Strength Potion (Critical Hit) | N91: =IFERROR(__xludf.DUMMYFUNCTION("""COMPUTED_VALUE"""),"The Target gains a +3 Modifier to Critical Hit for the rest of the Scene. [Throwable] [Small] [Consumable]") -> The Target gains a +3 Modifier to Critical Hit for the rest of the Scene. [Throwable] [Small] [Consumable]
K92: =IFERROR(__xludf.DUMMYFUNCTION("""COMPUTED_VALUE"""),"Type Brace (Fighting)") -> Type Brace (Fighting) | L92: =IFERROR(__xludf.DUMMYFUNCTION("""COMPUTED_VALUE"""),"While this Item is Equipped, the user resists Fighting Type Damaging Attacks by an additional Damage Step. [Equipment] [Large] [Pokemon]") -> While this Item is Equipped, the user resists Fighting Type Damaging Attacks by an additional Damage Step. [Equipment] [Large] [Pokemon] | M92: =IFERROR(__xludf.DUMMYFUNCTION("""COMPUTED_VALUE"""),"Greater Strength Potion (Special Attack)") -> Greater Strength Potion (Special Attack) | N92: =IFERROR(__xludf.DUMMYFUNCTION("""COMPUTED_VALUE"""),"The Target gains +3 CS in Special Attack. [Throwable] [Small] [Consumable]") -> The Target gains +3 CS in Special Attack. [Throwable] [Small] [Consumable]
K93: =IFERROR(__xludf.DUMMYFUNCTION("""COMPUTED_VALUE"""),"Type Brace (Fire)") -> Type Brace (Fire) | L93: =IFERROR(__xludf.DUMMYFUNCTION("""COMPUTED_VALUE"""),"While this Item is Equipped, the user resists Fire Type Damaging Attacks by an additional Damage Step. [Equipment] [Large] [Pokemon]") -> While this Item is Equipped, the user resists Fire Type Damaging Attacks by an additional Damage Step. [Equipment] [Large] [Pokemon] | M93: =IFERROR(__xludf.DUMMYFUNCTION("""COMPUTED_VALUE"""),"Greater Strength Potion (X)") -> Greater Strength Potion (X) | N93: =IFERROR(__xludf.DUMMYFUNCTION("""COMPUTED_VALUE"""),"Basic Strength Potions come in different Variations which are determined by the GM. X May be Attack, Special Attack, Critical Hit or Accuracy. If X is Attack or Special Attack, the Target gains +3 CS in that Stat. If X is Critical Hit or Accuracy, they ga"&"in a +3 Modifier to that Combat Value for the rest of the Scene. [Throwable] [Small] [Consumable]") -> Basic Strength Potions come in different Variations which are determined by the GM. X May be Attack, Special Attack, Critical Hit or Accuracy. If X is Attack or Special Attack, the Target gains +3 CS in that Stat. If X is Critical Hit or Accuracy, they gain a +3 Modifier to that Combat Value for the rest of the Scene. [Throwable] [Small] [Consumable]
K94: =IFERROR(__xludf.DUMMYFUNCTION("""COMPUTED_VALUE"""),"Type Brace (Flying)") -> Type Brace (Flying) | L94: =IFERROR(__xludf.DUMMYFUNCTION("""COMPUTED_VALUE"""),"While this Item is Equipped, the user resists Flying Type Damaging Attacks by an additional Damage Step. [Equipment] [Large] [Pokemon]") -> While this Item is Equipped, the user resists Flying Type Damaging Attacks by an additional Damage Step. [Equipment] [Large] [Pokemon] | M94: =IFERROR(__xludf.DUMMYFUNCTION("""COMPUTED_VALUE"""),"Greater Vitality Potion (Defense)") -> Greater Vitality Potion (Defense) | N94: =IFERROR(__xludf.DUMMYFUNCTION("""COMPUTED_VALUE"""),"The Target gains +3 CS in Defense. [Throwable] [Small] [Consumable]") -> The Target gains +3 CS in Defense. [Throwable] [Small] [Consumable]
K95: =IFERROR(__xludf.DUMMYFUNCTION("""COMPUTED_VALUE"""),"Type Brace (Ghost)") -> Type Brace (Ghost) | L95: =IFERROR(__xludf.DUMMYFUNCTION("""COMPUTED_VALUE"""),"While this Item is Equipped, the user resists Ghost Type Damaging Attacks by an additional Damage Step. [Equipment] [Large] [Pokemon]") -> While this Item is Equipped, the user resists Ghost Type Damaging Attacks by an additional Damage Step. [Equipment] [Large] [Pokemon] | M95: =IFERROR(__xludf.DUMMYFUNCTION("""COMPUTED_VALUE"""),"Greater Vitality Potion (Evasion)") -> Greater Vitality Potion (Evasion) | N95: =IFERROR(__xludf.DUMMYFUNCTION("""COMPUTED_VALUE"""),"The Target gains a +6 Modifier to Evasion for the rest of the Scene. [Throwable] [Small] [Consumable]") -> The Target gains a +6 Modifier to Evasion for the rest of the Scene. [Throwable] [Small] [Consumable]
K96: =IFERROR(__xludf.DUMMYFUNCTION("""COMPUTED_VALUE"""),"Type Brace (Grass)") -> Type Brace (Grass) | L96: =IFERROR(__xludf.DUMMYFUNCTION("""COMPUTED_VALUE"""),"While this Item is Equipped, the user resists Grass Type Damaging Attacks by an additional Damage Step. [Equipment] [Large] [Pokemon]") -> While this Item is Equipped, the user resists Grass Type Damaging Attacks by an additional Damage Step. [Equipment] [Large] [Pokemon] | M96: =IFERROR(__xludf.DUMMYFUNCTION("""COMPUTED_VALUE"""),"Greater Vitality Potion (Save Checks)") -> Greater Vitality Potion (Save Checks) | N96: =IFERROR(__xludf.DUMMYFUNCTION("""COMPUTED_VALUE"""),"The Target gains a +4 Modifier to Save Checks for the rest of the Scene. [Throwable] [Small] [Consumable]") -> The Target gains a +4 Modifier to Save Checks for the rest of the Scene. [Throwable] [Small] [Consumable]
K97: =IFERROR(__xludf.DUMMYFUNCTION("""COMPUTED_VALUE"""),"Type Brace (Ground)") -> Type Brace (Ground) | L97: =IFERROR(__xludf.DUMMYFUNCTION("""COMPUTED_VALUE"""),"While this Item is Equipped, the user resists Ground Type Damaging Attacks by an additional Damage Step. [Equipment] [Large] [Pokemon]") -> While this Item is Equipped, the user resists Ground Type Damaging Attacks by an additional Damage Step. [Equipment] [Large] [Pokemon] | M97: =IFERROR(__xludf.DUMMYFUNCTION("""COMPUTED_VALUE"""),"Greater Vitality Potion (Special Defense)") -> Greater Vitality Potion (Special Defense) | N97: =IFERROR(__xludf.DUMMYFUNCTION("""COMPUTED_VALUE"""),"The Target gains +3 CS in Special Defense. [Throwable] [Small] [Consumable]") -> The Target gains +3 CS in Special Defense. [Throwable] [Small] [Consumable]
K98: =IFERROR(__xludf.DUMMYFUNCTION("""COMPUTED_VALUE"""),"Type Brace (Ice)") -> Type Brace (Ice) | L98: =IFERROR(__xludf.DUMMYFUNCTION("""COMPUTED_VALUE"""),"While this Item is Equipped, the user resists Ice Type Damaging Attacks by an additional Damage Step. [Equipment] [Large] [Pokemon]") -> While this Item is Equipped, the user resists Ice Type Damaging Attacks by an additional Damage Step. [Equipment] [Large] [Pokemon] | M98: =IFERROR(__xludf.DUMMYFUNCTION("""COMPUTED_VALUE"""),"Greater Vitality Potion (X)") -> Greater Vitality Potion (X) | N98: =IFERROR(__xludf.DUMMYFUNCTION("""COMPUTED_VALUE"""),"Basic Strength Potions come in different Variations which are determined by the GM. X May be Defense, Special Defense, Evasion or Save Checks. If X is Defense or Special Defense, the Target gains +3 CS in that Stat. If X is Evasion, they gain a +6 Bonus t"&"o Evasion for the rest of the Scene. If X is Save Checks, they gain a +4 Modifier to that Combat Value for the rest of the Scene. [Throwable] [Small] [Consumable]") -> Basic Strength Potions come in different Variations which are determined by the GM. X May be Defense, Special Defense, Evasion or Save Checks. If X is Defense or Special Defense, the Target gains +3 CS in that Stat. If X is Evasion, they gain a +6 Bonus to Evasion for the rest of the Scene. If X is Save Checks, they gain a +4 Modifier to that Combat Value for the rest of the Scene. [Throwable] [Small] [Consumable]
K99: =IFERROR(__xludf.DUMMYFUNCTION("""COMPUTED_VALUE"""),"Type Brace (Normal)") -> Type Brace (Normal) | L99: =IFERROR(__xludf.DUMMYFUNCTION("""COMPUTED_VALUE"""),"While this Item is Equipped, the user resists Normal Type Damaging Attacks by an additional Damage Step. [Equipment] [Large] [Pokemon]") -> While this Item is Equipped, the user resists Normal Type Damaging Attacks by an additional Damage Step. [Equipment] [Large] [Pokemon] | M99: =IFERROR(__xludf.DUMMYFUNCTION("""COMPUTED_VALUE"""),"Green Shard") -> Green Shard | N99: =IFERROR(__xludf.DUMMYFUNCTION("""COMPUTED_VALUE"""),"This Item can be expended as a Free Action in the user's Inventory upon hitting a Bug, Grass or Ground Type Damaging Attack to increase its Damage Base by +3. The user may only expend one Shard Item per Attack. [Small] [Consumable] [Pokemon]") -> This Item can be expended as a Free Action in the user's Inventory upon hitting a Bug, Grass or Ground Type Damaging Attack to increase its Damage Base by +3. The user may only expend one Shard Item per Attack. [Small] [Consumable] [Pokemon]
K100: =IFERROR(__xludf.DUMMYFUNCTION("""COMPUTED_VALUE"""),"Type Brace (Poison)") -> Type Brace (Poison) | L100: =IFERROR(__xludf.DUMMYFUNCTION("""COMPUTED_VALUE"""),"While this Item is Equipped, the user resists Poison Type Damaging Attacks by an additional Damage Step. [Equipment] [Large] [Pokemon]") -> While this Item is Equipped, the user resists Poison Type Damaging Attacks by an additional Damage Step. [Equipment] [Large] [Pokemon] | M100: =IFERROR(__xludf.DUMMYFUNCTION("""COMPUTED_VALUE"""),"Harnessed Attack") -> Harnessed Attack | N100: =IFERROR(__xludf.DUMMYFUNCTION("""COMPUTED_VALUE"""),"When this Item is created, the GM will determine what Attack is harnessed in this Item. The holder may expend this Item as a Standard action (Or Swift if they’re using the Versatile Effect) to use the Attack as if it were on their Attack List. If the Atta"&"ck is Damaging, they may also choose to treat their Offensive Stat as if it were Double their Tier Value [Medium] [Consumable]") -> When this Item is created, the GM will determine what Attack is harnessed in this Item. The holder may expend this Item as a Standard action (Or Swift if they’re using the Versatile Effect) to use the Attack as if it were on their Attack List. If the Attack is Damaging, they may also choose to treat their Offensive Stat as if it were Double their Tier Value [Medium] [Consumable]
...

Sheet Attack Data
A1: Attack Name | B1: Type | C1: Class | D1: Frequency | E1: Range | F1: AC | G1: DB | H1: Effect | I1: Versatile Effect | J1: Attack Tier | K1: Metronome
A2: =IFERROR(__xludf.DUMMYFUNCTION("IMPORTRANGE('Homebrew Sheet'!$A$6,""'Attacks'!$A$2:$K$201"")"),"") | K2: =IFERROR(__xludf.DUMMYFUNCTION("""COMPUTED_VALUE"""),FALSE) -> FALSE
K3: =IFERROR(__xludf.DUMMYFUNCTION("""COMPUTED_VALUE"""),FALSE) -> FALSE
K4: =IFERROR(__xludf.DUMMYFUNCTION("""COMPUTED_VALUE"""),FALSE) -> FALSE
K5: =IFERROR(__xludf.DUMMYFUNCTION("""COMPUTED_VALUE"""),FALSE) -> FALSE
K6: =IFERROR(__xludf.DUMMYFUNCTION("""COMPUTED_VALUE"""),FALSE) -> FALSE
K7: =IFERROR(__xludf.DUMMYFUNCTION("""COMPUTED_VALUE"""),FALSE) -> FALSE
K8: =IFERROR(__xludf.DUMMYFUNCTION("""COMPUTED_VALUE"""),FALSE) -> FALSE
K9: =IFERROR(__xludf.DUMMYFUNCTION("""COMPUTED_VALUE"""),FALSE) -> FALSE
K10: =IFERROR(__xludf.DUMMYFUNCTION("""COMPUTED_VALUE"""),FALSE) -> FALSE
K11: =IFERROR(__xludf.DUMMYFUNCTION("""COMPUTED_VALUE"""),FALSE) -> FALSE
K12: =IFERROR(__xludf.DUMMYFUNCTION("""COMPUTED_VALUE"""),FALSE) -> FALSE
K13: =IFERROR(__xludf.DUMMYFUNCTION("""COMPUTED_VALUE"""),FALSE) -> FALSE
K14: =IFERROR(__xludf.DUMMYFUNCTION("""COMPUTED_VALUE"""),FALSE) -> FALSE
... K201: =IFERROR(__xludf.DUMMYFUNCTION("""COMPUTED_VALUE"""),FALSE) -> FALSE
A202: =IFERROR(__xludf.DUMMYFUNCTION("IMPORTRANGE(""https://docs.google.com/spreadsheets/d/1OWqz0Kj63DvuK16jiKGSn_Hv_N2mbyV2QAdHjKdcrpw"", ""'Attacks'!$A$2:$K"")"),"Attack Order") -> Attack Order | B202: =IFERROR(__xludf.DUMMYFUNCTION("""COMPUTED_VALUE"""),"Bug") -> Bug | C202: =IFERROR(__xludf.DUMMYFUNCTION("""COMPUTED_VALUE"""),"Physical") -> Physical | D202: =IFERROR(__xludf.DUMMYFUNCTION("""COMPUTED_VALUE"""),"EOT") -> EOT | E202: =IFERROR(__xludf.DUMMYFUNCTION("""COMPUTED_VALUE"""),"6, 1 Target, Full Action") -> 6, 1 Target, Full Action | F202: =IFERROR(__xludf.DUMMYFUNCTION("""COMPUTED_VALUE"""),3.0) -> 3 | G202: =IFERROR(__xludf.DUMMYFUNCTION("""COMPUTED_VALUE"""),8.0) -> 8 | H202: =IFERROR(__xludf.DUMMYFUNCTION("""COMPUTED_VALUE"""),"If Attack Order misses, an Ally that is Adjacent to the Target triggers an Attack of Opportunity against the Target. Spirit Surge.") -> If Attack Order misses, an Ally that is Adjacent to the Target triggers an Attack of Opportunity against the Target. Spirit Surge. | I202: =IFERROR(__xludf.DUMMYFUNCTION("""COMPUTED_VALUE"""),"--") -> -- | J202: =IFERROR(__xludf.DUMMYFUNCTION("""COMPUTED_VALUE"""),"Tier 2") -> Tier 2 | K202: =IFERROR(__xludf.DUMMYFUNCTION("""COMPUTED_VALUE"""),TRUE) -> TRUE
A203: =IFERROR(__xludf.DUMMYFUNCTION("""COMPUTED_VALUE"""),"Bug Bite") -> Bug Bite | B203: =IFERROR(__xludf.DUMMYFUNCTION("""COMPUTED_VALUE"""),"Bug") -> Bug | C203: =IFERROR(__xludf.DUMMYFUNCTION("""COMPUTED_VALUE"""),"Physical") -> Physical | D203: =IFERROR(__xludf.DUMMYFUNCTION("""COMPUTED_VALUE"""),"At-Will") -> At-Will | E203: =IFERROR(__xludf.DUMMYFUNCTION("""COMPUTED_VALUE"""),"Melee, 1 Target, Bite") -> Melee, 1 Target, Bite | F203: =IFERROR(__xludf.DUMMYFUNCTION("""COMPUTED_VALUE"""),2.0) -> 2 | G203: =IFERROR(__xludf.DUMMYFUNCTION("""COMPUTED_VALUE"""),6.0) -> 6 | H203: =IFERROR(__xludf.DUMMYFUNCTION("""COMPUTED_VALUE"""),"On a roll of 17+, the Target becomes Wounded.") -> On a roll of 17+, the Target becomes Wounded. | I203: =IFERROR(__xludf.DUMMYFUNCTION("""COMPUTED_VALUE"""),"--") -> -- | J203: =IFERROR(__xludf.DUMMYFUNCTION("""COMPUTED_VALUE"""),"Tier 1") -> Tier 1 | K203: =IFERROR(__xludf.DUMMYFUNCTION("""COMPUTED_VALUE"""),TRUE) -> TRUE
A204: =IFERROR(__xludf.DUMMYFUNCTION("""COMPUTED_VALUE"""),"Bug Buzz") -> Bug Buzz | B204: =IFERROR(__xludf.DUMMYFUNCTION("""COMPUTED_VALUE"""),"Bug") -> Bug | C204: =IFERROR(__xludf.DUMMYFUNCTION("""COMPUTED_VALUE"""),"Special") -> Special | D204: =IFERROR(__xludf.DUMMYFUNCTION("""COMPUTED_VALUE"""),"Scene x2") -> Scene x2 | E204: =IFERROR(__xludf.DUMMYFUNCTION("""COMPUTED_VALUE"""),"Close Blast 2 or Burst 1; Sonic") -> Close Blast 2 or Burst 1; Sonic | F204: =IFERROR(__xludf.DUMMYFUNCTION("""COMPUTED_VALUE"""),6.0) -> 6 | G204: =IFERROR(__xludf.DUMMYFUNCTION("""COMPUTED_VALUE"""),9.0) -> 9 | H204: =IFERROR(__xludf.DUMMYFUNCTION("""COMPUTED_VALUE"""),"On a roll of 18+, all Targets become Dazed. If a Target has negative Special Defense CS, the Effect Range automatically Triggers against them. Smite") -> On a roll of 18+, all Targets become Dazed. If a Target has negative Special Defense CS, the Effect Range automatically Triggers against them. Smite | I204: =IFERROR(__xludf.DUMMYFUNCTION("""COMPUTED_VALUE"""),"--") -> -- | J204: =IFERROR(__xludf.DUMMYFUNCTION("""COMPUTED_VALUE"""),"Tier 2") -> Tier 2 | K204: =IFERROR(__xludf.DUMMYFUNCTION("""COMPUTED_VALUE"""),TRUE) -> TRUE
A205: =IFERROR(__xludf.DUMMYFUNCTION("""COMPUTED_VALUE"""),"Defend Order") -> Defend Order | B205: =IFERROR(__xludf.DUMMYFUNCTION("""COMPUTED_VALUE"""),"Bug") -> Bug | C205: =IFERROR(__xludf.DUMMYFUNCTION("""COMPUTED_VALUE"""),"Status") -> Status | D205: =IFERROR(__xludf.DUMMYFUNCTION("""COMPUTED_VALUE"""),"EOT") -> EOT | E205: =IFERROR(__xludf.DUMMYFUNCTION("""COMPUTED_VALUE"""),"Close Blast 2, Sonic") -> Close Blast 2, Sonic | F205: =IFERROR(__xludf.DUMMYFUNCTION("""COMPUTED_VALUE"""),"--") -> -- | G205: =IFERROR(__xludf.DUMMYFUNCTION("""COMPUTED_VALUE"""),"--") -> -- | H205: =IFERROR(__xludf.DUMMYFUNCTION("""COMPUTED_VALUE"""),"All Targets gain DR equal to double your Tier Value until the start of your next Turn or gains +2 CS in Defense. Sureshot") -> All Targets gain DR equal to double your Tier Value until the start of your next Turn or gains +2 CS in Defense. Sureshot | I205: =IFERROR(__xludf.DUMMYFUNCTION("""COMPUTED_VALUE"""),"When used this way, the range become Self. All Adjacent Allies may use the Defend Maneuver with you as a Target as a Priority Free Action.") -> When used this way, the range become Self. All Adjacent Allies may use the Defend Maneuver with you as a Target as a Priority Free Action. | J205: =IFERROR(__xludf.DUMMYFUNCTION("""COMPUTED_VALUE"""),"Tier 1") -> Tier 1 | K205: =IFERROR(__xludf.DUMMYFUNCTION("""COMPUTED_VALUE"""),TRUE) -> TRUE
A206: =IFERROR(__xludf.DUMMYFUNCTION("""COMPUTED_VALUE"""),"Dull Drone") -> Dull Drone | B206: =IFERROR(__xludf.DUMMYFUNCTION("""COMPUTED_VALUE"""),"Bug") -> Bug | C206: =IFERROR(__xludf.DUMMYFUNCTION("""COMPUTED_VALUE"""),"Special") -> Special | D206: =IFERROR(__xludf.DUMMYFUNCTION("""COMPUTED_VALUE"""),"At-Will") -> At-Will | E206: =IFERROR(__xludf.DUMMYFUNCTION("""COMPUTED_VALUE"""),"4, 1 Target, Sonic") -> 4, 1 Target, Sonic | F206: =IFERROR(__xludf.DUMMYFUNCTION("""COMPUTED_VALUE"""),3.0) -> 3 | G206: =IFERROR(__xludf.DUMMYFUNCTION("""COMPUTED_VALUE"""),4.0) -> 4 | H206: =IFERROR(__xludf.DUMMYFUNCTION("""COMPUTED_VALUE"""),"On a roll of 18+, all Targets become Dazed.") -> On a roll of 18+, all Targets become Dazed. | I206: =IFERROR(__xludf.DUMMYFUNCTION("""COMPUTED_VALUE"""),"--") -> -- | J206: =IFERROR(__xludf.DUMMYFUNCTION("""COMPUTED_VALUE"""),"Tier 1") -> Tier 1 | K206: =IFERROR(__xludf.DUMMYFUNCTION("""COMPUTED_VALUE"""),TRUE) -> TRUE
A207: =IFERROR(__xludf.DUMMYFUNCTION("""COMPUTED_VALUE"""),"Fell Stinger") -> Fell Stinger | B207: =IFERROR(__xludf.DUMMYFUNCTION("""COMPUTED_VALUE"""),"Bug") -> Bug | C207: =IFERROR(__xludf.DUMMYFUNCTION("""COMPUTED_VALUE"""),"Physical") -> Physical | D207: =IFERROR(__xludf.DUMMYFUNCTION("""COMPUTED_VALUE"""),"At-Will") -> At-Will | E207: =IFERROR(__xludf.DUMMYFUNCTION("""COMPUTED_VALUE"""),"Melee, 1 Target") -> Melee, 1 Target | F207: =IFERROR(__xludf.DUMMYFUNCTION("""COMPUTED_VALUE"""),2.0) -> 2 | G207: =IFERROR(__xludf.DUMMYFUNCTION("""COMPUTED_VALUE"""),5.0) -> 5 | H207: =IFERROR(__xludf.DUMMYFUNCTION("""COMPUTED_VALUE"""),"If the Target faints as a result of being hit by Fell Stinger, the user gains +2 CS in Attack. ") -> If the Target faints as a result of being hit by Fell Stinger, the user gains +2 CS in Attack. | I207: =IFERROR(__xludf.DUMMYFUNCTION("""COMPUTED_VALUE"""),"--") -> -- | J207: =IFERROR(__xludf.DUMMYFUNCTION("""COMPUTED_VALUE"""),"Tier 1") -> Tier 1 | K207: =IFERROR(__xludf.DUMMYFUNCTION("""COMPUTED_VALUE"""),TRUE) -> TRUE
A208: =IFERROR(__xludf.DUMMYFUNCTION("""COMPUTED_VALUE"""),"First Impression") -> First Impression | B208: =IFERROR(__xludf.DUMMYFUNCTION("""COMPUTED_VALUE"""),"Bug") -> Bug | C208: =IFERROR(__xludf.DUMMYFUNCTION("""COMPUTED_VALUE"""),"Physical") -> Physical | D208: =IFERROR(__xludf.DUMMYFUNCTION("""COMPUTED_VALUE"""),"EOT") -> EOT | E208: =IFERROR(__xludf.DUMMYFUNCTION("""COMPUTED_VALUE"""),"Melee, 1 Target") -> Melee, 1 Target | F208: =IFERROR(__xludf.DUMMYFUNCTION("""COMPUTED_VALUE"""),3.0) -> 3 | G208: =IFERROR(__xludf.DUMMYFUNCTION("""COMPUTED_VALUE"""),8.0) -> 8 | H208: =IFERROR(__xludf.DUMMYFUNCTION("""COMPUTED_VALUE"""),"If the user entered the Scene this round, this has the Sureshot Keyword. After this Attack resolves, the user may perform a Full Switch as a Free Action. Spirit Surge") -> If the user entered the Scene this round, this has the Sureshot Keyword. After this Attack resolves, the user may perform a Full Switch as a Free Action. Spirit Surge | I208: =IFERROR(__xludf.DUMMYFUNCTION("""COMPUTED_VALUE"""),"--") -> -- | J208: =IFERROR(__xludf.DUMMYFUNCTION("""COMPUTED_VALUE"""),"Tier 2") -> Tier 2 | K208: =IFERROR(__xludf.DUMMYFUNCTION("""COMPUTED_VALUE"""),TRUE) -> TRUE
A209: =IFERROR(__xludf.DUMMYFUNCTION("""COMPUTED_VALUE"""),"Fury Cutter") -> Fury Cutter | B209: =IFERROR(__xludf.DUMMYFUNCTION("""COMPUTED_VALUE"""),"Bug") -> Bug | C209: =IFERROR(__xludf.DUMMYFUNCTION("""COMPUTED_VALUE"""),"Physical") -> Physical | D209: =IFERROR(__xludf.DUMMYFUNCTION("""COMPUTED_VALUE"""),"At-Will") -> At-Will | E209: =IFERROR(__xludf.DUMMYFUNCTION("""COMPUTED_VALUE"""),"Melee, 1 Target") -> Melee, 1 Target | F209: =IFERROR(__xludf.DUMMYFUNCTION("""COMPUTED_VALUE"""),3.0) -> 3 | G209: =IFERROR(__xludf.DUMMYFUNCTION("""COMPUTED_VALUE"""),4.0) -> 4 | H209: =IFERROR(__xludf.DUMMYFUNCTION("""COMPUTED_VALUE"""),"If the user is Provoked, Enraged, or as a Full Action, Fury Cutter may be used as if it was Close Blast 2 or Pass. ") -> If the user is Provoked, Enraged, or as a Full Action, Fury Cutter may be used as if it was Close Blast 2 or Pass. | I209: =IFERROR(__xludf.DUMMYFUNCTION("""COMPUTED_VALUE"""),"--") -> -- | J209: =IFERROR(__xludf.DUMMYFUNCTION("""COMPUTED_VALUE"""),"Tier 1") -> Tier 1 | K209: =IFERROR(__xludf.DUMMYFUNCTION("""COMPUTED_VALUE"""),TRUE) -> TRUE
A210: =IFERROR(__xludf.DUMMYFUNCTION("""COMPUTED_VALUE"""),"Giga Leech") -> Giga Leech | B210: =IFERROR(__xludf.DUMMYFUNCTION("""COMPUTED_VALUE"""),"Bug") -> Bug | C210: =IFERROR(__xludf.DUMMYFUNCTION("""COMPUTED_VALUE"""),"Physical") -> Physical | D210: =IFERROR(__xludf.DUMMYFUNCTION("""COMPUTED_VALUE"""),"Scene x2") -> Scene x2 | E210: =IFERROR(__xludf.DUMMYFUNCTION("""COMPUTED_VALUE"""),"Melee, 1 Target") -> Melee, 1 Target | F210: =IFERROR(__xludf.DUMMYFUNCTION("""COMPUTED_VALUE"""),5.0) -> 5 | G210: =IFERROR(__xludf.DUMMYFUNCTION("""COMPUTED_VALUE"""),10.0) -> 10 | H210: =IFERROR(__xludf.DUMMYFUNCTION("""COMPUTED_VALUE"""),"On a roll of 15+, choose a Stat. The Target is lowered by -1 CS in that Stat and the user gains +1 CS to that Stat. Drain.") -> On a roll of 15+, choose a Stat. The Target is lowered by -1 CS in that Stat and the user gains +1 CS to that Stat. Drain. | I210: =IFERROR(__xludf.DUMMYFUNCTION("""COMPUTED_VALUE"""),"--") -> -- | J210: =IFERROR(__xludf.DUMMYFUNCTION("""COMPUTED_VALUE"""),"Tier 3") -> Tier 3 | K210: =IFERROR(__xludf.DUMMYFUNCTION("""COMPUTED_VALUE"""),TRUE) -> TRUE
A211: =IFERROR(__xludf.DUMMYFUNCTION("""COMPUTED_VALUE"""),"Heal Order") -> Heal Order | B211: =IFERROR(__xludf.DUMMYFUNCTION("""COMPUTED_VALUE"""),"Bug") -> Bug | C211: =IFERROR(__xludf.DUMMYFUNCTION("""COMPUTED_VALUE"""),"Status") -> Status | D211: =IFERROR(__xludf.DUMMYFUNCTION("""COMPUTED_VALUE"""),"Scene x2") -> Scene x2 | E211: =IFERROR(__xludf.DUMMYFUNCTION("""COMPUTED_VALUE"""),"6m, 1 Target, Healing, Versatile") -> 6m, 1 Target, Healing, Versatile | F211: =IFERROR(__xludf.DUMMYFUNCTION("""COMPUTED_VALUE"""),"--") -> -- | G211: =IFERROR(__xludf.DUMMYFUNCTION("""COMPUTED_VALUE"""),"--") -> -- | H211: =IFERROR(__xludf.DUMMYFUNCTION("""COMPUTED_VALUE"""),"The Target restores 5 Ticks of Hit Points.") -> The Target restores 5 Ticks of Hit Points. | I211: =IFERROR(__xludf.DUMMYFUNCTION("""COMPUTED_VALUE"""),"The Target restores a Tick of Hit Points. When used this way, it doesn't expend the Frequency of Heal Order.") -> The Target restores a Tick of Hit Points. When used this way, it doesn't expend the Frequency of Heal Order. | J211: =IFERROR(__xludf.DUMMYFUNCTION("""COMPUTED_VALUE"""),"Tier 2") -> Tier 2 | K211: =IFERROR(__xludf.DUMMYFUNCTION("""COMPUTED_VALUE"""),TRUE) -> TRUE
A212: =IFERROR(__xludf.DUMMYFUNCTION("""COMPUTED_VALUE"""),"Infestation") -> Infestation | B212: =IFERROR(__xludf.DUMMYFUNCTION("""COMPUTED_VALUE"""),"Bug") -> Bug | C212: =IFERROR(__xludf.DUMMYFUNCTION("""COMPUTED_VALUE"""),"Status") -> Status | D212: =IFERROR(__xludf.DUMMYFUNCTION("""COMPUTED_VALUE"""),"Scene x2") -> Scene x2 | E212: =IFERROR(__xludf.DUMMYFUNCTION("""COMPUTED_VALUE"""),"8, Ranged Blast 3, Hazard, Versatile") -> 8, Ranged Blast 3, Hazard, Versatile | F212: =IFERROR(__xludf.DUMMYFUNCTION("""COMPUTED_VALUE"""),"--") -> -- | G212: =IFERROR(__xludf.DUMMYFUNCTION("""COMPUTED_VALUE"""),"--") -> -- | H212: =IFERROR(__xludf.DUMMYFUNCTION("""COMPUTED_VALUE"""),"All Spaces within the Range of this Attack have Infestation Hazards created in them. Infestation Hazards - Any Enemy who starts their Turn or moves through an Infestation Hazard has a penalty to Accuracy and Save Checks equal to your Tier Level until th"&"e end of their Turn") -> All Spaces within the Range of this Attack have Infestation Hazards created in them. Infestation Hazards - Any Enemy who starts their Turn or moves through an Infestation Hazard has a penalty to Accuracy and Save Checks equal to your Tier Level until the end of their Turn | I212: =IFERROR(__xludf.DUMMYFUNCTION("""COMPUTED_VALUE"""),"Same as the normal Effects but the Hazards are removed at the end of the Round. ") -> Same as the normal Effects but the Hazards are removed at the end of the Round. | J212: =IFERROR(__xludf.DUMMYFUNCTION("""COMPUTED_VALUE"""),"Tier 2") -> Tier 2 | K212: =IFERROR(__xludf.DUMMYFUNCTION("""COMPUTED_VALUE"""),TRUE) -> TRUE
A213: =IFERROR(__xludf.DUMMYFUNCTION("""COMPUTED_VALUE"""),"Insect Cleave") -> Insect Cleave | B213: =IFERROR(__xludf.DUMMYFUNCTION("""COMPUTED_VALUE"""),"Bug") -> Bug | C213: =IFERROR(__xludf.DUMMYFUNCTION("""COMPUTED_VALUE"""),"Physical") -> Physical | D213: =IFERROR(__xludf.DUMMYFUNCTION("""COMPUTED_VALUE"""),"EOT") -> EOT | E213: =IFERROR(__xludf.DUMMYFUNCTION("""COMPUTED_VALUE"""),"Melee, Pass or Close Blast 2") -> Melee, Pass or Close Blast 2 | F213: =IFERROR(__xludf.DUMMYFUNCTION("""COMPUTED_VALUE"""),5.0) -> 5 | G213: =IFERROR(__xludf.DUMMYFUNCTION("""COMPUTED_VALUE"""),6.0) -> 6 | H213: =IFERROR(__xludf.DUMMYFUNCTION("""COMPUTED_VALUE"""),"As a Full Action, or if the Target is Wounded, this Attack has the Smite Keyword.") -> As a Full Action, or if the Target is Wounded, this Attack has the Smite Keyword. | I213: =IFERROR(__xludf.DUMMYFUNCTION("""COMPUTED_VALUE"""),"--") -> -- | J213: =IFERROR(__xludf.DUMMYFUNCTION("""COMPUTED_VALUE"""),"Tier 1") -> Tier 1 | K213: =IFERROR(__xludf.DUMMYFUNCTION("""COMPUTED_VALUE"""),TRUE) -> TRUE
A214: =IFERROR(__xludf.DUMMYFUNCTION("""COMPUTED_VALUE"""),"Lance Stinger") -> Lance Stinger | B214: =IFERROR(__xludf.DUMMYFUNCTION("""COMPUTED_VALUE"""),"Bug") -> Bug | C214: =IFERROR(__xludf.DUMMYFUNCTION("""COMPUTED_VALUE"""),"Physical") -> Physical | D214: =IFERROR(__xludf.DUMMYFUNCTION("""COMPUTED_VALUE"""),"Scene x2") -> Scene x2 | E214: =IFERROR(__xludf.DUMMYFUNCTION("""COMPUTED_VALUE"""),"Melee, Full Action, Pass") -> Melee, Full Action, Pass | F214: =IFERROR(__xludf.DUMMYFUNCTION("""COMPUTED_VALUE"""),6.0) -> 6 | G214: =IFERROR(__xludf.DUMMYFUNCTION("""COMPUTED_VALUE"""),13.0) -> 13 | H214: =IFERROR(__xludf.DUMMYFUNCTION("""COMPUTED_VALUE"""),"Lance Stinger ignores any positive Defense Combat Stages of its Targets and cannot trigger Reactions.") -> Lance Stinger ignores any positive Defense Combat Stages of its Targets and cannot trigger Reactions. | I214: =IFERROR(__xludf.DUMMYFUNCTION("""COMPUTED_VALUE"""),"--") -> -- | J214: =IFERROR(__xludf.DUMMYFUNCTION("""COMPUTED_VALUE"""),"Tier 3") -> Tier 3 | K214: =IFERROR(__xludf.DUMMYFUNCTION("""COMPUTED_VALUE"""),TRUE) -> TRUE
A215: =IFERROR(__xludf.DUMMYFUNCTION("""COMPUTED_VALUE"""),"Leech Life") -> Leech Life | B215: =IFERROR(__xludf.DUMMYFUNCTION("""COMPUTED_VALUE"""),"Bug") -> Bug | C215: =IFERROR(__xludf.DUMMYFUNCTION("""COMPUTED_VALUE"""),"Physical") -> Physical | D215: =IFERROR(__xludf.DUMMYFUNCTION("""COMPUTED_VALUE"""),"Scene x2") -> Scene x2 | E215: =IFERROR(__xludf.DUMMYFUNCTION("""COMPUTED_VALUE"""),"4, 1 Target") -> 4, 1 Target | F215: =IFERROR(__xludf.DUMMYFUNCTION("""COMPUTED_VALUE"""),5.0) -> 5 | G215: =IFERROR(__xludf.DUMMYFUNCTION("""COMPUTED_VALUE"""),8.0) -> 8 | H215: =IFERROR(__xludf.DUMMYFUNCTION("""COMPUTED_VALUE"""),"Drain. ") -> Drain. | I215: =IFERROR(__xludf.DUMMYFUNCTION("""COMPUTED_VALUE"""),"--") -> -- | J215: =IFERROR(__xludf.DUMMYFUNCTION("""COMPUTED_VALUE"""),"Tier 2") -> Tier 2 | K215: =IFERROR(__xludf.DUMMYFUNCTION("""COMPUTED_VALUE"""),TRUE) -> TRUE
A216: =IFERROR(__xludf.DUMMYFUNCTION("""COMPUTED_VALUE"""),"Locust Swarm") -> Locust Swarm | B216: =IFERROR(__xludf.DUMMYFUNCTION("""COMPUTED_VALUE"""),"Bug") -> Bug | C216: =IFERROR(__xludf.DUMMYFUNCTION("""COMPUTED_VALUE"""),"Status") -> Status | D216: =IFERROR(__xludf.DUMMYFUNCTION("""COMPUTED_VALUE"""),"Scene x2") -> Scene x2 | E216: =IFERROR(__xludf.DUMMYFUNCTION("""COMPUTED_VALUE"""),"Field, Versatile") -> Field, Versatile | F216: =IFERROR(__xludf.DUMMYFUNCTION("""COMPUTED_VALUE"""),"--") -> -- | G216: =IFERROR(__xludf.DUMMYFUNCTION("""COMPUTED_VALUE"""),"--") -> -- | H216: =IFERROR(__xludf.DUMMYFUNCTION("""COMPUTED_VALUE"""),"The Field becomes Swarmed for the next 5 Rounds. While the Field is Swarmed, non Bug Type Enemies lose a Tick of Hit Points at the start of their Turn and Bug Type Pokemon gain a Tick of Temporary Hit Points at the start of their Turn.") -> The Field becomes Swarmed for the next 5 Rounds. While the Field is Swarmed, non Bug Type Enemies lose a Tick of Hit Points at the start of their Turn and Bug Type Pokemon gain a Tick of Temporary Hit Points at the start of their Turn. | I216: =IFERROR(__xludf.DUMMYFUNCTION("""COMPUTED_VALUE"""),"Same as the normal Effect, but at the end of the Round, roll a Luck Check and with an 8 or less, the Field is no longer affected by this Attack.") -> Same as the normal Effect, but at the end of the Round, roll a Luck Check and with an 8 or less, the Field is no longer affected by this Attack. | J216: =IFERROR(__xludf.DUMMYFUNCTION("""COMPUTED_VALUE"""),"Tier 2") -> Tier 2 | K216: =IFERROR(__xludf.DUMMYFUNCTION("""COMPUTED_VALUE"""),TRUE) -> TRUE
A217: =IFERROR(__xludf.DUMMYFUNCTION("""COMPUTED_VALUE"""),"Lunge") -> Lunge | B217: =IFERROR(__xludf.DUMMYFUNCTION("""COMPUTED_VALUE"""),"Bug") -> Bug | C217: =IFERROR(__xludf.DUMMYFUNCTION("""COMPUTED_VALUE"""),"Physical") -> Physical | D217: =IFERROR(__xludf.DUMMYFUNCTION("""COMPUTED_VALUE"""),"EOT") -> EOT | E217: =IFERROR(__xludf.DUMMYFUNCTION("""COMPUTED_VALUE"""),"Melee, 1 Target, Dash") -> Melee, 1 Target, Dash | F217: =IFERROR(__xludf.DUMMYFUNCTION("""COMPUTED_VALUE"""),3.0) -> 3 | G217: =IFERROR(__xludf.DUMMYFUNCTION("""COMPUTED_VALUE"""),8.0) -> 8 | H217: =IFERROR(__xludf.DUMMYFUNCTION("""COMPUTED_VALUE"""),"Lunge gains the Sureshot Keyword if the Target is Slowed, Trapped or Vulnerable or if the Dash Keyword is Activated.") -> Lunge gains the Sureshot Keyword if the Target is Slowed, Trapped or Vulnerable or if the Dash Keyword is Activated. | I217: =IFERROR(__xludf.DUMMYFUNCTION("""COMPUTED_VALUE"""),"--") -> -- | J217: =IFERROR(__xludf.DUMMYFUNCTION("""COMPUTED_VALUE"""),"Tier 2") -> Tier 2 | K217: =IFERROR(__xludf.DUMMYFUNCTION("""COMPUTED_VALUE"""),TRUE) -> TRUE
A218: =IFERROR(__xludf.DUMMYFUNCTION("""COMPUTED_VALUE"""),"Megahorn") -> Megahorn | B218: =IFERROR(__xludf.DUMMYFUNCTION("""COMPUTED_VALUE"""),"Bug") -> Bug | C218: =IFERROR(__xludf.DUMMYFUNCTION("""COMPUTED_VALUE"""),"Physical") -> Physical | D218: =IFERROR(__xludf.DUMMYFUNCTION("""COMPUTED_VALUE"""),"Scene x2") -> Scene x2 | E218: =IFERROR(__xludf.DUMMYFUNCTION("""COMPUTED_VALUE"""),"Melee, 1 Target") -> Melee, 1 Target | F218: =IFERROR(__xludf.DUMMYFUNCTION("""COMPUTED_VALUE"""),4.0) -> 4 | G218: =IFERROR(__xludf.DUMMYFUNCTION("""COMPUTED_VALUE"""),12.0) -> 12 | H218: =IFERROR(__xludf.DUMMYFUNCTION("""COMPUTED_VALUE"""),"The Target loses -1 CS in Defense. If they already have negative CS in Defense, they also become Vulnerable against Melee Attacks until the end of the next Round.") -> The Target loses -1 CS in Defense. If they already have negative CS in Defense, they also become Vulnerable against Melee Attacks until the end of the next Round. | I218: =IFERROR(__xludf.DUMMYFUNCTION("""COMPUTED_VALUE"""),"--") -> -- | J218: =IFERROR(__xludf.DUMMYFUNCTION("""COMPUTED_VALUE"""),"Tier 3") -> Tier 3 | K218: =IFERROR(__xludf.DUMMYFUNCTION("""COMPUTED_VALUE"""),TRUE) -> TRUE
A219: =IFERROR(__xludf.DUMMYFUNCTION("""COMPUTED_VALUE"""),"Pheromone Haze") -> Pheromone Haze | B219: =IFERROR(__xludf.DUMMYFUNCTION("""COMPUTED_VALUE"""),"Bug") -> Bug | C219: =IFERROR(__xludf.DUMMYFUNCTION("""COMPUTED_VALUE"""),"Status") -> Status | D219: =IFERROR(__xludf.DUMMYFUNCTION("""COMPUTED_VALUE"""),"Scene x2") -> Scene x2 | E219: =IFERROR(__xludf.DUMMYFUNCTION("""COMPUTED_VALUE"""),"Blessing, Versatile") -> Blessing, Versatile | F219: =IFERROR(__xludf.DUMMYFUNCTION("""COMPUTED_VALUE"""),"--") -> -- | G219: =IFERROR(__xludf.DUMMYFUNCTION("""COMPUTED_VALUE"""),"--") -> -- | H219: =IFERROR(__xludf.DUMMYFUNCTION("""COMPUTED_VALUE"""),"Blessing - Any user affected by Pheromone Haze may activate it as a Free Action when using a Bug Type Damaging Attack to grant it the Smite Keyword. If the Attack hits, it hits, it is also increased by one damage step. (Max 1.5x Effectiveness). Pheromone "&"Haze may be Activated 3 times and then disappears. ") -> Blessing - Any user affected by Pheromone Haze may activate it as a Free Action when using a Bug Type Damaging Attack to grant it the Smite Keyword. If the Attack hits, it hits, it is also increased by one damage step. (Max 1.5x Effectiveness). Pheromone Haze may be Activated 3 times and then disappears. | I219: =IFERROR(__xludf.DUMMYFUNCTION("""COMPUTED_VALUE"""),"Same as the normal Effect, but it only has 1 Activation.") -> Same as the normal Effect, but it only has 1 Activation. | J219: =IFERROR(__xludf.DUMMYFUNCTION("""COMPUTED_VALUE"""),"Tier 2") -> Tier 2 | K219: =IFERROR(__xludf.DUMMYFUNCTION("""COMPUTED_VALUE"""),TRUE) -> TRUE
A220: =IFERROR(__xludf.DUMMYFUNCTION("""COMPUTED_VALUE"""),"Pheromone Spray") -> Pheromone Spray | B220: =IFERROR(__xludf.DUMMYFUNCTION("""COMPUTED_VALUE"""),"Bug") -> Bug | C220: =IFERROR(__xludf.DUMMYFUNCTION("""COMPUTED_VALUE"""),"Special") -> Special | D220: =IFERROR(__xludf.DUMMYFUNCTION("""COMPUTED_VALUE"""),"EOT") -> EOT | E220: =IFERROR(__xludf.DUMMYFUNCTION("""COMPUTED_VALUE"""),"Close Blast 2") -> Close Blast 2 | F220: =IFERROR(__xludf.DUMMYFUNCTION("""COMPUTED_VALUE"""),5.0) -> 5 | G220: =IFERROR(__xludf.DUMMYFUNCTION("""COMPUTED_VALUE"""),4.0) -> 4 | H220: =IFERROR(__xludf.DUMMYFUNCTION("""COMPUTED_VALUE"""),"One Target becomes Marked with a Haze Mark. Attacks against Enemies with a Haze Mark have a bonus to Effect Ranges equal to your Tier Level. When an Effect Range Triggers against an Enemy with a Haze Mark, the Haze Mark is removed. Spirit Surge") -> One Target becomes Marked with a Haze Mark. Attacks against Enemies with a Haze Mark have a bonus to Effect Ranges equal to your Tier Level. When an Effect Range Triggers against an Enemy with a Haze Mark, the Haze Mark is removed. Spirit Surge | I220: =IFERROR(__xludf.DUMMYFUNCTION("""COMPUTED_VALUE"""),"--") -> -- | J220: =IFERROR(__xludf.DUMMYFUNCTION("""COMPUTED_VALUE"""),"Tier 1") -> Tier 1 | K220: =IFERROR(__xludf.DUMMYFUNCTION("""COMPUTED_VALUE"""),TRUE) -> TRUE
A221: =IFERROR(__xludf.DUMMYFUNCTION("""COMPUTED_VALUE"""),"Pin Missile") -> Pin Missile | B221: =IFERROR(__xludf.DUMMYFUNCTION("""COMPUTED_VALUE"""),"Bug") -> Bug | C221: =IFERROR(__xludf.DUMMYFUNCTION("""COMPUTED_VALUE"""),"Physical") -> Physical | D221: =IFERROR(__xludf.DUMMYFUNCTION("""COMPUTED_VALUE"""),"EOT") -> EOT | E221: =IFERROR(__xludf.DUMMYFUNCTION("""COMPUTED_VALUE"""),"6, 1 Target") -> 6, 1 Target | F221: =IFERROR(__xludf.DUMMYFUNCTION("""COMPUTED_VALUE"""),5.0) -> 5 | G221: =IFERROR(__xludf.DUMMYFUNCTION("""COMPUTED_VALUE"""),4.0) -> 4 | H221: =IFERROR(__xludf.DUMMYFUNCTION("""COMPUTED_VALUE"""),"If Pin Missile hits at least 4 times, the Target becomes Wounded. Five Strike") -> If Pin Missile hits at least 4 times, the Target becomes Wounded. Five Strike | I221: =IFERROR(__xludf.DUMMYFUNCTION("""COMPUTED_VALUE"""),"--") -> -- | J221: =IFERROR(__xludf.DUMMYFUNCTION("""COMPUTED_VALUE"""),"Tier 1") -> Tier 1 | K221: =IFERROR(__xludf.DUMMYFUNCTION("""COMPUTED_VALUE"""),TRUE) -> TRUE
A222: =IFERROR(__xludf.DUMMYFUNCTION("""COMPUTED_VALUE"""),"Pollen Puff") -> Pollen Puff | B222: =IFERROR(__xludf.DUMMYFUNCTION("""COMPUTED_VALUE"""),"Bug") -> Bug | C222: =IFERROR(__xludf.DUMMYFUNCTION("""COMPUTED_VALUE"""),"Special") -> Special | D222: =IFERROR(__xludf.DUMMYFUNCTION("""COMPUTED_VALUE"""),"EOT") -> EOT | E222: =IFERROR(__xludf.DUMMYFUNCTION("""COMPUTED_VALUE"""),"6, 1 Target") -> 6, 1 Target | F222: =IFERROR(__xludf.DUMMYFUNCTION("""COMPUTED_VALUE"""),4.0) -> 4 | G222: =IFERROR(__xludf.DUMMYFUNCTION("""COMPUTED_VALUE"""),8.0) -> 8 | H222: =IFERROR(__xludf.DUMMYFUNCTION("""COMPUTED_VALUE"""),"If Pollen Puff targets an Ally instead of dealing damage, they restore 2 Ticks of Hit Points or Temporary Hit Points.") -> If Pollen Puff targets an Ally instead of dealing damage, they restore 2 Ticks of Hit Points or Temporary Hit Points. | I222: =IFERROR(__xludf.DUMMYFUNCTION("""COMPUTED_VALUE"""),"--") -> -- | J222: =IFERROR(__xludf.DUMMYFUNCTION("""COMPUTED_VALUE"""),"Tier 2") -> Tier 2 | K222: =IFERROR(__xludf.DUMMYFUNCTION("""COMPUTED_VALUE"""),TRUE) -> TRUE
A223: =IFERROR(__xludf.DUMMYFUNCTION("""COMPUTED_VALUE"""),"Powder") -> Powder | B223: =IFERROR(__xludf.DUMMYFUNCTION("""COMPUTED_VALUE"""),"Bug") -> Bug | C223: =IFERROR(__xludf.DUMMYFUNCTION("""COMPUTED_VALUE"""),"Status") -> Status | D223: =IFERROR(__xludf.DUMMYFUNCTION("""COMPUTED_VALUE"""),"Scene x2") -> Scene x2 | E223: =IFERROR(__xludf.DUMMYFUNCTION("""COMPUTED_VALUE"""),"6, Ranged Blast 3, Versatile") -> 6, Ranged Blast 3, Versatile | F223: =IFERROR(__xludf.DUMMYFUNCTION("""COMPUTED_VALUE"""),4.0) -> 4 | G223: =IFERROR(__xludf.DUMMYFUNCTION("""COMPUTED_VALUE"""),"--") -> -- | H223: =IFERROR(__xludf.DUMMYFUNCTION("""COMPUTED_VALUE"""),"The Target gains a Flammable Coat. Whenever a Combatant with a Flammable Coat is hit with a 1 Target Ranged Damaging Attack, the Attacker may expend the Coat. Once expended, a Burst 2 explosion occurs originating from the Enemy with the Coat and all Comba"&"tants within this Range are also hit with the Triggering Attack. ") -> The Target gains a Flammable Coat. Whenever a Combatant with a Flammable Coat is hit with a 1 Target Ranged Damaging Attack, the Attacker may expend the Coat. Once expended, a Burst 2 explosion occurs originating from the Enemy with the Coat and all Combatants within this Range are also hit with the Triggering Attack. | I223: =IFERROR(__xludf.DUMMYFUNCTION("""COMPUTED_VALUE"""),"Same as the normal Effects, but the Range is changed to 3, 1 Target and the explosion is a Burst 1 instead.") -> Same as the normal Effects, but the Range is changed to 3, 1 Target and the explosion is a Burst 1 instead. | J223: =IFERROR(__xludf.DUMMYFUNCTION("""COMPUTED_VALUE"""),"Tier 2") -> Tier 2 | K223: =IFERROR(__xludf.DUMMYFUNCTION("""COMPUTED_VALUE"""),TRUE) -> TRUE
A224: =IFERROR(__xludf.DUMMYFUNCTION("""COMPUTED_VALUE"""),"Powder Storm") -> Powder Storm | B224: =IFERROR(__xludf.DUMMYFUNCTION("""COMPUTED_VALUE"""),"Bug") -> Bug | C224: =IFERROR(__xludf.DUMMYFUNCTION("""COMPUTED_VALUE"""),"Special") -> Special | D224: =IFERROR(__xludf.DUMMYFUNCTION("""COMPUTED_VALUE"""),"Scene") -> Scene | E224: =IFERROR(__xludf.DUMMYFUNCTION("""COMPUTED_VALUE"""),"Close Blast 3, Full Action, Reckless") -> Close Blast 3, Full Action, Reckless | F224: =IFERROR(__xludf.DUMMYFUNCTION("""COMPUTED_VALUE"""),6.0) -> 6 | G224: =IFERROR(__xludf.DUMMYFUNCTION("""COMPUTED_VALUE"""),13.0) -> 13 | H224: =IFERROR(__xludf.DUMMYFUNCTION("""COMPUTED_VALUE"""),"After Damage Calculations, lower the Offensive Stat used for this Attack by -2 CS. Smite") -> After Damage Calculations, lower the Offensive Stat used for this Attack by -2 CS. Smite | I224: =IFERROR(__xludf.DUMMYFUNCTION("""COMPUTED_VALUE"""),"--") -> -- | J224: =IFERROR(__xludf.DUMMYFUNCTION("""COMPUTED_VALUE"""),"Tier 3") -> Tier 3 | K224: =IFERROR(__xludf.DUMMYFUNCTION("""COMPUTED_VALUE"""),TRUE) -> TRUE
A225: =IFERROR(__xludf.DUMMYFUNCTION("""COMPUTED_VALUE"""),"Quiver Dance") -> Quiver Dance | B225: =IFERROR(__xludf.DUMMYFUNCTION("""COMPUTED_VALUE"""),"Bug") -> Bug | C225: =IFERROR(__xludf.DUMMYFUNCTION("""COMPUTED_VALUE"""),"Status") -> Status | D225: =IFERROR(__xludf.DUMMYFUNCTION("""COMPUTED_VALUE"""),"Scene x2") -> Scene x2 | E225: =IFERROR(__xludf.DUMMYFUNCTION("""COMPUTED_VALUE"""),"Self, Versatile") -> Self, Versatile | F225: =IFERROR(__xludf.DUMMYFUNCTION("""COMPUTED_VALUE"""),"--") -> -- | G225: =IFERROR(__xludf.DUMMYFUNCTION("""COMPUTED_VALUE"""),"--") -> -- | H225: =IFERROR(__xludf.DUMMYFUNCTION("""COMPUTED_VALUE"""),"The user gains +2 CS in Special Attack, Special Defense and Speed.") -> The user gains +2 CS in Special Attack, Special Defense and Speed. | I225: =IFERROR(__xludf.DUMMYFUNCTION("""COMPUTED_VALUE"""),"Choose Special Attack, Special Defense or Speed to gain +1 CS in.") -> Choose Special Attack, Special Defense or Speed to gain +1 CS in. | J225: =IFERROR(__xludf.DUMMYFUNCTION("""COMPUTED_VALUE"""),"Tier 2") -> Tier 2 | K225: =IFERROR(__xludf.DUMMYFUNCTION("""COMPUTED_VALUE"""),TRUE) -> TRUE
A226: =IFERROR(__xludf.DUMMYFUNCTION("""COMPUTED_VALUE"""),"Rage Powder") -> Rage Powder | B226: =IFERROR(__xludf.DUMMYFUNCTION("""COMPUTED_VALUE"""),"Bug") -> Bug | C226: =IFERROR(__xludf.DUMMYFUNCTION("""COMPUTED_VALUE"""),"Status") -> Status | D226: =IFERROR(__xludf.DUMMYFUNCTION("""COMPUTED_VALUE"""),"Scene x2") -> Scene x2 | E226: =IFERROR(__xludf.DUMMYFUNCTION("""COMPUTED_VALUE"""),"Burst 1 or Close Blast 2; Versatile") -> Burst 1 or Close Blast 2; Versatile | F226: =IFERROR(__xludf.DUMMYFUNCTION("""COMPUTED_VALUE"""),5.0) -> 5 | G226: =IFERROR(__xludf.DUMMYFUNCTION("""COMPUTED_VALUE"""),"--") -> -- | H226: =IFERROR(__xludf.DUMMYFUNCTION("""COMPUTED_VALUE"""),"All Targets hit by Rage Powder become Provoked by the user until the end of their next Turn. On a roll of 15+, they also become Enraged. Friendly.") -> All Targets hit by Rage Powder become Provoked by the user until the end of their next Turn. On a roll of 15+, they also become Enraged. Friendly. | I226: =IFERROR(__xludf.DUMMYFUNCTION("""COMPUTED_VALUE"""),"All Spaces in the Range of this Attack gain Powder Hazards until the end of the Round. Enemies that Trigger this Hazard become Provoked by their nearest Enemy Combatant that they can legally Target. Powder Hazard - Whenever an Enemy passes through or en"&"ds their turn on a Powder Hazard the Effect listed is applied. Users with the Breathless Capability ignore this Hazard.") -> All Spaces in the Range of this Attack gain Powder Hazards until the end of the Round. Enemies that Trigger this Hazard become Provoked by their nearest Enemy Combatant that they can legally Target. Powder Hazard - Whenever an Enemy passes through or ends their turn on a Powder Hazard the Effect listed is applied. Users with the Breathless Capability ignore this Hazard. | J226: =IFERROR(__xludf.DUMMYFUNCTION("""COMPUTED_VALUE"""),"Tier 2") -> Tier 2 | K226: =IFERROR(__xludf.DUMMYFUNCTION("""COMPUTED_VALUE"""),TRUE) -> TRUE
A227: =IFERROR(__xludf.DUMMYFUNCTION("""COMPUTED_VALUE"""),"Skitter Dance") -> Skitter Dance | B227: =IFERROR(__xludf.DUMMYFUNCTION("""COMPUTED_VALUE"""),"Bug") -> Bug | C227: =IFERROR(__xludf.DUMMYFUNCTION("""COMPUTED_VALUE"""),"Status") -> Status | D227: =IFERROR(__xludf.DUMMYFUNCTION("""COMPUTED_VALUE"""),"At-Will") -> At-Will | E227: =IFERROR(__xludf.DUMMYFUNCTION("""COMPUTED_VALUE"""),"Self, Movement Action") -> Self, Movement Action | F227: =IFERROR(__xludf.DUMMYFUNCTION("""COMPUTED_VALUE"""),"--") -> -- | G227: =IFERROR(__xludf.DUMMYFUNCTION("""COMPUTED_VALUE"""),"--") -> -- | H227: =IFERROR(__xludf.DUMMYFUNCTION("""COMPUTED_VALUE"""),"The user’s next Melee Attack this Turn ignores Speed Evasion or they gain +1 Evasion.") -> The user’s next Melee Attack this Turn ignores Speed Evasion or they gain +1 Evasion. | I227: =IFERROR(__xludf.DUMMYFUNCTION("""COMPUTED_VALUE"""),"--") -> -- | J227: =IFERROR(__xludf.DUMMYFUNCTION("""COMPUTED_VALUE"""),"Tier 1") -> Tier 1 | K227: =IFERROR(__xludf.DUMMYFUNCTION("""COMPUTED_VALUE"""),TRUE) -> TRUE
A228: =IFERROR(__xludf.DUMMYFUNCTION("""COMPUTED_VALUE"""),"Skitter Smack") -> Skitter Smack | B228: =IFERROR(__xludf.DUMMYFUNCTION("""COMPUTED_VALUE"""),"Bug") -> Bug | C228: =IFERROR(__xludf.DUMMYFUNCTION("""COMPUTED_VALUE"""),"Physical") -> Physical | D228: =IFERROR(__xludf.DUMMYFUNCTION("""COMPUTED_VALUE"""),"EOT") -> EOT | E228: =IFERROR(__xludf.DUMMYFUNCTION("""COMPUTED_VALUE"""),"Melee, 1 Target") -> Melee, 1 Target | F228: =IFERROR(__xludf.DUMMYFUNCTION("""COMPUTED_VALUE"""),2.0) -> 2 | G228: =IFERROR(__xludf.DUMMYFUNCTION("""COMPUTED_VALUE"""),7.0) -> 7 | H228: =IFERROR(__xludf.DUMMYFUNCTION("""COMPUTED_VALUE"""),"The user may declare the usage of Skitter Smack at the start of their Turn. When Moving this turn, they do not provoke Attacks of Opportunity and do not trigger Reactions.") -> The user may declare the usage of Skitter Smack at the start of their Turn. When Moving this turn, they do not provoke Attacks of Opportunity and do not trigger Reactions. | I228: =IFERROR(__xludf.DUMMYFUNCTION("""COMPUTED_VALUE"""),"--") -> -- | J228: =IFERROR(__xludf.DUMMYFUNCTION("""COMPUTED_VALUE"""),"Tier 1") -> Tier 1 | K228: =IFERROR(__xludf.DUMMYFUNCTION("""COMPUTED_VALUE"""),TRUE) -> TRUE
A229: =IFERROR(__xludf.DUMMYFUNCTION("""COMPUTED_VALUE"""),"Silk Trap") -> Silk Trap | B229: =IFERROR(__xludf.DUMMYFUNCTION("""COMPUTED_VALUE"""),"Bug") -> Bug | C229: =IFERROR(__xludf.DUMMYFUNCTION("""COMPUTED_VALUE"""),"Status") -> Status | D229: =IFERROR(__xludf.DUMMYFUNCTION("""COMPUTED_VALUE"""),"Scene") -> Scene | E229: =IFERROR(__xludf.DUMMYFUNCTION("""COMPUTED_VALUE"""),"4, 1 Target, Versatile") -> 4, 1 Target, Versatile | F229: =IFERROR(__xludf.DUMMYFUNCTION("""COMPUTED_VALUE"""),5.0) -> 5 | G229: =IFERROR(__xludf.DUMMYFUNCTION("""COMPUTED_VALUE"""),"--") -> -- | H229: =IFERROR(__xludf.DUMMYFUNCTION("""COMPUTED_VALUE"""),"The Target becomes Slowed. While Slowed this way, their Melee Attacks are resisted an additional Damage step. If this Attack misses, they instead are Slowed without any additional effects. Spirit Surge") -> The Target becomes Slowed. While Slowed this way, their Melee Attacks are resisted an additional Damage step. If this Attack misses, they instead are Slowed without any additional effects. Spirit Surge | I229: =IFERROR(__xludf.DUMMYFUNCTION("""COMPUTED_VALUE"""),"--") -> -- | J229: =IFERROR(__xludf.DUMMYFUNCTION("""COMPUTED_VALUE"""),"Tier 3") -> Tier 3 | K229: =IFERROR(__xludf.DUMMYFUNCTION("""COMPUTED_VALUE"""),FALSE) -> FALSE
A230: =IFERROR(__xludf.DUMMYFUNCTION("""COMPUTED_VALUE"""),"Silk Weave") -> Silk Weave | B230: =IFERROR(__xludf.DUMMYFUNCTION("""COMPUTED_VALUE"""),"Bug") -> Bug | C230: =IFERROR(__xludf.DUMMYFUNCTION("""COMPUTED_VALUE"""),"Status") -> Status | D230: =IFERROR(__xludf.DUMMYFUNCTION("""COMPUTED_VALUE"""),"Scene x2") -> Scene x2 | E230: =IFERROR(__xludf.DUMMYFUNCTION("""COMPUTED_VALUE"""),"4m, 1 Target or Self; Coat") -> 4m, 1 Target or Self; Coat | F230: =IFERROR(__xludf.DUMMYFUNCTION("""COMPUTED_VALUE"""),"--") -> -- | G230: =IFERROR(__xludf.DUMMYFUNCTION("""COMPUTED_VALUE"""),"--") -> -- | H230: =IFERROR(__xludf.DUMMYFUNCTION("""COMPUTED_VALUE"""),"The Target gains a Silk Coat. The Target may expend a Silk Coat to become cured of a Physical Affliction or to reset a Stat to its Default Value") -> The Target gains a Silk Coat. The Target may expend a Silk Coat to become cured of a Physical Affliction or to reset a Stat to its Default Value | I230: =IFERROR(__xludf.DUMMYFUNCTION("""COMPUTED_VALUE"""),"--") -> -- | J230: =IFERROR(__xludf.DUMMYFUNCTION("""COMPUTED_VALUE"""),"Tier 2") -> Tier 2 | K230: =IFERROR(__xludf.DUMMYFUNCTION("""COMPUTED_VALUE"""),TRUE) -> TRUE
